Workbook
Name application_status_current: Lookup_Lists!$C$5:$C$12
Name bond_issuer_type: Lookup_Lists!$I$5:$I$7
Name construction_type: Lookup_Lists!$E$5:$E$9
Name predicted_advance_flag: Lookup_Lists!$O$5:$O$7
Name predicted_next_path: Lookup_Lists!$M$5:$M$11
Name predicted_next_status: Lookup_Lists!$K$5:$K$12
Name target_population: Lookup_Lists!$G$5:$G$8
Name yes_no: Lookup_Lists!$A$5:$A$6

Sheet Read_Me
A1: Texas 2025 4% + Tax-Exempt Bond Simulator Template
A3: Purpose | B3: This workbook is a starter input template for a Texas 2025 4% + tax-exempt bond rules engine.
A4: How to use | B4: 1) Paste the latest status-log universe into Applicant_List. 2) Fill the orange/purple manual QAP fields. 3) Enter one test project in Hypothetical_Project. 4) Have the Python engine write results to Rules_Output or the engine output columns.
A5: Color key | B5: Blue font = manual input. Black font = formulas / derived values. Gray fill = derived logic. Light red fill = engine outputs. Orange/purple sections = manual QAP and site rule inputs.
A6: Required fields | B6: Columns marked Req in Lookup_Lists should be completed before running the simulator.
A7: Derived flags | B7: all_manual_boxes_checked_flag and project_ready_now_flag are formula-driven helper fields. They are intended as starter logic and can be refined as the Texas engine matures.
A8: Scope note | B8: This template is for a Texas pipeline/rules engine, not a California-style score-and-award allocator.
A10: Key tabs
A11: Applicant_List | B11: Main status-log universe plus added QAP/manual fields.
A12: Hypothetical_Project | B12: Single-row test project with same schema as Applicant_List.
A13: Rules_Output | B13: Output area for the simulator/decision engine.
A14: Lookup_Lists | B14: Dropdown values plus full field dictionary.
A16: New in this version | B16: Adds a queue-based funding allocation layer: projects are screened by the existing rules engine, sorted by reservation-date priority, and funded until the manual capacity assumption is exhausted.

Sheet Applicant_List
A1: Texas 2025 4% + Tax-Exempt Bond Simulator - 2026-02-10 mapped status log
A2: Identity & Snapshot | K2: Current Public Process | R2: Project Characteristics | X2: Bond & Credit Structure | AI2: Manual QAP Thresholds | BB2: Site / Deconcentration | BJ2: Path Selection | BO2: Queue / Priority | BU2: Engine Outputs | CC2: Notes & Contacts
A3: snapshot_date | B3: application_source_log | C3: tdhca_number | D3: previous_tdhca_number | E3: development_name | F3: development_city | G3: development_county | H3: development_region | I3: development_address | J3: zip_code | K3: full_application_submission_date | L3: application_status_current | M3: board_meeting_date_current | N3: determination_notice_issuance_date_current | O3: bond_reservation_date_current | P3: bond_expiration_date_current | Q3: closed_date_current | R3: construction_type | S3: target_population | T3: total_units | U3: total_low_income_units | V3: scattered_site_flag | W3: existing_residential_development_flag | X3: bond_issuer | Y3: bond_issuer_type | Z3: bond_reservation_amount_requested | AA3: bond_amount_recommended | AB3: requested_htc_amount | AC3: recommended_htc_amount | AD3: requested_state_tax_credit_amount | AE3: recommended_state_tax_credit_amount | AF3: direct_loan_request_flag | AG3: property_tax_exemption_flag | AH3: pfc_structure_flag | AI3: site_control_valid_flag | AJ3: site_control_document_date | AK3: resolutions_complete_flag | AL3: local_approval_complete_flag | AM3: third_party_reports_complete_flag | AN3: esa_complete_flag | AO3: market_analysis_complete_flag | AP3: appraisal_complete_flag | AQ3: scr_complete_flag | AR3: feasibility_report_complete_flag | AS3: deficiency_notice_issued_flag | AT3: deficiency_notice_date | AU3: deficiency_response_due_date | AV3: deficiency_cleared_flag | AW3: deficiency_cleared_date | AX3: material_deficiency_flag | AY3: underwriting_complete_flag | AZ3: underwriting_pass_flag | BA3: financial_feasible_flag | BB3: deconcentration_compliant_flag | BC3: one_mile_rule_compliant_flag | BD3: two_mile_same_year_rule_relevant_flag | BE3: existing_lura_conflict_flag | BF3: rural_area_flag | BG3: urban_area_flag | BH3: qct_flag | BI3: high_opportunity_override_flag | BJ3: streamlined_eligible_flag | BK3: board_review_required_flag | BL3: chapter12_issue_flag | BM3: ready_for_determination_notice_flag | BN3: ready_for_board_flag | BO3: pipeline_entry_date | BP3: carryforward_from_prior_log_flag | BQ3: new_project_this_snapshot_flag | BR3: all_manual_boxes_checked_flag | BS3: project_ready_now_flag | BT3: pipeline_seniority_rank_manual | BU3: predicted_next_status | BV3: predicted_next_path | BW3: predicted_blocker_code | BX3: predicted_reason_1 | BY3: predicted_reason_2 | BZ3: predicted_reason_3 | CA3: predicted_relative_rank | CB3: predicted_advance_flag | CC3: notes | CD3: applicant_contact | CE3: applicant_phone | CF3: applicant_email | CG3: bond_issuer_contact | CH3: bond_issuer_phone
A4: 2026-02-10 | B4: 2026-02-10 | C4: 25427 | D4: 24426 | E4: Bay Terrace | F4: Baytown | G4: Harris | H4: 6 | I4: 1502 Nolan Road | J4: 77520 | K4: 45659 | L4: Closed | M4: 45757 | N4: 45834 | O4: 45670 | P4: 45850 | R4: Acq/Rehab | S4: General | T4: 130 | U4: 130 | X4: Southeast Texas HFC | Y4: Local HFC | Z4: 22500000 | AB4: 1300304 | AC4: 1285865 | AD4: 1250000 | AE4: 1250000 | AF4: N | AG4: N | AI4: Y | AK4: Y | AL4: Y | AM4: Y | AS4: N | AX4: N | AY4: Y | AZ4: Y | BA4: Y | BB4: Y | BC4: Y | BE4: N | BJ4: Y | BK4: N | BL4: N | BM4: Y | BN4: Y | BO4: 45659 | BP4: Y | BQ4: N | BR4: =IF(COUNTIF(AI4:BM4,"N")+COUNTBLANK(AI4:BM4)=0,"Y","N") | BS4: =IF(AND(BR4="Y",OR(L4="Submitted",L4="Under Review")),"Y",IF(L4="Closed","Y","N")) | BT4: 5 | BU4: =Rule_Flags!Q3 | BV4: =Rule_Flags!P3 | BW4: =IF(Rule_Flags!E3=1,"SITE_CONTROL",IF(Rule_Flags!F3=1,"APPROVALS",IF(Rule_Flags!G3=1,"REPORTS",IF(Rule_Flags!H3=1,"DEFICIENCY",IF(Rule_Flags!I3=1,"UNDERWRITING",IF(Rule_Flags!J3=1,"COMPLIANCE","")))))) | BX4: =IF(BW4="SITE_CONTROL","Site control missing or invalid",IF(BW4="APPROVALS","Required approvals or resolutions incomplete",IF(BW4="REPORTS","Required third-party reports incomplete",IF(BW4="DEFICIENCY","Unresolved deficiency or material deficiency",IF(BW4="UNDERWRITING","Underwriting / feasibility not passed",IF(BW4="COMPLIANCE","Deconcentration, one-mile, LURA, or Chapter 12 issue","Ready under current engine rules")))))) | BY4: =IF(BV4="Determination Notice","Streamlined + DN-ready assumptions satisfied",IF(BV4="Board","Board-required or board-ready assumptions satisfied","")) | BZ4: =IF(AND(BP4="Y",BQ4<>"Y"),"Carryforward project retains queue priority",IF(BQ4="Y","New project enters behind carryforward projects","")) | CA4: =_xludf.RANK.EQ(Rule_Flags!O3,Rule_Flags!$O$3:$O$402,0) | CB4: =IF(OR(BU4="Determination Notice Issued",BU4="Board",BU4="Closed"),"Y","N") | CD4: Steve Anderson | CE4: (650) 400-8553 | CF4: steve@anderson.org | CG4: Ron Williams | CH4: (281) 484-4663
A5: 2026-02-10 | B5: 2026-02-10 | C5: 25428 | D5: 24434 | E5: Independence Village | F5: Amarillo | G5: Randall | H5: 1 | I5: 4700 Virginia | J5: 79109 | K5: 45659 | L5: Withdrawn | M5: 45820 | O5: 45723 | P5: 45903 | R5: Acq/Rehab | S5: Elderly | T5: 150 | U5: 150 | X5: Panhandle Regional HFC | Y5: Local HFC | Z5: 25000000 | AB5: 1324312 | AD5: 463534 | AF5: N | AG5: N | AI5: Y | AK5: Y | AL5: Y | AM5: Y | AS5: N | AX5: N | AY5: Y | AZ5: Y | BA5: Y | BB5: Y | BC5: Y | BE5: N | BJ5: Y | BK5: N | BL5: N | BM5: Y | BN5: Y | BO5: 45659 | BP5: Y | BQ5: N | BR5: =IF(COUNTIF(AI5:BM5,"N")+COUNTBLANK(AI5:BM5)=0,"Y","N") | BS5: =IF(AND(BR5="Y",OR(L5="Submitted",L5="Under Review")),"Y",IF(L5="Closed","Y","N")) | BT5: 6 | BU5: =Rule_Flags!Q4 | BV5: =Rule_Flags!P4 | BW5: =IF(Rule_Flags!E4=1,"SITE_CONTROL",IF(Rule_Flags!F4=1,"APPROVALS",IF(Rule_Flags!G4=1,"REPORTS",IF(Rule_Flags!H4=1,"DEFICIENCY",IF(Rule_Flags!I4=1,"UNDERWRITING",IF(Rule_Flags!J4=1,"COMPLIANCE","")))))) | BX5: =IF(BW5="SITE_CONTROL","Site control missing or invalid",IF(BW5="APPROVALS","Required approvals or resolutions incomplete",IF(BW5="REPORTS","Required third-party reports incomplete",IF(BW5="DEFICIENCY","Unresolved deficiency or material deficiency",IF(BW5="UNDERWRITING","Underwriting / feasibility not passed",IF(BW5="COMPLIANCE","Deconcentration, one-mile, LURA, or Chapter 12 issue","Ready under current engine rules")))))) | BY5: =IF(BV5="Determination Notice","Streamlined + DN-ready assumptions satisfied",IF(BV5="Board","Board-required or board-ready assumptions satisfied","")) | BZ5: =IF(AND(BP5="Y",BQ5<>"Y"),"Carryforward project retains queue priority",IF(BQ5="Y","New project enters behind carryforward projects","")) | CA5: =_xludf.RANK.EQ(Rule_Flags!O4,Rule_Flags!$O$3:$O$402,0) | CB5: =IF(OR(BU5="Determination Notice Issued",BU5="Board",BU5="Closed"),"Y","N") | CD5: Rae Wilder | CE5: (805) 413-0672 | CF5: rachel.posthumus@ccinvest.com | CG5: Michael Carr | CH5: (806) 360-2060
A6: 2026-02-10 | B6: 2026-02-10 | C6: 25420 | E6: The Bloom at Lamar Square | F6: Austin | G6: Travis | H6: 7 | I6: 1326 & 1328 Lamar Square Drive | J6: 78704 | K6: 45659 | L6: Withdrawn | M6: 45757 | N6: 45880 | O6: 45880 | P6: 46060 | R6: New Construction | S6: Supportive Housing | T6: 58 | U6: 58 | X6: TSAHC | Y6: Other | Z6: 16500000 | AB6: 903744 | AC6: 903744 | AD6: 900000 | AF6: N | AG6: Y | AI6: Y | AK6: Y | AL6: Y | AM6: Y | AS6: N | AX6: N | AY6: Y | AZ6: Y | BA6: Y | BB6: Y | BC6: Y | BE6: N | BJ6: Y | BK6: N | BL6: N | BM6: Y | BN6: Y | BO6: 45659 | BP6: Y | BQ6: N | BR6: =IF(COUNTIF(AI6:BM6,"N")+COUNTBLANK(AI6:BM6)=0,"Y","N") | BS6: =IF(AND(BR6="Y",OR(L6="Submitted",L6="Under Review")),"Y",IF(L6="Closed","Y","N")) | BT6: 4 | BU6: =Rule_Flags!Q5 | BV6: =Rule_Flags!P5 | BW6: =IF(Rule_Flags!E5=1,"SITE_CONTROL",IF(Rule_Flags!F5=1,"APPROVALS",IF(Rule_Flags!G5=1,"REPORTS",IF(Rule_Flags!H5=1,"DEFICIENCY",IF(Rule_Flags!I5=1,"UNDERWRITING",IF(Rule_Flags!J5=1,"COMPLIANCE","")))))) | BX6: =IF(BW6="SITE_CONTROL","Site control missing or invalid",IF(BW6="APPROVALS","Required approvals or resolutions incomplete",IF(BW6="REPORTS","Required third-party reports incomplete",IF(BW6="DEFICIENCY","Unresolved deficiency or material deficiency",IF(BW6="UNDERWRITING","Underwriting / feasibility not passed",IF(BW6="COMPLIANCE","Deconcentration, one-mile, LURA, or Chapter 12 issue","Ready under current engine rules")))))) | BY6: =IF(BV6="Determination Notice","Streamlined + DN-ready assumptions satisfied",IF(BV6="Board","Board-required or board-ready assumptions satisfied","")) | BZ6: =IF(AND(BP6="Y",BQ6<>"Y"),"Carryforward project retains queue priority",IF(BQ6="Y","New project enters behind carryforward projects","")) | CA6: =_xludf.RANK.EQ(Rule_Flags!O5,Rule_Flags!$O$3:$O$402,0) | CB6: =IF(OR(BU6="Determination Notice Issued",BU6="Board",BU6="Closed"),"Y","N") | CC6: construction_type mapped from raw 'NC' to 'New Construction'; property_tax_exemption normalized from 'Y (50%)' to 'Y' | CD6: Walter Moreau | CE6: (512) 610-4016 | CF6: walter.moreau@foundcom.org | CG6: David Danenfelzer | CH6: (512) 477-3562
A7: 2026-02-10 | B7: 2026-02-10 | C7: 25429 | E7: Huntington Place Senior Little Elm | F7: Little Elm | G7: Denton | H7: 3 | I7: NEQ Navo Road and Union Park Blvd | J7: 76227 | K7: 45663 | L7: Closed | M7: 45757 | N7: 45769 | O7: 45670 | P7: 45850 | R7: New Construction | S7: Elderly | T7: 198 | U7: 198 | X7: THF PFC | Y7: Other | Z7: 35000000 | AB7: 1987061 | AC7: 1987061 | AF7: N | AG7: Y | AH7: Y | AI7: Y | AK7: Y | AL7: Y | AM7: Y | AS7: N | AX7: N | AY7: Y | AZ7: Y | BA7: Y | BB7: Y | BC7: Y | BE7: N | BJ7: Y | BK7: N | BL7: N | BM7: Y | BN7: Y | BO7: 45663 | BP7: Y | BQ7: N | BR7: =IF(COUNTIF(AI7:BM7,"N")+COUNTBLANK(AI7:BM7)=0,"Y","N") | BS7: =IF(AND(BR7="Y",OR(L7="Submitted",L7="Under Review")),"Y",IF(L7="Closed","Y","N")) | BT7: 7 | BU7: =Rule_Flags!Q6 | BV7: =Rule_Flags!P6 | BW7: =IF(Rule_Flags!E6=1,"SITE_CONTROL",IF(Rule_Flags!F6=1,"APPROVALS",IF(Rule_Flags!G6=1,"REPORTS",IF(Rule_Flags!H6=1,"DEFICIENCY",IF(Rule_Flags!I6=1,"UNDERWRITING",IF(Rule_Flags!J6=1,"COMPLIANCE","")))))) | BX7: =IF(BW7="SITE_CONTROL","Site control missing or invalid",IF(BW7="APPROVALS","Required approvals or resolutions incomplete",IF(BW7="REPORTS","Required third-party reports incomplete",IF(BW7="DEFICIENCY","Unresolved deficiency or material deficiency",IF(BW7="UNDERWRITING","Underwriting / feasibility not passed",IF(BW7="COMPLIANCE","Deconcentration, one-mile, LURA, or Chapter 12 issue","Ready under current engine rules")))))) | BY7: =IF(BV7="Determination Notice","Streamlined + DN-ready assumptions satisfied",IF(BV7="Board","Board-required or board-ready assumptions satisfied","")) | BZ7: =IF(AND(BP7="Y",BQ7<>"Y"),"Carryforward project retains queue priority",IF(BQ7="Y","New project enters behind carryforward projects","")) | CA7: =_xludf.RANK.EQ(Rule_Flags!O6,Rule_Flags!$O$3:$O$402,0) | CB7: =IF(OR(BU7="Determination Notice Issued",BU7="Board",BU7="Closed"),"Y","N") | CC7: construction_type mapped from raw 'NC' to 'New Construction' | CD7: Ryan Combs | CE7: (512) 983-0422 | CF7: ryan@crossdevelopment.net | CG7: Jonathan Coreas | CH7: (830) 693-8100
A8: 2026-02-10 | B8: 2026-02-10 | C8: 25415 | D8: 8417 | E8: Seville Apartments | F8: Beaumont | G8: Jefferson | H8: 5 | I8: 4325 Crow Road | J8: 77706 | K8: 45665 | L8: Closed | M8: 45785 | N8: 45811 | O8: 45667 | P8: 45847 | R8: Acq/Rehab | S8: Elderly | T8: 90 | U8: 90 | X8: Jefferson County HFC | Y8: Local HFC | Z8: 10000000 | AB8: 645144 | AC8: 645144 | AF8: N | AG8: Y | AI8: Y | AK8: Y | AL8: Y | AM8: Y | AS8: N | AX8: N | AY8: Y | AZ8: Y | BA8: Y | BB8: Y | BC8: Y | BE8: N | BJ8: Y | BK8: N | BL8: N | BM8: Y | BN8: Y | BO8: 45665 | BP8: Y | BQ8: N | BR8: =IF(COUNTIF(AI8:BM8,"N")+COUNTBLANK(AI8:BM8)=0,"Y","N") | BS8: =IF(AND(BR8="Y",OR(L8="Submitted",L8="Under Review")),"Y",IF(L8="Closed","Y","N")) | BT8: 11 | BU8: =Rule_Flags!Q7 | BV8: =Rule_Flags!P7 | BW8: =IF(Rule_Flags!E7=1,"SITE_CONTROL",IF(Rule_Flags!F7=1,"APPROVALS",IF(Rule_Flags!G7=1,"REPORTS",IF(Rule_Flags!H7=1,"DEFICIENCY",IF(Rule_Flags!I7=1,"UNDERWRITING",IF(Rule_Flags!J7=1,"COMPLIANCE","")))))) | BX8: =IF(BW8="SITE_CONTROL","Site control missing or invalid",IF(BW8="APPROVALS","Required approvals or resolutions incomplete",IF(BW8="REPORTS","Required third-party reports incomplete",IF(BW8="DEFICIENCY","Unresolved deficiency or material deficiency",IF(BW8="UNDERWRITING","Underwriting / feasibility not passed",IF(BW8="COMPLIANCE","Deconcentration, one-mile, LURA, or Chapter 12 issue","Ready under current engine rules")))))) | BY8: =IF(BV8="Determination Notice","Streamlined + DN-ready assumptions satisfied",IF(BV8="Board","Board-required or board-ready assumptions satisfied","")) | BZ8: =IF(AND(BP8="Y",BQ8<>"Y"),"Carryforward project retains queue priority",IF(BQ8="Y","New project enters behind carryforward projects","")) | CA8: =_xludf.RANK.EQ(Rule_Flags!O7,Rule_Flags!$O$3:$O$402,0) | CB8: =IF(OR(BU8="Determination Notice Issued",BU8="Board",BU8="Closed"),"Y","N") | CD8: Andrew Bennett | CE8: (720) 749-3206 | CF8: abennett@steelellc.com | CG8: Jeff Branick | CH8: (409) 654-6730
A9: 2026-02-10 | B9: 2026-02-10 | C9: 25409 | D9: 060628 | E9: Lancaster Apartments | F9: Katy | G9: Harris | H9: 6 | I9: 20100 Park Row Boulevard | J9: 77449 | K9: 45665 | L9: Closed | M9: 45757 | N9: 45772 | O9: 45670 | P9: 45850 | R9: Acq/Rehab | S9: General | T9: 252 | U9: 252 | X9: HHA Fountainview PFC | Y9: Other | Z9: 30000000 | AB9: 1710060 | AC9: 1710060 | AD9: 350000 | AF9: N | AG9: Y | AH9: Y | AI9: Y | AK9: Y | AL9: Y | AM9: Y | AS9: N | AX9: N | AY9: Y | AZ9: Y | BA9: Y | BB9: Y | BC9: Y | BE9: N | BJ9: Y | BK9: N | BL9: N | BM9: Y | BN9: Y | BO9: 45665 | BP9: Y | BQ9: N | BR9: =IF(COUNTIF(AI9:BM9,"N")+COUNTBLANK(AI9:BM9)=0,"Y","N") | BS9: =IF(AND(BR9="Y",OR(L9="Submitted",L9="Under Review")),"Y",IF(L9="Closed","Y","N")) | BT9: 8 | BU9: =Rule_Flags!Q8 | BV9: =Rule_Flags!P8 | BW9: =IF(Rule_Flags!E8=1,"SITE_CONTROL",IF(Rule_Flags!F8=1,"APPROVALS",IF(Rule_Flags!G8=1,"REPORTS",IF(Rule_Flags!H8=1,"DEFICIENCY",IF(Rule_Flags!I8=1,"UNDERWRITING",IF(Rule_Flags!J8=1,"COMPLIANCE","")))))) | BX9: =IF(BW9="SITE_CONTROL","Site control missing or invalid",IF(BW9="APPROVALS","Required approvals or resolutions incomplete",IF(BW9="REPORTS","Required third-party reports incomplete",IF(BW9="DEFICIENCY","Unresolved deficiency or material deficiency",IF(BW9="UNDERWRITING","Underwriting / feasibility not passed",IF(BW9="COMPLIANCE","Deconcentration, one-mile, LURA, or Chapter 12 issue","Ready under current engine rules")))))) | BY9: =IF(BV9="Determination Notice","Streamlined + DN-ready assumptions satisfied",IF(BV9="Board","Board-required or board-ready assumptions satisfied","")) | BZ9: =IF(AND(BP9="Y",BQ9<>"Y"),"Carryforward project retains queue priority",IF(BQ9="Y","New project enters behind carryforward projects","")) | CA9: =_xludf.RANK.EQ(Rule_Flags!O8,Rule_Flags!$O$3:$O$402,0) | CB9: =IF(OR(BU9="Determination Notice Issued",BU9="Board",BU9="Closed"),"Y","N") | CD9: Jeremy Bartholomew | CE9: (713) 334-5514 | CF9: jeremy@resolutioncompanies.com | CG9: Jennine Hovell-Cox | CH9: (713) 260-0501
A10: 2026-02-10 | B10: 2026-02-10 | C10: 25410 | D10: 07433 | E10: Regency Park | F10: Houston | G10: Harris | H10: 6 | I10: 10600 Southown Trace Trail | J10: 77034 | K10: 45665 | L10: Closed | M10: 45757 | N10: 45772 | O10: 45670 | P10: 45850 | R10: Acq/Rehab | S10: General | T10: 252 | U10: 252 | X10: HHA Fountainview PFC | Y10: Other | Z10: 30000000 | AB10: 1408353 | AC10: 1408353 | AD10: 470000 | AF10: N | AG10: Y | AH10: Y | AI10: Y | AK10: Y | AL10: Y | AM10: Y | AS10: N | AX10: N | AY10: Y | AZ10: Y | BA10: Y | BB10: Y | BC10: Y | BE10: N | BJ10: Y | BK10: N | BL10: N | BM10: Y | BN10: Y | BO10: 45665 | BP10: Y | BQ10: N | BR10: =IF(COUNTIF(AI10:BM10,"N")+COUNTBLANK(AI10:BM10)=0,"Y","N") | BS10: =IF(AND(BR10="Y",OR(L10="Submitted",L10="Under Review")),"Y",IF(L10="Closed","Y","N")) | BT10: 9 | BU10: =Rule_Flags!Q9 | BV10: =Rule_Flags!P9 | BW10: =IF(Rule_Flags!E9=1,"SITE_CONTROL",IF(Rule_Flags!F9=1,"APPROVALS",IF(Rule_Flags!G9=1,"REPORTS",IF(Rule_Flags!H9=1,"DEFICIENCY",IF(Rule_Flags!I9=1,"UNDERWRITING",IF(Rule_Flags!J9=1,"COMPLIANCE","")))))) | BX10: =IF(BW10="SITE_CONTROL","Site control missing or invalid",IF(BW10="APPROVALS","Required approvals or resolutions incomplete",IF(BW10="REPORTS","Required third-party reports incomplete",IF(BW10="DEFICIENCY","Unresolved deficiency or material deficiency",IF(BW10="UNDERWRITING","Underwriting / feasibility not passed",IF(BW10="COMPLIANCE","Deconcentration, one-mile, LURA, or Chapter 12 issue","Ready under current engine rules")))))) | BY10: =IF(BV10="Determination Notice","Streamlined + DN-ready assumptions satisfied",IF(BV10="Board","Board-required or board-ready assumptions satisfied","")) | BZ10: =IF(AND(BP10="Y",BQ10<>"Y"),"Carryforward project retains queue priority",IF(BQ10="Y","New project enters behind carryforward projects","")) | CA10: =_xludf.RANK.EQ(Rule_Flags!O9,Rule_Flags!$O$3:$O$402,0) | CB10: =IF(OR(BU10="Determination Notice Issued",BU10="Board",BU10="Closed"),"Y","N") | CD10: Jeremy Bartholomew | CE10: (713) 334-5514 | CF10: jeremy@resolutioncompanies.com | CG10: Jennine Hovell-Cox | CH10: (713) 260-0501
A11: 2026-02-10 | B11: 2026-02-10 | C11: 25411 | D11: 01456 | E11: Sugar Creek | F11: Houston | G11: Harris | H11: 6 | I11: 11501 West Road | J11: 77065 | K11: 45665 | L11: Closed | M11: 45757 | N11: 45772 | O11: 45672 | P11: 45852 | R11: Acq/Rehab | S11: General | T11: 240 | U11: 240 | X11: HHA Fountainview PFC | Y11: Other | Z11: 28000000 | AB11: 1442123 | AC11: 1442123 | AF11: N | AG11: Y | AH11: Y | AI11: Y | AK11: Y | AL11: Y | AM11: Y | AS11: N | AX11: N | AY11: Y | AZ11: Y | BA11: Y | BB11: Y | BC11: Y | BE11: N | BJ11: Y | BK11: N | BL11: N | BM11: Y | BN11: Y | BO11: 45665 | BP11: Y | BQ11: N | BR11: =IF(COUNTIF(AI11:BM11,"N")+COUNTBLANK(AI11:BM11)=0,"Y","N") | BS11: =IF(AND(BR11="Y",OR(L11="Submitted",L11="Under Review")),"Y",IF(L11="Closed","Y","N")) | BT11: 10 | BU11: =Rule_Flags!Q10 | BV11: =Rule_Flags!P10 | BW11: =IF(Rule_Flags!E10=1,"SITE_CONTROL",IF(Rule_Flags!F10=1,"APPROVALS",IF(Rule_Flags!G10=1,"REPORTS",IF(Rule_Flags!H10=1,"DEFICIENCY",IF(Rule_Flags!I10=1,"UNDERWRITING",IF(Rule_Flags!J10=1,"COMPLIANCE","")))))) | BX11: =IF(BW11="SITE_CONTROL","Site control missing or invalid",IF(BW11="APPROVALS","Required approvals or resolutions incomplete",IF(BW11="REPORTS","Required third-party reports incomplete",IF(BW11="DEFICIENCY","Unresolved deficiency or material deficiency",IF(BW11="UNDERWRITING","Underwriting / feasibility not passed",IF(BW11="COMPLIANCE","Deconcentration, one-mile, LURA, or Chapter 12 issue","Ready under current engine rules")))))) | BY11: =IF(BV11="Determination Notice","Streamlined + DN-ready assumptions satisfied",IF(BV11="Board","Board-required or board-ready assumptions satisfied","")) | BZ11: =IF(AND(BP11="Y",BQ11<>"Y"),"Carryforward project retains queue priority",IF(BQ11="Y","New project enters behind carryforward projects","")) | CA11: =_xludf.RANK.EQ(Rule_Flags!O10,Rule_Flags!$O$3:$O$402,0) | CB11: =IF(OR(BU11="Determination Notice Issued",BU11="Board",BU11="Closed"),"Y","N") | CD11: Jeremy Bartholomew | CE11: (713) 334-5514 | CF11: jeremy@resolutioncompanies.com | CG11: Jennine Hovell-Cox | CH11: (713) 260-0501
A12: 2026-02-10 | B12: 2026-02-10 | C12: 25433 | E12: Brady Village | F12: Lancaster | G12: Dallas | H12: 3 | I12: Brady Drive and McKinney Drive | J12: 75146 | K12: 45666 | L12: Withdrawn | M12: 45820 | O12: 45667 | P12: 45847 | R12: Acq/Rehab | S12: General | T12: 60 | U12: 60 | X12: Texas Home Collaborative | Y12: Other | Z12: 25000000 | AB12: 752709 | AF12: N | AG12: N | AI12: Y | AK12: Y | AL12: Y | AM12: Y | AS12: N | AX12: N | AY12: Y | AZ12: Y | BA12: Y | BB12: Y | BC12: Y | BE12: N | BJ12: Y | BK12: N | BL12: N | BM12: Y | BN12: Y | BO12: 45666 | BP12: Y | BQ12: N | BR12: =IF(COUNTIF(AI12:BM12,"N")+COUNTBLANK(AI12:BM12)=0,"Y","N") | BS12: =IF(AND(BR12="Y",OR(L12="Submitted",L12="Under Review")),"Y",IF(L12="Closed","Y","N")) | BT12: 12 | BU12: =Rule_Flags!Q11 | BV12: =Rule_Flags!P11 | BW12: =IF(Rule_Flags!E11=1,"SITE_CONTROL",IF(Rule_Flags!F11=1,"APPROVALS",IF(Rule_Flags!G11=1,"REPORTS",IF(Rule_Flags!H11=1,"DEFICIENCY",IF(Rule_Flags!I11=1,"UNDERWRITING",IF(Rule_Flags!J11=1,"COMPLIANCE","")))))) | BX12: =IF(BW12="SITE_CONTROL","Site control missing or invalid",IF(BW12="APPROVALS","Required approvals or resolutions incomplete",IF(BW12="REPORTS","Required third-party reports incomplete",IF(BW12="DEFICIENCY","Unresolved deficiency or material deficiency",IF(BW12="UNDERWRITING","Underwriting / feasibility not passed",IF(BW12="COMPLIANCE","Deconcentration, one-mile, LURA, or Chapter 12 issue","Ready under current engine rules")))))) | BY12: =IF(BV12="Determination Notice","Streamlined + DN-ready assumptions satisfied",IF(BV12="Board","Board-required or board-ready assumptions satisfied","")) | BZ12: =IF(AND(BP12="Y",BQ12<>"Y"),"Carryforward project retains queue priority",IF(BQ12="Y","New project enters behind carryforward projects","")) | CA12: =_xludf.RANK.EQ(Rule_Flags!O11,Rule_Flags!$O$3:$O$402,0) | CB12: =IF(OR(BU12="Determination Notice Issued",BU12="Board",BU12="Closed"),"Y","N") | CD12: Melissa Fisher | CE12: (972) 701-5555 | CF12: mfisher@rise-residential.com | CG12: Antonio Williams | CH12: (903) 276-7557
A13: 2026-02-10 | B13: 2026-02-10 | C13: 25434 | D13: 9989 | E13: Seaport Village | F13: Galveston | G13: Galveston | H13: 6 | I13: 7200 Heards Lane | J13: 77551 | K13: 45666 | L13: Withdrawn | M13: 45820 | O13: 45667 | P13: 45847 | R13: Acq/Rehab | S13: General | T13: 192 | U13: 192 | X13: Texas Home Collaborative | Y13: Other | Z13: 25000000 | AB13: 1267031 | AF13: N | AG13: N | AI13: Y | AK13: Y | AL13: Y | AM13: Y | AS13: N | AX13: N | AY13: Y | AZ13: Y | BA13: Y | BB13: Y | BC13: Y | BE13: N | BJ13: Y | BK13: N | BL13: N | BM13: Y | BN13: Y | BO13: 45666 | BP13: Y | BQ13: N | BR13: =IF(COUNTIF(AI13:BM13,"N")+COUNTBLANK(AI13:BM13)=0,"Y","N") | BS13: =IF(AND(BR13="Y",OR(L13="Submitted",L13="Under Review")),"Y",IF(L13="Closed","Y","N")) | BT13: 13 | BU13: =Rule_Flags!Q12 | BV13: =Rule_Flags!P12 | BW13: =IF(Rule_Flags!E12=1,"SITE_CONTROL",IF(Rule_Flags!F12=1,"APPROVALS",IF(Rule_Flags!G12=1,"REPORTS",IF(Rule_Flags!H12=1,"DEFICIENCY",IF(Rule_Flags!I12=1,"UNDERWRITING",IF(Rule_Flags!J12=1,"COMPLIANCE","")))))) | BX13: =IF(BW13="SITE_CONTROL","Site control missing or invalid",IF(BW13="APPROVALS","Required approvals or resolutions incomplete",IF(BW13="REPORTS","Required third-party reports incomplete",IF(BW13="DEFICIENCY","Unresolved deficiency or material deficiency",IF(BW13="UNDERWRITING","Underwriting / feasibility not passed",IF(BW13="COMPLIANCE","Deconcentration, one-mile, LURA, or Chapter 12 issue","Ready under current engine rules")))))) | BY13: =IF(BV13="Determination Notice","Streamlined + DN-ready assumptions satisfied",IF(BV13="Board","Board-required or board-ready assumptions satisfied","")) | BZ13: =IF(AND(BP13="Y",BQ13<>"Y"),"Carryforward project retains queue priority",IF(BQ13="Y","New project enters behind carryforward projects","")) | CA13: =_xludf.RANK.EQ(Rule_Flags!O12,Rule_Flags!$O$3:$O$402,0) | CB13: =IF(OR(BU13="Determination Notice Issued",BU13="Board",BU13="Closed"),"Y","N") | CD13: Bill Fisher | CE13: (214) 608-7201 | CF13: bill.fisher@sonomaadvisors.com | CG13: Antonio Williams | CH13: (903) 276-7557
A14: 2026-02-10 | B14: 2026-02-10 | C14: 25435 | E14: Sienna Villas | F14: Freeport | G14: Brazoria | H14: 6 | I14: 902 North Avenue J | J14: 77541 | K14: 45666 | L14: Withdrawn | M14: 45820 | O14: 45883 | P14: 46063 | R14: Acq/Rehab | S14: General | T14: 156 | U14: 156 | X14: Texas Home Collaborative | Y14: Other | Z14: 20000000 | AB14: 1183699 | AF14: N | AG14: N | AI14: Y | AK14: Y | AL14: Y | AM14: Y | AS14: N | AX14: N | AY14: Y | AZ14: Y | BA14: Y | BB14: Y | BC14: Y | BE14: N | BJ14: Y | BK14: N | BL14: N | BM14: Y | BN14: Y | BO14: 45666 | BP14: Y | BQ14: N | BR14: =IF(COUNTIF(AI14:BM14,"N")+COUNTBLANK(AI14:BM14)=0,"Y","N") | BS14: =IF(AND(BR14="Y",OR(L14="Submitted",L14="Under Review")),"Y",IF(L14="Closed","Y","N")) | BT14: 14 | BU14: =Rule_Flags!Q13 | BV14: =Rule_Flags!P13 | BW14: =IF(Rule_Flags!E13=1,"SITE_CONTROL",IF(Rule_Flags!F13=1,"APPROVALS",IF(Rule_Flags!G13=1,"REPORTS",IF(Rule_Flags!H13=1,"DEFICIENCY",IF(Rule_Flags!I13=1,"UNDERWRITING",IF(Rule_Flags!J13=1,"COMPLIANCE","")))))) | BX14: =IF(BW14="SITE_CONTROL","Site control missing or invalid",IF(BW14="APPROVALS","Required approvals or resolutions incomplete",IF(BW14="REPORTS","Required third-party reports incomplete",IF(BW14="DEFICIENCY","Unresolved deficiency or material deficiency",IF(BW14="UNDERWRITING","Underwriting / feasibility not passed",IF(BW14="COMPLIANCE","Deconcentration, one-mile, LURA, or Chapter 12 issue","Ready under current engine rules")))))) | BY14: =IF(BV14="Determination Notice","Streamlined + DN-ready assumptions satisfied",IF(BV14="Board","Board-required or board-ready assumptions satisfied","")) | BZ14: =IF(AND(BP14="Y",BQ14<>"Y"),"Carryforward project retains queue priority",IF(BQ14="Y","New project enters behind carryforward projects","")) | CA14: =_xludf.RANK.EQ(Rule_Flags!O13,Rule_Flags!$O$3:$O$402,0) | CB14: =IF(OR(BU14="Determination Notice Issued",BU14="Board",BU14="Closed"),"Y","N") | CD14: Bill Fisher | CE14: (214) 608-7201 | CF14: bill.fisher@sonomaadvisors.com | CG14: Antonio Williams | CH14: (903) 276-7557
A15: 2026-02-10 | B15: 2026-02-10 | C15: 25441 | D15: 24445 | E15: Aureus at Whisper Hills | F15: San Marcos | G15: Hays | H15: 7 | I15: 538 Celebration Way | J15: 78666 | K15: 45667 | L15: Withdrawn | M15: 45785 | O15: 45671 | P15: 45851 | R15: New Construction | S15: Elderly | T15: 267 | U15: 267 | X15: SMHA Finance PFC | Y15: Other | Z15: 40000000 | AB15: 2915592 | AF15: N | AG15: Y | AH15: Y | AI15: Y | AK15: Y | AL15: Y | AM15: Y | AS15: N | AX15: N | AY15: Y | AZ15: Y | BA15: Y | BB15: Y | BC15: Y | BE15: N | BJ15: Y | BK15: N | BL15: N | BM15: Y | BN15: Y | BO15: 45667 | BP15: Y | BQ15: N | BR15: =IF(COUNTIF(AI15:BM15,"N")+COUNTBLANK(AI15:BM15)=0,"Y","N") | BS15: =IF(AND(BR15="Y",OR(L15="Submitted",L15="Under Review")),"Y",IF(L15="Closed","Y","N")) | BT15: 19 | BU15: =Rule_Flags!Q14 | BV15: =Rule_Flags!P14 | BW15: =IF(Rule_Flags!E14=1,"SITE_CONTROL",IF(Rule_Flags!F14=1,"APPROVALS",IF(Rule_Flags!G14=1,"REPORTS",IF(Rule_Flags!H14=1,"DEFICIENCY",IF(Rule_Flags!I14=1,"UNDERWRITING",IF(Rule_Flags!J14=1,"COMPLIANCE","")))))) | BX15: =IF(BW15="SITE_CONTROL","Site control missing or invalid",IF(BW15="APPROVALS","Required approvals or resolutions incomplete",IF(BW15="REPORTS","Required third-party reports incomplete",IF(BW15="DEFICIENCY","Unresolved deficiency or material deficiency",IF(BW15="UNDERWRITING","Underwriting / feasibility not passed",IF(BW15="COMPLIANCE","Deconcentration, one-mile, LURA, or Chapter 12 issue","Ready under current engine rules")))))) | BY15: =IF(BV15="Determination Notice","Streamlined + DN-ready assumptions satisfied",IF(BV15="Board","Board-required or board-ready assumptions satisfied","")) | BZ15: =IF(AND(BP15="Y",BQ15<>"Y"),"Carryforward project retains queue priority",IF(BQ15="Y","New project enters behind carryforward projects","")) | CA15: =_xludf.RANK.EQ(Rule_Flags!O14,Rule_Flags!$O$3:$O$402,0) | CB15: =IF(OR(BU15="Determination Notice Issued",BU15="Board",BU15="Closed"),"Y","N") | CC15: construction_type mapped from raw 'NC' to 'New Construction' | CD15: John Latham | CE15: (210) 354-3705 | CF15: john@missiondg.com | CG15: Lana Wagner | CH15: (512) 353-5058
A16: 2026-02-10 | B16: 2026-02-10 | C16: 25406 | D16: 04475 | E16: Fairlake Cove | F16: Houston | G16: Harris | H16: 6 | I16: 11100 E FM 1960 | J16: 77336 | K16: 45667 | L16: Withdrawn | M16: 45785 | O16: 45671 | P16: 45851 | R16: Acq/Rehab | S16: General | T16: 200 | U16: 200 | X16: HHA Fountainview PFC | Y16: Other | Z16: 40000000 | AB16: 1686761 | AF16: N | AG16: Y | AH16: Y | AI16: Y | AK16: Y | AL16: Y | AM16: Y | AS16: N | AX16: N | AY16: Y | AZ16: Y | BA16: Y | BB16: Y | BC16: Y | BE16: N | BJ16: Y | BK16: N | BL16: N | BM16: Y | BN16: Y | BO16: 45667 | BP16: Y | BQ16: N | BR16: =IF(COUNTIF(AI16:BM16,"N")+COUNTBLANK(AI16:BM16)=0,"Y","N") | BS16: =IF(AND(BR16="Y",OR(L16="Submitted",L16="Under Review")),"Y",IF(L16="Closed","Y","N")) | BT16: 16 | BU16: =Rule_Flags!Q15 | BV16: =Rule_Flags!P15 | BW16: =IF(Rule_Flags!E15=1,"SITE_CONTROL",IF(Rule_Flags!F15=1,"APPROVALS",IF(Rule_Flags!G15=1,"REPORTS",IF(Rule_Flags!H15=1,"DEFICIENCY",IF(Rule_Flags!I15=1,"UNDERWRITING",IF(Rule_Flags!J15=1,"COMPLIANCE","")))))) | BX16: =IF(BW16="SITE_CONTROL","Site control missing or invalid",IF(BW16="APPROVALS","Required approvals or resolutions incomplete",IF(BW16="REPORTS","Required third-party reports incomplete",IF(BW16="DEFICIENCY","Unresolved deficiency or material deficiency",IF(BW16="UNDERWRITING","Underwriting / feasibility not passed",IF(BW16="COMPLIANCE","Deconcentration, one-mile, LURA, or Chapter 12 issue","Ready under current engine rules")))))) | BY16: =IF(BV16="Determination Notice","Streamlined + DN-ready assumptions satisfied",IF(BV16="Board","Board-required or board-ready assumptions satisfied","")) | BZ16: =IF(AND(BP16="Y",BQ16<>"Y"),"Carryforward project retains queue priority",IF(BQ16="Y","New project enters behind carryforward projects","")) | CA16: =_xludf.RANK.EQ(Rule_Flags!O15,Rule_Flags!$O$3:$O$402,0) | CB16: =IF(OR(BU16="Determination Notice Issued",BU16="Board",BU16="Closed"),"Y","N") | CD16: Brad Fisher | CE16: (913) 787-1676 | CF16: bfisher@aprilhousing.com | CG16: Jennine Hovell-Cox | CH16: (713) 260-0501
A17: 2026-02-10 | B17: 2026-02-10 | C17: 25436 | E17: Jackson Apartments | F17: McAllen | G17: Hidalgo | H17: 11 | I17: 2200 W Jackson Avenue | J17: 78503 | K17: 45667 | L17: Withdrawn | M17: 45820 | O17: 45883 | P17: 46063 | R17: New Construction | S17: General | T17: 88 | U17: 88 | X17: Texas Home Collaborative | Y17: Other | Z17: 12000000 | AB17: 776722 | AF17: N | AG17: N | AI17: Y | AK17: Y | AL17: Y | AM17: Y | AS17: N | AX17: N | AY17: Y | AZ17: Y | BA17: Y | BB17: Y | BC17: Y | BE17: N | BJ17: Y | BK17: N | BL17: N | BM17: Y | BN17: Y | BO17: 45667 | BP17: Y | BQ17: N | BR17: =IF(COUNTIF(AI17:BM17,"N")+COUNTBLANK(AI17:BM17)=0,"Y","N") | BS17: =IF(AND(BR17="Y",OR(L17="Submitted",L17="Under Review")),"Y",IF(L17="Closed","Y","N")) | BT17: 18 | BU17: =Rule_Flags!Q16 | BV17: =Rule_Flags!P16 | BW17: =IF(Rule_Flags!E16=1,"SITE_CONTROL",IF(Rule_Flags!F16=1,"APPROVALS",IF(Rule_Flags!G16=1,"REPORTS",IF(Rule_Flags!H16=1,"DEFICIENCY",IF(Rule_Flags!I16=1,"UNDERWRITING",IF(Rule_Flags!J16=1,"COMPLIANCE","")))))) | BX17: =IF(BW17="SITE_CONTROL","Site control missing or invalid",IF(BW17="APPROVALS","Required approvals or resolutions incomplete",IF(BW17="REPORTS","Required third-party reports incomplete",IF(BW17="DEFICIENCY","Unresolved deficiency or material deficiency",IF(BW17="UNDERWRITING","Underwriting / feasibility not passed",IF(BW17="COMPLIANCE","Deconcentration, one-mile, LURA, or Chapter 12 issue","Ready under current engine rules")))))) | BY17: =IF(BV17="Determination Notice","Streamlined + DN-ready assumptions satisfied",IF(BV17="Board","Board-required or board-ready assumptions satisfied","")) | BZ17: =IF(AND(BP17="Y",BQ17<>"Y"),"Carryforward project retains queue priority",IF(BQ17="Y","New project enters behind carryforward projects","")) | CA17: =_xludf.RANK.EQ(Rule_Flags!O16,Rule_Flags!$O$3:$O$402,0) | CB17: =IF(OR(BU17="Determination Notice Issued",BU17="Board",BU17="Closed"),"Y","N") | CC17: construction_type mapped from raw 'NC' to 'New Construction' | CD17: Melissa Fisher | CE17: (972) 701-5555 | CF17: mfisher@rise-residential.com | CG17: Antonio Williams | CH17: (903) 276-7557
A18: 2026-02-10 | B18: 2026-02-10 | C18: 25405 | E18: HiLine Illinois | F18: Dallas | G18: Dallas | H18: 3 | I18: 4710 W Illinois Avenue | J18: 75211 | K18: 45667 | L18: Closed | M18: 45785 | N18: 45825 | O18: 45672 | P18: 45852 | R18: New Construction | S18: General | T18: 200 | U18: 200 | X18: Dallas HFC | Y18: Local HFC | Z18: 35000000 | AB18: 2784011 | AC18: 2784011 | AF18: N | AG18: Y | AI18: Y | AK18: Y | AL18: Y | AM18: Y | AS18: N | AX18: N | AY18: Y | AZ18: Y | BA18: Y | BB18: Y | BC18: Y | BE18: N | BJ18: Y | BK18: N | BL18: N | BM18: Y | BN18: Y | BO18: 45667 | BP18: Y | BQ18: N | BR18: =IF(COUNTIF(AI18:BM18,"N")+COUNTBLANK(AI18:BM18)=0,"Y","N") | BS18: =IF(AND(BR18="Y",OR(L18="Submitted",L18="Under Review")),"Y",IF(L18="Closed","Y","N")) | BT18: 15 | BU18: =Rule_Flags!Q17 | BV18: =Rule_Flags!P17 | BW18: =IF(Rule_Flags!E17=1,"SITE_CONTROL",IF(Rule_Flags!F17=1,"APPROVALS",IF(Rule_Flags!G17=1,"REPORTS",IF(Rule_Flags!H17=1,"DEFICIENCY",IF(Rule_Flags!I17=1,"UNDERWRITING",IF(Rule_Flags!J17=1,"COMPLIANCE","")))))) | BX18: =IF(BW18="SITE_CONTROL","Site control missing or invalid",IF(BW18="APPROVALS","Required approvals or resolutions incomplete",IF(BW18="REPORTS","Required third-party reports incomplete",IF(BW18="DEFICIENCY","Unresolved deficiency or material deficiency",IF(BW18="UNDERWRITING","Underwriting / feasibility not passed",IF(BW18="COMPLIANCE","Deconcentration, one-mile, LURA, or Chapter 12 issue","Ready under current engine rules")))))) | BY18: =IF(BV18="Determination Notice","Streamlined + DN-ready assumptions satisfied",IF(BV18="Board","Board-required or board-ready assumptions satisfied","")) | BZ18: =IF(AND(BP18="Y",BQ18<>"Y"),"Carryforward project retains queue priority",IF(BQ18="Y","New project enters behind carryforward projects","")) | CA18: =_xludf.RANK.EQ(Rule_Flags!O17,Rule_Flags!$O$3:$O$402,0) | CB18: =IF(OR(BU18="Determination Notice Issued",BU18="Board",BU18="Closed"),"Y","N") | CC18: construction_type mapped from raw 'NC' to 'New Construction' | CD18: Adrian Iglesias | CE18: (214)613-6569 | CF18: aiglesias@ghdevelopment.com | CG18: Aaron Eaquinto | CH18: (214) 670-4941
A19: 2026-02-10 | B19: 2026-02-10 | C19: 25413 | E19: Sunflower Terrace | F19: Houston | G19: Harris | H19: 6 | I19: 5050 Sunflower Street | J19: 77033 | K19: 45667 | L19: Closed | M19: 45757 | N19: 45779 | O19: 45671 | P19: 45851 | R19: Acq/Rehab | S19: General | T19: 160 | U19: 160 | X19: Houston HFC | Y19: Local HFC | Z19: 28000000 | AB19: 1996896 | AC19: 1996896 | AF19: N | AG19: Y | AI19: Y | AK19: Y | AL19: Y | AM19: Y | AS19: N | AX19: N | AY19: Y | AZ19: Y | BA19: Y | BB19: Y | BC19: Y | BE19: N | BJ19: Y | BK19: N | BL19: N | BM19: Y | BN19: Y | BO19: 45667 | BP19: Y | BQ19: N | BR19: =IF(COUNTIF(AI19:BM19,"N")+COUNTBLANK(AI19:BM19)=0,"Y","N") | BS19: =IF(AND(BR19="Y",OR(L19="Submitted",L19="Under Review")),"Y",IF(L19="Closed","Y","N")) | BT19: 17 | BU19: =Rule_Flags!Q18 | BV19: =Rule_Flags!P18 | BW19: =IF(Rule_Flags!E18=1,"SITE_CONTROL",IF(Rule_Flags!F18=1,"APPROVALS",IF(Rule_Flags!G18=1,"REPORTS",IF(Rule_Flags!H18=1,"DEFICIENCY",IF(Rule_Flags!I18=1,"UNDERWRITING",IF(Rule_Flags!J18=1,"COMPLIANCE","")))))) | BX19: =IF(BW19="SITE_CONTROL","Site control missing or invalid",IF(BW19="APPROVALS","Required approvals or resolutions incomplete",IF(BW19="REPORTS","Required third-party reports incomplete",IF(BW19="DEFICIENCY","Unresolved deficiency or material deficiency",IF(BW19="UNDERWRITING","Underwriting / feasibility not passed",IF(BW19="COMPLIANCE","Deconcentration, one-mile, LURA, or Chapter 12 issue","Ready under current engine rules")))))) | BY19: =IF(BV19="Determination Notice","Streamlined + DN-ready assumptions satisfied",IF(BV19="Board","Board-required or board-ready assumptions satisfied","")) | BZ19: =IF(AND(BP19="Y",BQ19<>"Y"),"Carryforward project retains queue priority",IF(BQ19="Y","New project enters behind carryforward projects","")) | CA19: =_xludf.RANK.EQ(Rule_Flags!O18,Rule_Flags!$O$3:$O$402,0) | CB19: =IF(OR(BU19="Determination Notice Issued",BU19="Board",BU19="Closed"),"Y","N") | CD19: Allan Izzo | CE19: (646) 825-7106 | CF19: allan.izzo@fairstead.com | CG19: Richard Mudd, Sr. | CH19: (713) 461-2749
A20: 2026-02-10 | B20: 2026-02-10 | C20: 25439 | D20: 95157 | E20: Pleasant Hill Village | F20: Houston | G20: Harris | H20: 6 | I20: 3814 Lyons Avenue | J20: 77020 | K20: 45670 | L20: Approved | M20: 45820 | N20: 45826 | O20: 45880 | P20: 46060 | R20: Acq/Rehab | S20: Elderly | T20: 165 | U20: 165 | X20: HHA Fountainview PFC | Y20: Other | Z20: 20000000 | AB20: 1176012 | AC20: 1176012 | AF20: N | AG20: Y | AH20: Y | AI20: Y | AK20: Y | AL20: Y | AM20: Y | AS20: N | AX20: N | AY20: Y | AZ20: Y | BA20: Y | BB20: Y | BC20: Y | BE20: N | BJ20: Y | BK20: N | BL20: N | BM20: Y | BN20: Y | BO20: 45670 | BP20: Y | BQ20: N | BR20: =IF(COUNTIF(AI20:BM20,"N")+COUNTBLANK(AI20:BM20)=0,"Y","N") | BS20: =IF(AND(BR20="Y",OR(L20="Submitted",L20="Under Review")),"Y",IF(L20="Closed","Y","N")) | BT20: 25 | BU20: =Rule_Flags!Q19 | BV20: =Rule_Flags!P19 | BW20: =IF(Rule_Flags!E19=1,"SITE_CONTROL",IF(Rule_Flags!F19=1,"APPROVALS",IF(Rule_Flags!G19=1,"REPORTS",IF(Rule_Flags!H19=1,"DEFICIENCY",IF(Rule_Flags!I19=1,"UNDERWRITING",IF(Rule_Flags!J19=1,"COMPLIANCE","")))))) | BX20: =IF(BW20="SITE_CONTROL","Site control missing or invalid",IF(BW20="APPROVALS","Required approvals or resolutions incomplete",IF(BW20="REPORTS","Required third-party reports incomplete",IF(BW20="DEFICIENCY","Unresolved deficiency or material deficiency",IF(BW20="UNDERWRITING","Underwriting / feasibility not passed",IF(BW20="COMPLIANCE","Deconcentration, one-mile, LURA, or Chapter 12 issue","Ready under current engine rules")))))) | BY20: =IF(BV20="Determination Notice","Streamlined + DN-ready assumptions satisfied",IF(BV20="Board","Board-required or board-ready assumptions satisfied","")) | BZ20: =IF(AND(BP20="Y",BQ20<>"Y"),"Carryforward project retains queue priority",IF(BQ20="Y","New project enters behind carryforward projects","")) | CA20: =_xludf.RANK.EQ(Rule_Flags!O19,Rule_Flags!$O$3:$O$402,0) | CB20: =IF(OR(BU20="Determination Notice Issued",BU20="Board",BU20="Closed"),"Y","N") | CD20: Harvey Clemons, Jr. | CE20: (713) 224-0052 | CF20: hclemons@aol.com | CG20: David Northern, Sr. | CH20: (713) 260-0522
A21: 2026-02-10 | B21: 2026-02-10 | C21: 25437 | E21: Manor Apartments | F21: Austin | G21: Travis | H21: 7 | I21: 6705 Manor Road | J21: 78723 | K21: 45670 | L21: Withdrawn | M21: 45785 | N21: 45800 | O21: 45671 | P21: 45851 | R21: New Construction | S21: General | T21: 181 | U21: 179 | X21: Travis County HFC | Y21: Local HFC | Z21: 35000000 | AB21: 2902773 | AC21: 2902773 | AF21: N | AG21: Y | AI21: Y | AK21: Y | AL21: Y | AM21: Y | AS21: N | AX21: N | AY21: Y | AZ21: Y | BA21: Y | BB21: Y | BC21: Y | BE21: N | BJ21: Y | BK21: N | BL21: N | BM21: Y | BN21: Y | BO21: 45670 | BP21: Y | BQ21: N | BR21: =IF(COUNTIF(AI21:BM21,"N")+COUNTBLANK(AI21:BM21)=0,"Y","N") | BS21: =IF(AND(BR21="Y",OR(L21="Submitted",L21="Under Review")),"Y",IF(L21="Closed","Y","N")) | BT21: 23 | BU21: =Rule_Flags!Q20 | BV21: =Rule_Flags!P20 | BW21: =IF(Rule_Flags!E20=1,"SITE_CONTROL",IF(Rule_Flags!F20=1,"APPROVALS",IF(Rule_Flags!G20=1,"REPORTS",IF(Rule_Flags!H20=1,"DEFICIENCY",IF(Rule_Flags!I20=1,"UNDERWRITING",IF(Rule_Flags!J20=1,"COMPLIANCE","")))))) | BX21: =IF(BW21="SITE_CONTROL","Site control missing or invalid",IF(BW21="APPROVALS","Required approvals or resolutions incomplete",IF(BW21="REPORTS","Required third-party reports incomplete",IF(BW21="DEFICIENCY","Unresolved deficiency or material deficiency",IF(BW21="UNDERWRITING","Underwriting / feasibility not passed",IF(BW21="COMPLIANCE","Deconcentration, one-mile, LURA, or Chapter 12 issue","Ready under current engine rules")))))) | BY21: =IF(BV21="Determination Notice","Streamlined + DN-ready assumptions satisfied",IF(BV21="Board","Board-required or board-ready assumptions satisfied","")) | BZ21: =IF(AND(BP21="Y",BQ21<>"Y"),"Carryforward project retains queue priority",IF(BQ21="Y","New project enters behind carryforward projects","")) | CA21: =_xludf.RANK.EQ(Rule_Flags!O20,Rule_Flags!$O$3:$O$402,0) | CB21: =IF(OR(BU21="Determination Notice Issued",BU21="Board",BU21="Closed"),"Y","N") | CC21: construction_type mapped from raw 'NC' to 'New Construction' | CD21: Chad Baker | CE21: (214) 295-5645 | CF21: cbaker@amtexhousing.com | CG21: Ana Everett | CH21: (512) 854-1745
A22: 2026-02-10 | B22: 2026-02-10 | C22: 25438 | D22: 538613 | E22: Britton's Place | F22: Houston | G22: Harris | H22: 6 | I22: 3730 Lyons Avenue | J22: 77020 | K22: 45670 | L22: Approved | M22: 45820 | N22: 45833 | O22: 45880 | P22: 46060 | R22: Acq/Rehab | S22: General | T22: 48 | U22: 48 | X22: HHA Fountainview PFC | Y22: Other | Z22: 20000000 | AB22: 466454 | AC22: 466454 | AF22: N | AG22: Y | AH22: Y | AI22: Y | AK22: Y | AL22: Y | AM22: Y | AS22: N | AX22: N | AY22: Y | AZ22: Y | BA22: Y | BB22: Y | BC22: Y | BE22: N | BJ22: Y | BK22: N | BL22: N | BM22: Y | BN22: Y | BO22: 45670 | BP22: Y | BQ22: N | BR22: =IF(COUNTIF(AI22:BM22,"N")+COUNTBLANK(AI22:BM22)=0,"Y","N") | BS22: =IF(AND(BR22="Y",OR(L22="Submitted",L22="Under Review")),"Y",IF(L22="Closed","Y","N")) | BT22: 24 | BU22: =Rule_Flags!Q21 | BV22: =Rule_Flags!P21 | BW22: =IF(Rule_Flags!E21=1,"SITE_CONTROL",IF(Rule_Flags!F21=1,"APPROVALS",IF(Rule_Flags!G21=1,"REPORTS",IF(Rule_Flags!H21=1,"DEFICIENCY",IF(Rule_Flags!I21=1,"UNDERWRITING",IF(Rule_Flags!J21=1,"COMPLIANCE","")))))) | BX22: =IF(BW22="SITE_CONTROL","Site control missing or invalid",IF(BW22="APPROVALS","Required approvals or resolutions incomplete",IF(BW22="REPORTS","Required third-party reports incomplete",IF(BW22="DEFICIENCY","Unresolved deficiency or material deficiency",IF(BW22="UNDERWRITING","Underwriting / feasibility not passed",IF(BW22="COMPLIANCE","Deconcentration, one-mile, LURA, or Chapter 12 issue","Ready under current engine rules")))))) | BY22: =IF(BV22="Determination Notice","Streamlined + DN-ready assumptions satisfied",IF(BV22="Board","Board-required or board-ready assumptions satisfied","")) | BZ22: =IF(AND(BP22="Y",BQ22<>"Y"),"Carryforward project retains queue priority",IF(BQ22="Y","New project enters behind carryforward projects","")) | CA22: =_xludf.RANK.EQ(Rule_Flags!O21,Rule_Flags!$O$3:$O$402,0) | CB22: =IF(OR(BU22="Determination Notice Issued",BU22="Board",BU22="Closed"),"Y","N") | CD22: Harvey Clemons, Jr. | CE22: (713) 224-0052 | CF22: hclemons@aol.com | CG22: David Northern, Sr. | CH22: (713) 260-0522
A23: 2026-02-10 | B23: 2026-02-10 | C23: 25417 | E23: Reserve at Ella | F23: Houston | G23: Harris | H23: 6 | I23: 867 Rushcreek Drive | J23: 77067 | K23: 45670 | L23: Withdrawn | M23: 45820 | O23: 45671 | P23: 45851 | R23: New Construction | S23: General | T23: 344 | U23: 344 | X23: HHA Fountainview PFC | Y23: Other | Z23: 50000000 | AB23: 3405323 | AF23: N | AG23: Y | AH23: Y | AI23: Y | AK23: Y | AL23: Y | AM23: Y | AS23: N | AX23: N | AY23: Y | AZ23: Y | BA23: Y | BB23: Y | BC23: Y | BE23: N | BJ23: Y | BK23: N | BL23: N | BM23: Y | BN23: Y | BO23: 45670 | BP23: Y | BQ23: N | BR23: =IF(COUNTIF(AI23:BM23,"N")+COUNTBLANK(AI23:BM23)=0,"Y","N") | BS23: =IF(AND(BR23="Y",OR(L23="Submitted",L23="Under Review")),"Y",IF(L23="Closed","Y","N")) | BT23: 22 | BU23: =Rule_Flags!Q22 | BV23: =Rule_Flags!P22 | BW23: =IF(Rule_Flags!E22=1,"SITE_CONTROL",IF(Rule_Flags!F22=1,"APPROVALS",IF(Rule_Flags!G22=1,"REPORTS",IF(Rule_Flags!H22=1,"DEFICIENCY",IF(Rule_Flags!I22=1,"UNDERWRITING",IF(Rule_Flags!J22=1,"COMPLIANCE","")))))) | BX23: =IF(BW23="SITE_CONTROL","Site control missing or invalid",IF(BW23="APPROVALS","Required approvals or resolutions incomplete",IF(BW23="REPORTS","Required third-party reports incomplete",IF(BW23="DEFICIENCY","Unresolved deficiency or material deficiency",IF(BW23="UNDERWRITING","Underwriting / feasibility not passed",IF(BW23="COMPLIANCE","Deconcentration, one-mile, LURA, or Chapter 12 issue","Ready under current engine rules")))))) | BY23: =IF(BV23="Determination Notice","Streamlined + DN-ready assumptions satisfied",IF(BV23="Board","Board-required or board-ready assumptions satisfied","")) | BZ23: =IF(AND(BP23="Y",BQ23<>"Y"),"Carryforward project retains queue priority",IF(BQ23="Y","New project enters behind carryforward projects","")) | CA23: =_xludf.RANK.EQ(Rule_Flags!O22,Rule_Flags!$O$3:$O$402,0) | CB23: =IF(OR(BU23="Determination Notice Issued",BU23="Board",BU23="Closed"),"Y","N") | CC23: construction_type mapped from raw 'NC' to 'New Construction' | CD23: Tony Ly | CE23: (713) 980-1622 | CF23: tonyly@stoacapitalpartners.com | CG23: Bill Walter | CH23: (512) 684-3842
A24: 2026-02-10 | B24: 2026-02-10 | C24: 25404 | E24: Torrington Briarwood | F24: Mesquite | G24: Dallas | H24: 3 | I24: 2250 Dean Street | J24: 75180 | K24: 45670 | L24: Closed | M24: 45785 | N24: 45433 | O24: 45671 | P24: 45851 | R24: New Construction | S24: General | T24: 313 | U24: 313 | X24: The Mesquite HFC | Y24: Local HFC | Z24: 50000000 | AB24: 4371047 | AC24: 4331927 | AF24: N | AG24: Y | AI24: Y | AK24: Y | AL24: Y | AM24: Y | AS24: N | AX24: N | AY24: Y | AZ24: Y | BA24: Y | BB24: Y | BC24: Y | BE24: N | BJ24: Y | BK24: N | BL24: N | BM24: Y | BN24: Y | BO24: 45670 | BP24: Y | BQ24: N | BR24: =IF(COUNTIF(AI24:BM24,"N")+COUNTBLANK(AI24:BM24)=0,"Y","N") | BS24: =IF(AND(BR24="Y",OR(L24="Submitted",L24="Under Review")),"Y",IF(L24="Closed","Y","N")) | BT24: 20 | BU24: =Rule_Flags!Q23 | BV24: =Rule_Flags!P23 | BW24: =IF(Rule_Flags!E23=1,"SITE_CONTROL",IF(Rule_Flags!F23=1,"APPROVALS",IF(Rule_Flags!G23=1,"REPORTS",IF(Rule_Flags!H23=1,"DEFICIENCY",IF(Rule_Flags!I23=1,"UNDERWRITING",IF(Rule_Flags!J23=1,"COMPLIANCE","")))))) | BX24: =IF(BW24="SITE_CONTROL","Site control missing or invalid",IF(BW24="APPROVALS","Required approvals or resolutions incomplete",IF(BW24="REPORTS","Required third-party reports incomplete",IF(BW24="DEFICIENCY","Unresolved deficiency or material deficiency",IF(BW24="UNDERWRITING","Underwriting / feasibility not passed",IF(BW24="COMPLIANCE","Deconcentration, one-mile, LURA, or Chapter 12 issue","Ready under current engine rules")))))) | BY24: =IF(BV24="Determination Notice","Streamlined + DN-ready assumptions satisfied",IF(BV24="Board","Board-required or board-ready assumptions satisfied","")) | BZ24: =IF(AND(BP24="Y",BQ24<>"Y"),"Carryforward project retains queue priority",IF(BQ24="Y","New project enters behind carryforward projects","")) | CA24: =_xludf.RANK.EQ(Rule_Flags!O23,Rule_Flags!$O$3:$O$402,0) | CB24: =IF(OR(BU24="Determination Notice Issued",BU24="Board",BU24="Closed"),"Y","N") | CC24: construction_type mapped from raw 'NC' to 'New Construction' | CD24: Karsten Lowe | CE24: (210) 493-8633 | CF24: Karsten.Lowe@jpi.com | CG24: Ted Chinn | CH24: (972) 216-6287
A25: 2026-02-10 | B25: 2026-02-10 | C25: 25412 | D25: 07457 | E25: Wyndham Park | F25: Baytown | G25: Harris | H25: 6 | I25: 2700 Rollingbrook Drive | J25: 77521 | K25: 45670 | L25: Closed | M25: 45785 | N25: 45811 | O25: 45673 | P25: 45853 | R25: Acq/Rehab | S25: Elderly | T25: 184 | U25: 184 | X25: Southeast Texas HFC | Y25: Local HFC | Z25: 20000000 | AB25: 986417 | AC25: 986417 | AF25: N | AG25: Y | AI25: Y | AK25: Y | AL25: Y | AM25: Y | AS25: N | AX25: N | AY25: Y | AZ25: Y | BA25: Y | BB25: Y | BC25: Y | BE25: N | BJ25: Y | BK25: N | BL25: N | BM25: Y | BN25: Y | BO25: 45670 | BP25: Y | BQ25: N | BR25: =IF(COUNTIF(AI25:BM25,"N")+COUNTBLANK(AI25:BM25)=0,"Y","N") | BS25: =IF(AND(BR25="Y",OR(L25="Submitted",L25="Under Review")),"Y",IF(L25="Closed","Y","N")) | BT25: 21 | BU25: =Rule_Flags!Q24 | BV25: =Rule_Flags!P24 | BW25: =IF(Rule_Flags!E24=1,"SITE_CONTROL",IF(Rule_Flags!F24=1,"APPROVALS",IF(Rule_Flags!G24=1,"REPORTS",IF(Rule_Flags!H24=1,"DEFICIENCY",IF(Rule_Flags!I24=1,"UNDERWRITING",IF(Rule_Flags!J24=1,"COMPLIANCE","")))))) | BX25: =IF(BW25="SITE_CONTROL","Site control missing or invalid",IF(BW25="APPROVALS","Required approvals or resolutions incomplete",IF(BW25="REPORTS","Required third-party reports incomplete",IF(BW25="DEFICIENCY","Unresolved deficiency or material deficiency",IF(BW25="UNDERWRITING","Underwriting / feasibility not passed",IF(BW25="COMPLIANCE","Deconcentration, one-mile, LURA, or Chapter 12 issue","Ready under current engine rules")))))) | BY25: =IF(BV25="Determination Notice","Streamlined + DN-ready assumptions satisfied",IF(BV25="Board","Board-required or board-ready assumptions satisfied","")) | BZ25: =IF(AND(BP25="Y",BQ25<>"Y"),"Carryforward project retains queue priority",IF(BQ25="Y","New project enters behind carryforward projects","")) | CA25: =_xludf.RANK.EQ(Rule_Flags!O24,Rule_Flags!$O$3:$O$402,0) | CB25: =IF(OR(BU25="Determination Notice Issued",BU25="Board",BU25="Closed"),"Y","N") | CD25: Jeremy Bartholomew | CE25: (713) 334-5514 | CF25: jeremy@resolutioncompanies.com | CG25: Ron Williams | CH25: (281) 484-4663
A26: 2026-02-10 | B26: 2026-02-10 | C26: 21608S | D26: 21608 | E26: Fiji Lofts | F26: Dallas | G26: Dallas | H26: 3 | I26: 301 S. Corinth Road | J26: 75203 | K26: 45525 | L26: Active | M26: 46037 | O26: 46057 | P26: 46229 | R26: New Construction | S26: General | T26: 204 | U26: 204 | X26: TDHCA | Y26: TDHCA | Z26: 6000000 | AB26: 2885077 | AF26: N | AG26: Y | AI26: Y | AK26: Y | AL26: Y | AM26: Y | AS26: N | AX26: N | AY26: Y | AZ26: Y | BA26: Y | BB26: Y | BC26: Y | BE26: N | BJ26: Y | BK26: N | BL26: N | BM26: Y | BN26: Y | BO26: 45525 | BP26: Y | BQ26: N | BR26: =IF(COUNTIF(AI26:BM26,"N")+COUNTBLANK(AI26:BM26)=0,"Y","N") | BS26: =IF(AND(BR26="Y",OR(L26="Submitted",L26="Under Review")),"Y",IF(L26="Closed","Y","N")) | BT26: 1 | BU26: =Rule_Flags!Q25 | BV26: =Rule_Flags!P25 | BW26: =IF(Rule_Flags!E25=1,"SITE_CONTROL",IF(Rule_Flags!F25=1,"APPROVALS",IF(Rule_Flags!G25=1,"REPORTS",IF(Rule_Flags!H25=1,"DEFICIENCY",IF(Rule_Flags!I25=1,"UNDERWRITING",IF(Rule_Flags!J25=1,"COMPLIANCE","")))))) | BX26: =IF(BW26="SITE_CONTROL","Site control missing or invalid",IF(BW26="APPROVALS","Required approvals or resolutions incomplete",IF(BW26="REPORTS","Required third-party reports incomplete",IF(BW26="DEFICIENCY","Unresolved deficiency or material deficiency",IF(BW26="UNDERWRITING","Underwriting / feasibility not passed",IF(BW26="COMPLIANCE","Deconcentration, one-mile, LURA, or Chapter 12 issue","Ready under current engine rules")))))) | BY26: =IF(BV26="Determination Notice","Streamlined + DN-ready assumptions satisfied",IF(BV26="Board","Board-required or board-ready assumptions satisfied","")) | BZ26: =IF(AND(BP26="Y",BQ26<>"Y"),"Carryforward project retains queue priority",IF(BQ26="Y","New project enters behind carryforward projects","")) | CA26: =_xludf.RANK.EQ(Rule_Flags!O25,Rule_Flags!$O$3:$O$402,0) | CB26: =IF(OR(BU26="Determination Notice Issued",BU26="Board",BU26="Closed"),"Y","N") | CC26: construction_type mapped from raw 'NC' to 'New Construction' | CD26: Joseph Agumadu | CE26: (214) 342-1400 | CF26: development@sdcus.com | CG26: Teresa Morales | CH26: (512) 475-3344
A27: 2026-02-10 | B27: 2026-02-10 | C27: 21614S | D27: 21614 | E27: Murdeaux Villas | F27: Dallas | G27: Dallas | H27: 3 | I27: 125 S. Murdeaux Lane | J27: 75217 | K27: 45540 | L27: Active | M27: 46058 | O27: 46049 | P27: 46229 | R27: Acq/Rehab | S27: General | T27: 301 | U27: 301 | X27: TDHCA | Y27: TDHCA | Z27: 5000000 | AB27: 3687762 | AF27: N | AG27: Y | AI27: Y | AK27: Y | AL27: Y | AM27: Y | AS27: N | AX27: N | AY27: Y | AZ27: Y | BA27: Y | BB27: Y | BC27: Y | BE27: N | BJ27: Y | BK27: N | BL27: N | BM27: Y | BN27: Y | BO27: 45540 | BP27: Y | BQ27: N | BR27: =IF(COUNTIF(AI27:BM27,"N")+COUNTBLANK(AI27:BM27)=0,"Y","N") | BS27: =IF(AND(BR27="Y",OR(L27="Submitted",L27="Under Review")),"Y",IF(L27="Closed","Y","N")) | BT27: 2 | BU27: =Rule_Flags!Q26 | BV27: =Rule_Flags!P26 | BW27: =IF(Rule_Flags!E26=1,"SITE_CONTROL",IF(Rule_Flags!F26=1,"APPROVALS",IF(Rule_Flags!G26=1,"REPORTS",IF(Rule_Flags!H26=1,"DEFICIENCY",IF(Rule_Flags!I26=1,"UNDERWRITING",IF(Rule_Flags!J26=1,"COMPLIANCE","")))))) | BX27: =IF(BW27="SITE_CONTROL","Site control missing or invalid",IF(BW27="APPROVALS","Required approvals or resolutions incomplete",IF(BW27="REPORTS","Required third-party reports incomplete",IF(BW27="DEFICIENCY","Unresolved deficiency or material deficiency",IF(BW27="UNDERWRITING","Underwriting / feasibility not passed",IF(BW27="COMPLIANCE","Deconcentration, one-mile, LURA, or Chapter 12 issue","Ready under current engine rules")))))) | BY27: =IF(BV27="Determination Notice","Streamlined + DN-ready assumptions satisfied",IF(BV27="Board","Board-required or board-ready assumptions satisfied","")) | BZ27: =IF(AND(BP27="Y",BQ27<>"Y"),"Carryforward project retains queue priority",IF(BQ27="Y","New project enters behind carryforward projects","")) | CA27: =_xludf.RANK.EQ(Rule_Flags!O26,Rule_Flags!$O$3:$O$402,0) | CB27: =IF(OR(BU27="Determination Notice Issued",BU27="Board",BU27="Closed"),"Y","N") | CD27: Ryan Hamilton | CE27: (417) 882-1701 | CF27: ryanhamilton@hamiltoncorporation.com | CG27: Teresa Morales | CH27: (512) 475-3344
A28: 2026-02-10 | B28: 2026-02-10 | C28: 25425 | E28: Bridge at Treeline | F28: Austin | G28: Travis | H28: 7 | I28: 12201 Heatherly Drive | J28: 78747 | K28: 45671 | L28: Withdrawn | M28: 45757 | O28: 45672 | P28: 45852 | R28: New Construction | S28: General | T28: 330 | U28: 330 | X28: Austin Affordable PFC | Y28: Other | Z28: 40000000 | AB28: 2443032 | AF28: N | AG28: Y | AH28: Y | AI28: Y | AK28: Y | AL28: Y | AM28: Y | AS28: N | AX28: N | AY28: Y | AZ28: Y | BA28: Y | BB28: Y | BC28: Y | BE28: N | BJ28: Y | BK28: N | BL28: N | BM28: Y | BN28: Y | BO28: 45671 | BP28: Y | BQ28: N | BR28: =IF(COUNTIF(AI28:BM28,"N")+COUNTBLANK(AI28:BM28)=0,"Y","N") | BS28: =IF(AND(BR28="Y",OR(L28="Submitted",L28="Under Review")),"Y",IF(L28="Closed","Y","N")) | BT28: 29 | BU28: =Rule_Flags!Q27 | BV28: =Rule_Flags!P27 | BW28: =IF(Rule_Flags!E27=1,"SITE_CONTROL",IF(Rule_Flags!F27=1,"APPROVALS",IF(Rule_Flags!G27=1,"REPORTS",IF(Rule_Flags!H27=1,"DEFICIENCY",IF(Rule_Flags!I27=1,"UNDERWRITING",IF(Rule_Flags!J27=1,"COMPLIANCE","")))))) | BX28: =IF(BW28="SITE_CONTROL","Site control missing or invalid",IF(BW28="APPROVALS","Required approvals or resolutions incomplete",IF(BW28="REPORTS","Required third-party reports incomplete",IF(BW28="DEFICIENCY","Unresolved deficiency or material deficiency",IF(BW28="UNDERWRITING","Underwriting / feasibility not passed",IF(BW28="COMPLIANCE","Deconcentration, one-mile, LURA, or Chapter 12 issue","Ready under current engine rules")))))) | BY28: =IF(BV28="Determination Notice","Streamlined + DN-ready assumptions satisfied",IF(BV28="Board","Board-required or board-ready assumptions satisfied","")) | BZ28: =IF(AND(BP28="Y",BQ28<>"Y"),"Carryforward project retains queue priority",IF(BQ28="Y","New project enters behind carryforward projects","")) | CA28: =_xludf.RANK.EQ(Rule_Flags!O27,Rule_Flags!$O$3:$O$402,0) | CB28: =IF(OR(BU28="Determination Notice Issued",BU28="Board",BU28="Closed"),"Y","N") | CC28: construction_type mapped from raw 'NC' to 'New Construction' | CD28: Sam Kumar | CE28: (512) 247-7000 | CF28: SKumar@journeymangroup.com | CG28: Ron Kowal | CH28: 512‐477‐4488
A29: 2026-02-10 | B29: 2026-02-10 | C29: 25431 | D29: 93101 | E29: The Meadows | F29: Garland | G29: Dallas | H29: 3 | I29: 3826 Easton Meadows Drive | J29: 75043 | K29: 45671 | L29: Withdrawn | M29: 45820 | O29: 45672 | P29: 45852 | R29: Acq/Rehab | S29: General | T29: 152 | U29: 152 | X29: Texas Home Collaborative | Y29: Other | Z29: 25000000 | AB29: 1527490 | AF29: N | AG29: Y | AI29: Y | AK29: Y | AL29: Y | AM29: Y | AS29: N | AX29: N | AY29: Y | AZ29: Y | BA29: Y | BB29: Y | BC29: Y | BE29: N | BJ29: Y | BK29: N | BL29: N | BM29: Y | BN29: Y | BO29: 45671 | BP29: Y | BQ29: N | BR29: =IF(COUNTIF(AI29:BM29,"N")+COUNTBLANK(AI29:BM29)=0,"Y","N") | BS29: =IF(AND(BR29="Y",OR(L29="Submitted",L29="Under Review")),"Y",IF(L29="Closed","Y","N")) | BT29: 30 | BU29: =Rule_Flags!Q28 | BV29: =Rule_Flags!P28 | BW29: =IF(Rule_Flags!E28=1,"SITE_CONTROL",IF(Rule_Flags!F28=1,"APPROVALS",IF(Rule_Flags!G28=1,"REPORTS",IF(Rule_Flags!H28=1,"DEFICIENCY",IF(Rule_Flags!I28=1,"UNDERWRITING",IF(Rule_Flags!J28=1,"COMPLIANCE","")))))) | BX29: =IF(BW29="SITE_CONTROL","Site control missing or invalid",IF(BW29="APPROVALS","Required approvals or resolutions incomplete",IF(BW29="REPORTS","Required third-party reports incomplete",IF(BW29="DEFICIENCY","Unresolved deficiency or material deficiency",IF(BW29="UNDERWRITING","Underwriting / feasibility not passed",IF(BW29="COMPLIANCE","Deconcentration, one-mile, LURA, or Chapter 12 issue","Ready under current engine rules")))))) | BY29: =IF(BV29="Determination Notice","Streamlined + DN-ready assumptions satisfied",IF(BV29="Board","Board-required or board-ready assumptions satisfied","")) | BZ29: =IF(AND(BP29="Y",BQ29<>"Y"),"Carryforward project retains queue priority",IF(BQ29="Y","New project enters behind carryforward projects","")) | CA29: =_xludf.RANK.EQ(Rule_Flags!O28,Rule_Flags!$O$3:$O$402,0) | CB29: =IF(OR(BU29="Determination Notice Issued",BU29="Board",BU29="Closed"),"Y","N") | CD29: Brad Fisher | CE29: (913) 787-1676 | CF29: bfisher@aprilhousing.com | CG29: Antonio Williams | CH29: (903) 276-7557
A30: 2026-02-10 | B30: 2026-02-10 | C30: 25401 | E30: Enclave at Cypress | F30: Cypress | G30: Harris | H30: 6 | I30: 15815 Merle Road | J30: 77433 | K30: 45671 | L30: Withdrawn | M30: 45785 | O30: 45672 | P30: 45852 | R30: New Construction | S30: General | T30: 363 | U30: 363 | X30: Harris County HFC | Y30: Local HFC | Z30: 50000000 | AB30: 3570057 | AF30: N | AG30: Y | AI30: Y | AK30: Y | AL30: Y | AM30: Y | AS30: N | AX30: N | AY30: Y | AZ30: Y | BA30: Y | BB30: Y | BC30: Y | BE30: N | BJ30: Y | BK30: N | BL30: N | BM30: Y | BN30: Y | BO30: 45671 | BP30: Y | BQ30: N | BR30: =IF(COUNTIF(AI30:BM30,"N")+COUNTBLANK(AI30:BM30)=0,"Y","N") | BS30: =IF(AND(BR30="Y",OR(L30="Submitted",L30="Under Review")),"Y",IF(L30="Closed","Y","N")) | BT30: 26 | BU30: =Rule_Flags!Q29 | BV30: =Rule_Flags!P29 | BW30: =IF(Rule_Flags!E29=1,"SITE_CONTROL",IF(Rule_Flags!F29=1,"APPROVALS",IF(Rule_Flags!G29=1,"REPORTS",IF(Rule_Flags!H29=1,"DEFICIENCY",IF(Rule_Flags!I29=1,"UNDERWRITING",IF(Rule_Flags!J29=1,"COMPLIANCE","")))))) | BX30: =IF(BW30="SITE_CONTROL","Site control missing or invalid",IF(BW30="APPROVALS","Required approvals or resolutions incomplete",IF(BW30="REPORTS","Required third-party reports incomplete",IF(BW30="DEFICIENCY","Unresolved deficiency or material deficiency",IF(BW30="UNDERWRITING","Underwriting / feasibility not passed",IF(BW30="COMPLIANCE","Deconcentration, one-mile, LURA, or Chapter 12 issue","Ready under current engine rules")))))) | BY30: =IF(BV30="Determination Notice","Streamlined + DN-ready assumptions satisfied",IF(BV30="Board","Board-required or board-ready assumptions satisfied","")) | BZ30: =IF(AND(BP30="Y",BQ30<>"Y"),"Carryforward project retains queue priority",IF(BQ30="Y","New project enters behind carryforward projects","")) | CA30: =_xludf.RANK.EQ(Rule_Flags!O29,Rule_Flags!$O$3:$O$402,0) | CB30: =IF(OR(BU30="Determination Notice Issued",BU30="Board",BU30="Closed"),"Y","N") | CC30: construction_type mapped from raw 'NC' to 'New Construction' | CD30: Mark Gregg | CE30: (210) 771-4127 | CF30: mgregg@streamlineap.com | CG30: Rene Martinez | CH30: (832) 927-4955
A31: 2026-02-10 | B31: 2026-02-10 | C31: 25432 | E31: Village at Meadowbend | F31: Temple | G31: Bell | H31: 8 | I31: 2787 S. Martin Luther King Drive | J31: 76504 | K31: 45671 | L31: Withdrawn | M31: 45820 | O31: 45672 | P31: 45852 | R31: Acq/Rehab | S31: General | T31: 237 | U31: 237 | X31: Texas Home Collaborative | Y31: Other | Z31: 25000000 | AB31: 2052801 | AF31: N | AG31: Y | AI31: Y | AK31: Y | AL31: Y | AM31: Y | AS31: N | AX31: N | AY31: Y | AZ31: Y | BA31: Y | BB31: Y | BC31: Y | BE31: N | BJ31: Y | BK31: N | BL31: N | BM31: Y | BN31: Y | BO31: 45671 | BP31: Y | BQ31: N | BR31: =IF(COUNTIF(AI31:BM31,"N")+COUNTBLANK(AI31:BM31)=0,"Y","N") | BS31: =IF(AND(BR31="Y",OR(L31="Submitted",L31="Under Review")),"Y",IF(L31="Closed","Y","N")) | BT31: 31 | BU31: =Rule_Flags!Q30 | BV31: =Rule_Flags!P30 | BW31: =IF(Rule_Flags!E30=1,"SITE_CONTROL",IF(Rule_Flags!F30=1,"APPROVALS",IF(Rule_Flags!G30=1,"REPORTS",IF(Rule_Flags!H30=1,"DEFICIENCY",IF(Rule_Flags!I30=1,"UNDERWRITING",IF(Rule_Flags!J30=1,"COMPLIANCE","")))))) | BX31: =IF(BW31="SITE_CONTROL","Site control missing or invalid",IF(BW31="APPROVALS","Required approvals or resolutions incomplete",IF(BW31="REPORTS","Required third-party reports incomplete",IF(BW31="DEFICIENCY","Unresolved deficiency or material deficiency",IF(BW31="UNDERWRITING","Underwriting / feasibility not passed",IF(BW31="COMPLIANCE","Deconcentration, one-mile, LURA, or Chapter 12 issue","Ready under current engine rules")))))) | BY31: =IF(BV31="Determination Notice","Streamlined + DN-ready assumptions satisfied",IF(BV31="Board","Board-required or board-ready assumptions satisfied","")) | BZ31: =IF(AND(BP31="Y",BQ31<>"Y"),"Carryforward project retains queue priority",IF(BQ31="Y","New project enters behind carryforward projects","")) | CA31: =_xludf.RANK.EQ(Rule_Flags!O30,Rule_Flags!$O$3:$O$402,0) | CB31: =IF(OR(BU31="Determination Notice Issued",BU31="Board",BU31="Closed"),"Y","N") | CD31: Asia Williams | CE31: (213) 362-0260 | CF31: awilliams@chavezfoundation.org | CG31: Antonio Williams | CH31: (903) 276-7557
A32: 2026-02-10 | B32: 2026-02-10 | C32: 25407 | D32: 03436 | E32: Northland Woods | F32: Houston | G32: Harris | H32: 6 | I32: 15165 Vickery Drive | J32: 77032 | K32: 45671 | L32: Withdrawn | M32: 45785 | O32: 45673 | P32: 45853 | R32: Acq/Rehab | S32: General | T32: 280 | U32: 280 | X32: HHA Fountainview PFC | Y32: Other | Z32: 45000000 | AB32: 3400940 | AF32: N | AG32: Y | AH32: Y | AI32: Y | AK32: Y | AL32: Y | AM32: Y | AS32: N | AX32: N | AY32: Y | AZ32: Y | BA32: Y | BB32: Y | BC32: Y | BE32: N | BJ32: Y | BK32: N | BL32: N | BM32: Y | BN32: Y | BO32: 45671 | BP32: Y | BQ32: N | BR32: =IF(COUNTIF(AI32:BM32,"N")+COUNTBLANK(AI32:BM32)=0,"Y","N") | BS32: =IF(AND(BR32="Y",OR(L32="Submitted",L32="Under Review")),"Y",IF(L32="Closed","Y","N")) | BT32: 28 | BU32: =Rule_Flags!Q31 | BV32: =Rule_Flags!P31 | BW32: =IF(Rule_Flags!E31=1,"SITE_CONTROL",IF(Rule_Flags!F31=1,"APPROVALS",IF(Rule_Flags!G31=1,"REPORTS",IF(Rule_Flags!H31=1,"DEFICIENCY",IF(Rule_Flags!I31=1,"UNDERWRITING",IF(Rule_Flags!J31=1,"COMPLIANCE","")))))) | BX32: =IF(BW32="SITE_CONTROL","Site control missing or invalid",IF(BW32="APPROVALS","Required approvals or resolutions incomplete",IF(BW32="REPORTS","Required third-party reports incomplete",IF(BW32="DEFICIENCY","Unresolved deficiency or material deficiency",IF(BW32="UNDERWRITING","Underwriting / feasibility not passed",IF(BW32="COMPLIANCE","Deconcentration, one-mile, LURA, or Chapter 12 issue","Ready under current engine rules")))))) | BY32: =IF(BV32="Determination Notice","Streamlined + DN-ready assumptions satisfied",IF(BV32="Board","Board-required or board-ready assumptions satisfied","")) | BZ32: =IF(AND(BP32="Y",BQ32<>"Y"),"Carryforward project retains queue priority",IF(BQ32="Y","New project enters behind carryforward projects","")) | CA32: =_xludf.RANK.EQ(Rule_Flags!O31,Rule_Flags!$O$3:$O$402,0) | CB32: =IF(OR(BU32="Determination Notice Issued",BU32="Board",BU32="Closed"),"Y","N") | CD32: Brad Fisher | CE32: (913) 787-1676 | CF32: bfisher@aprilhousing.com | CG32: Jennine Hovell-Cox | CH32: (713) 260-0501
A33: 2026-02-10 | B33: 2026-02-10 | C33: 25403 | D33: CMTS 2514 | E33: Waters at Stone Creek | F33: Lewisville | G33: Denton | H33: 3 | I33: 328 E Southwest Parkway | J33: 75067 | K33: 45671 | L33: Approved | M33: 45757 | N33: 45789 | O33: 45882 | P33: 46062 | R33: Acq/Rehab | S33: General | T33: 199 | U33: 199 | X33: Denton County HFC | Y33: Local HFC | Z33: 30000000 | AB33: 2213923 | AC33: 2213923 | AF33: N | AG33: Y | AI33: Y | AK33: Y | AL33: Y | AM33: Y | AS33: N | AX33: N | AY33: Y | AZ33: Y | BA33: Y | BB33: Y | BC33: Y | BE33: N | BJ33: Y | BK33: N | BL33: N | BM33: Y | BN33: Y | BO33: 45671 | BP33: Y | BQ33: N | BR33: =IF(COUNTIF(AI33:BM33,"N")+COUNTBLANK(AI33:BM33)=0,"Y","N") | BS33: =IF(AND(BR33="Y",OR(L33="Submitted",L33="Under Review")),"Y",IF(L33="Closed","Y","N")) | BT33: 27 | BU33: =Rule_Flags!Q32 | BV33: =Rule_Flags!P32 | BW33: =IF(Rule_Flags!E32=1,"SITE_CONTROL",IF(Rule_Flags!F32=1,"APPROVALS",IF(Rule_Flags!G32=1,"REPORTS",IF(Rule_Flags!H32=1,"DEFICIENCY",IF(Rule_Flags!I32=1,"UNDERWRITING",IF(Rule_Flags!J32=1,"COMPLIANCE","")))))) | BX33: =IF(BW33="SITE_CONTROL","Site control missing or invalid",IF(BW33="APPROVALS","Required approvals or resolutions incomplete",IF(BW33="REPORTS","Required third-party reports incomplete",IF(BW33="DEFICIENCY","Unresolved deficiency or material deficiency",IF(BW33="UNDERWRITING","Underwriting / feasibility not passed",IF(BW33="COMPLIANCE","Deconcentration, one-mile, LURA, or Chapter 12 issue","Ready under current engine rules")))))) | BY33: =IF(BV33="Determination Notice","Streamlined + DN-ready assumptions satisfied",IF(BV33="Board","Board-required or board-ready assumptions satisfied","")) | BZ33: =IF(AND(BP33="Y",BQ33<>"Y"),"Carryforward project retains queue priority",IF(BQ33="Y","New project enters behind carryforward projects","")) | CA33: =_xludf.RANK.EQ(Rule_Flags!O32,Rule_Flags!$O$3:$O$402,0) | CB33: =IF(OR(BU33="Determination Notice Issued",BU33="Board",BU33="Closed"),"Y","N") | CD33: Rafael Navarro | CE33: (469) 206-8930 | CF33: navarro@atlantichousing.org | CG33: Andy Eads | CH33: (904) 349-2801
A34: 2026-02-10 | B34: 2026-02-10 | C34: 25422 | E34: Covington Acres | F34: Keene | G34: Johnson | H34: 3 | I34: 2632 US Highway 67 | J34: 76031 | K34: 45673 | L34: Closed | M34: 45785 | N34: 45769 | O34: 45674 | P34: 45854 | R34: New Construction | S34: General | T34: 252 | U34: 252 | X34: THF PFC | Y34: Other | Z34: 40000000 | AB34: 2926539 | AC34: 2905038 | AF34: N | AG34: Y | AH34: Y | AI34: Y | AK34: Y | AL34: Y | AM34: Y | AS34: N | AX34: N | AY34: Y | AZ34: Y | BA34: Y | BB34: Y | BC34: Y | BE34: N | BJ34: Y | BK34: N | BL34: N | BM34: Y | BN34: Y | BO34: 45673 | BP34: Y | BQ34: N | BR34: =IF(COUNTIF(AI34:BM34,"N")+COUNTBLANK(AI34:BM34)=0,"Y","N") | BS34: =IF(AND(BR34="Y",OR(L34="Submitted",L34="Under Review")),"Y",IF(L34="Closed","Y","N")) | BT34: 32 | BU34: =Rule_Flags!Q33 | BV34: =Rule_Flags!P33 | BW34: =IF(Rule_Flags!E33=1,"SITE_CONTROL",IF(Rule_Flags!F33=1,"APPROVALS",IF(Rule_Flags!G33=1,"REPORTS",IF(Rule_Flags!H33=1,"DEFICIENCY",IF(Rule_Flags!I33=1,"UNDERWRITING",IF(Rule_Flags!J33=1,"COMPLIANCE","")))))) | BX34: =IF(BW34="SITE_CONTROL","Site control missing or invalid",IF(BW34="APPROVALS","Required approvals or resolutions incomplete",IF(BW34="REPORTS","Required third-party reports incomplete",IF(BW34="DEFICIENCY","Unresolved deficiency or material deficiency",IF(BW34="UNDERWRITING","Underwriting / feasibility not passed",IF(BW34="COMPLIANCE","Deconcentration, one-mile, LURA, or Chapter 12 issue","Ready under current engine rules")))))) | BY34: =IF(BV34="Determination Notice","Streamlined + DN-ready assumptions satisfied",IF(BV34="Board","Board-required or board-ready assumptions satisfied","")) | BZ34: =IF(AND(BP34="Y",BQ34<>"Y"),"Carryforward project retains queue priority",IF(BQ34="Y","New project enters behind carryforward projects","")) | CA34: =_xludf.RANK.EQ(Rule_Flags!O33,Rule_Flags!$O$3:$O$402,0) | CB34: =IF(OR(BU34="Determination Notice Issued",BU34="Board",BU34="Closed"),"Y","N") | CC34: construction_type mapped from raw 'NC' to 'New Construction' | CD34: Elena Harston | CE34: (925) 586-7619 | CF34: eharston@kittleproperties.com | CG34: Jonathan Coreas | CH34: (830) 693‐8100
A35: 2026-02-10 | B35: 2026-02-10 | C35: 25445 | E35: Enclave at Sherman | F35: Sherman | G35: Grayson | H35: 3 | I35: 2700 US-82 | J35: 75090 | K35: 45679 | L35: Withdrawn | M35: 45785 | O35: 45680 | P35: 45860 | R35: New Construction | S35: General | T35: 360 | U35: 360 | X35: THF PFC | Y35: Other | Z35: 50000000 | AB35: 3572847 | AF35: N | AG35: Y | AH35: Y | AI35: Y | AK35: Y | AL35: Y | AM35: Y | AS35: N | AX35: N | AY35: Y | AZ35: Y | BA35: Y | BB35: Y | BC35: Y | BE35: N | BJ35: Y | BK35: N | BL35: N | BM35: Y | BN35: Y | BO35: 45679 | BP35: Y | BQ35: N | BR35: =IF(COUNTIF(AI35:BM35,"N")+COUNTBLANK(AI35:BM35)=0,"Y","N") | BS35: =IF(AND(BR35="Y",OR(L35="Submitted",L35="Under Review")),"Y",IF(L35="Closed","Y","N")) | BT35: 33 | BU35: =Rule_Flags!Q34 | BV35: =Rule_Flags!P34 | BW35: =IF(Rule_Flags!E34=1,"SITE_CONTROL",IF(Rule_Flags!F34=1,"APPROVALS",IF(Rule_Flags!G34=1,"REPORTS",IF(Rule_Flags!H34=1,"DEFICIENCY",IF(Rule_Flags!I34=1,"UNDERWRITING",IF(Rule_Flags!J34=1,"COMPLIANCE","")))))) | BX35: =IF(BW35="SITE_CONTROL","Site control missing or invalid",IF(BW35="APPROVALS","Required approvals or resolutions incomplete",IF(BW35="REPORTS","Required third-party reports incomplete",IF(BW35="DEFICIENCY","Unresolved deficiency or material deficiency",IF(BW35="UNDERWRITING","Underwriting / feasibility not passed",IF(BW35="COMPLIANCE","Deconcentration, one-mile, LURA, or Chapter 12 issue","Ready under current engine rules")))))) | BY35: =IF(BV35="Determination Notice","Streamlined + DN-ready assumptions satisfied",IF(BV35="Board","Board-required or board-ready assumptions satisfied","")) | BZ35: =IF(AND(BP35="Y",BQ35<>"Y"),"Carryforward project retains queue priority",IF(BQ35="Y","New project enters behind carryforward projects","")) | CA35: =_xludf.RANK.EQ(Rule_Flags!O34,Rule_Flags!$O$3:$O$402,0) | CB35: =IF(OR(BU35="Determination Notice Issued",BU35="Board",BU35="Closed"),"Y","N") | CC35: construction_type mapped from raw 'NC' to 'New Construction' | CD35: Mark Gregg | CE35: (210) 771-4127 | CF35: mgregg@streamlineap.com | CG35: Allison Millihorn | CH35: (830) 693-8100
A36: 2026-02-10 | B36: 2026-02-10 | C36: 25418 | E36: Parmer North Apartments | F36: Pflugerville | G36: Travis | H36: 7 | I36: 1420 E Howard Lane | J36: 78660 | K36: 45680 | L36: Withdrawn | M36: 45785 | O36: 45680 | P36: 45860 | R36: New Construction | S36: General | T36: 288 | U36: 288 | X36: Travis County HFC | Y36: Local HFC | Z36: 40000000 | AB36: 2254150 | AF36: N | AG36: Y | AI36: Y | AK36: Y | AL36: Y | AM36: Y | AS36: N | AX36: N | AY36: Y | AZ36: Y | BA36: Y | BB36: Y | BC36: Y | BE36: N | BJ36: Y | BK36: N | BL36: N | BM36: Y | BN36: Y | BO36: 45680 | BP36: Y | BQ36: N | BR36: =IF(COUNTIF(AI36:BM36,"N")+COUNTBLANK(AI36:BM36)=0,"Y","N") | BS36: =IF(AND(BR36="Y",OR(L36="Submitted",L36="Under Review")),"Y",IF(L36="Closed","Y","N")) | BT36: 34 | BU36: =Rule_Flags!Q35 | BV36: =Rule_Flags!P35 | BW36: =IF(Rule_Flags!E35=1,"SITE_CONTROL",IF(Rule_Flags!F35=1,"APPROVALS",IF(Rule_Flags!G35=1,"REPORTS",IF(Rule_Flags!H35=1,"DEFICIENCY",IF(Rule_Flags!I35=1,"UNDERWRITING",IF(Rule_Flags!J35=1,"COMPLIANCE","")))))) | BX36: =IF(BW36="SITE_CONTROL","Site control missing or invalid",IF(BW36="APPROVALS","Required approvals or resolutions incomplete",IF(BW36="REPORTS","Required third-party reports incomplete",IF(BW36="DEFICIENCY","Unresolved deficiency or material deficiency",IF(BW36="UNDERWRITING","Underwriting / feasibility not passed",IF(BW36="COMPLIANCE","Deconcentration, one-mile, LURA, or Chapter 12 issue","Ready under current engine rules")))))) | BY36: =IF(BV36="Determination Notice","Streamlined + DN-ready assumptions satisfied",IF(BV36="Board","Board-required or board-ready assumptions satisfied","")) | BZ36: =IF(AND(BP36="Y",BQ36<>"Y"),"Carryforward project retains queue priority",IF(BQ36="Y","New project enters behind carryforward projects","")) | CA36: =_xludf.RANK.EQ(Rule_Flags!O35,Rule_Flags!$O$3:$O$402,0) | CB36: =IF(OR(BU36="Determination Notice Issued",BU36="Board",BU36="Closed"),"Y","N") | CC36: construction_type mapped from raw 'NC' to 'New Construction' | CD36: Sam Kumar | CE36: (512) 247-7000 | CF36: SKumar@journeymangroup.com | CG36: Christy Moffett | CH36: (512) 854-1161
A37: 2026-02-10 | B37: 2026-02-10 | C37: 25447 | D37: 24490 | E37: Columbia Renaissance Square | F37: Fort Worth | G37: Tarrant | H37: 3 | I37: 2757 Moresby Street | J37: 76105 | K37: 45684 | L37: Closed | M37: 45757 | N37: 45744 | O37: 45685 | P37: 45865 | R37: New Construction | S37: General | T37: 100 | U37: 100 | X37: Tarrant County HFC | Y37: Local HFC | Z37: 25000000 | AB37: 1465750 | AC37: 1465750 | AF37: N | AG37: N | AI37: Y | AK37: Y | AL37: Y | AM37: Y | AS37: N | AX37: N | AY37: Y | AZ37: Y | BA37: Y | BB37: Y | BC37: Y | BE37: N | BJ37: Y | BK37: N | BL37: N | BM37: Y | BN37: Y | BO37: 45684 | BP37: Y | BQ37: N | BR37: =IF(COUNTIF(AI37:BM37,"N")+COUNTBLANK(AI37:BM37)=0,"Y","N") | BS37: =IF(AND(BR37="Y",OR(L37="Submitted",L37="Under Review")),"Y",IF(L37="Closed","Y","N")) | BT37: 36 | BU37: =Rule_Flags!Q36 | BV37: =Rule_Flags!P36 | BW37: =IF(Rule_Flags!E36=1,"SITE_CONTROL",IF(Rule_Flags!F36=1,"APPROVALS",IF(Rule_Flags!G36=1,"REPORTS",IF(Rule_Flags!H36=1,"DEFICIENCY",IF(Rule_Flags!I36=1,"UNDERWRITING",IF(Rule_Flags!J36=1,"COMPLIANCE","")))))) | BX37: =IF(BW37="SITE_CONTROL","Site control missing or invalid",IF(BW37="APPROVALS","Required approvals or resolutions incomplete",IF(BW37="REPORTS","Required third-party reports incomplete",IF(BW37="DEFICIENCY","Unresolved deficiency or material deficiency",IF(BW37="UNDERWRITING","Underwriting / feasibility not passed",IF(BW37="COMPLIANCE","Deconcentration, one-mile, LURA, or Chapter 12 issue","Ready under current engine rules")))))) | BY37: =IF(BV37="Determination Notice","Streamlined + DN-ready assumptions satisfied",IF(BV37="Board","Board-required or board-ready assumptions satisfied","")) | BZ37: =IF(AND(BP37="Y",BQ37<>"Y"),"Carryforward project retains queue priority",IF(BQ37="Y","New project enters behind carryforward projects","")) | CA37: =_xludf.RANK.EQ(Rule_Flags!O36,Rule_Flags!$O$3:$O$402,0) | CB37: =IF(OR(BU37="Determination Notice Issued",BU37="Board",BU37="Closed"),"Y","N") | CC37: construction_type mapped from raw 'NC' to 'New Construction' | CD37: Clara Trejos | CE37: (404) 867-6921 | CF37: ctrejos@columbiares.com | CG37: Kristen Camareno | CH37: (817) 884-1965
A38: 2026-02-10 | B38: 2026-02-10 | C38: 25442 | E38: Palladium Buckner Station | F38: Dallas | G38: Dallas | H38: 3 | I38: 8008 Elam Road | J38: 75217 | K38: 45684 | L38: Closed | M38: 45785 | N38: 45825 | O38: 45685 | P38: 45865 | R38: New Construction | S38: General | T38: 304 | U38: 244 | X38: City of Dallas HFC | Y38: Local HFC | Z38: 50000000 | AB38: 3390779 | AC38: 3378599 | AF38: N | AG38: Y | AI38: Y | AK38: Y | AL38: Y | AM38: Y | AS38: N | AX38: N | AY38: Y | AZ38: Y | BA38: Y | BB38: Y | BC38: Y | BE38: N | BJ38: Y | BK38: N | BL38: N | BM38: Y | BN38: Y | BO38: 45684 | BP38: Y | BQ38: N | BR38: =IF(COUNTIF(AI38:BM38,"N")+COUNTBLANK(AI38:BM38)=0,"Y","N") | BS38: =IF(AND(BR38="Y",OR(L38="Submitted",L38="Under Review")),"Y",IF(L38="Closed","Y","N")) | BT38: 35 | BU38: =Rule_Flags!Q37 | BV38: =Rule_Flags!P37 | BW38: =IF(Rule_Flags!E37=1,"SITE_CONTROL",IF(Rule_Flags!F37=1,"APPROVALS",IF(Rule_Flags!G37=1,"REPORTS",IF(Rule_Flags!H37=1,"DEFICIENCY",IF(Rule_Flags!I37=1,"UNDERWRITING",IF(Rule_Flags!J37=1,"COMPLIANCE","")))))) | BX38: =IF(BW38="SITE_CONTROL","Site control missing or invalid",IF(BW38="APPROVALS","Required approvals or resolutions incomplete",IF(BW38="REPORTS","Required third-party reports incomplete",IF(BW38="DEFICIENCY","Unresolved deficiency or material deficiency",IF(BW38="UNDERWRITING","Underwriting / feasibility not passed",IF(BW38="COMPLIANCE","Deconcentration, one-mile, LURA, or Chapter 12 issue","Ready under current engine rules")))))) | BY38: =IF(BV38="Determination Notice","Streamlined + DN-ready assumptions satisfied",IF(BV38="Board","Board-required or board-ready assumptions satisfied","")) | BZ38: =IF(AND(BP38="Y",BQ38<>"Y"),"Carryforward project retains queue priority",IF(BQ38="Y","New project enters behind carryforward projects","")) | CA38: =_xludf.RANK.EQ(Rule_Flags!O37,Rule_Flags!$O$3:$O$402,0) | CB38: =IF(OR(BU38="Determination Notice Issued",BU38="Board",BU38="Closed"),"Y","N") | CC38: construction_type mapped from raw 'NC' to 'New Construction' | CD38: Thomas Huth | CE38: (972) 774-4400 | CF38: thuth@palladiumusa.com | CG38: Aaron Eaquinto | CH38: (214) 670-4941
A39: 2026-02-10 | B39: 2026-02-10 | C39: 25451 | D39: 24498 | E39: Mesa Hills I | F39: El Paso | G39: El Paso | H39: 13 | I39: Bluff Canyon Circle and S Mesa Hills Drive | J39: 79912 | K39: 45693 | L39: Approved | M39: 45820 | N39: 45930 | O39: 45667 | P39: 46387 | R39: New Construction | S39: General | T39: 64 | U39: 64 | X39: Alamito PFC | Y39: Other | Z39: 11115876 | AB39: 782057 | AC39: 782057 | AF39: N | AG39: Y | AH39: Y | AI39: Y | AK39: Y | AL39: Y | AM39: Y | AS39: N | AX39: N | AY39: Y | AZ39: Y | BA39: Y | BB39: Y | BC39: Y | BE39: N | BJ39: Y | BK39: N | BL39: N | BM39: Y | BN39: Y | BO39: 45693 | BP39: Y | BQ39: N | BR39: =IF(COUNTIF(AI39:BM39,"N")+COUNTBLANK(AI39:BM39)=0,"Y","N") | BS39: =IF(AND(BR39="Y",OR(L39="Submitted",L39="Under Review")),"Y",IF(L39="Closed","Y","N")) | BT39: 37 | BU39: =Rule_Flags!Q38 | BV39: =Rule_Flags!P38 | BW39: =IF(Rule_Flags!E38=1,"SITE_CONTROL",IF(Rule_Flags!F38=1,"APPROVALS",IF(Rule_Flags!G38=1,"REPORTS",IF(Rule_Flags!H38=1,"DEFICIENCY",IF(Rule_Flags!I38=1,"UNDERWRITING",IF(Rule_Flags!J38=1,"COMPLIANCE","")))))) | BX39: =IF(BW39="SITE_CONTROL","Site control missing or invalid",IF(BW39="APPROVALS","Required approvals or resolutions incomplete",IF(BW39="REPORTS","Required third-party reports incomplete",IF(BW39="DEFICIENCY","Unresolved deficiency or material deficiency",IF(BW39="UNDERWRITING","Underwriting / feasibility not passed",IF(BW39="COMPLIANCE","Deconcentration, one-mile, LURA, or Chapter 12 issue","Ready under current engine rules")))))) | BY39: =IF(BV39="Determination Notice","Streamlined + DN-ready assumptions satisfied",IF(BV39="Board","Board-required or board-ready assumptions satisfied","")) | BZ39: =IF(AND(BP39="Y",BQ39<>"Y"),"Carryforward project retains queue priority",IF(BQ39="Y","New project enters behind carryforward projects","")) | CA39: =_xludf.RANK.EQ(Rule_Flags!O38,Rule_Flags!$O$3:$O$402,0) | CB39: =IF(OR(BU39="Determination Notice Issued",BU39="Board",BU39="Closed"),"Y","N") | CC39: construction_type mapped from raw 'NC' to 'New Construction' | CD39: Satish Bhaskar | CE39: (915) 849-3730 | CF39: sbhaskar@ephome.org | CG39: Satish Bhaskar | CH39: (915) 849-3730
A40: 2026-02-10 | B40: 2026-02-10 | C40: 25449 | D40: 24481 | E40: Enclave on Louetta | F40: Spring | G40: Harris | H40: 6 | I40: 2324 Louetta Road | J40: 77388 | K40: 45695 | L40: Closed | M40: 45785 | N40: 45799 | O40: 45680 | P40: 45860 | R40: New Construction | S40: General | T40: 358 | U40: 358 | X40: HHA Fountainview PFC | Y40: Other | Z40: 50000000 | AB40: 3651702 | AC40: 3646918 | AF40: N | AG40: Y | AH40: Y | AI40: Y | AK40: Y | AL40: Y | AM40: Y | AS40: N | AX40: N | AY40: Y | AZ40: Y | BA40: Y | BB40: Y | BC40: Y | BE40: N | BJ40: Y | BK40: N | BL40: N | BM40: Y | BN40: Y | BO40: 45695 | BP40: Y | BQ40: N | BR40: =IF(COUNTIF(AI40:BM40,"N")+COUNTBLANK(AI40:BM40)=0,"Y","N") | BS40: =IF(AND(BR40="Y",OR(L40="Submitted",L40="Under Review")),"Y",IF(L40="Closed","Y","N")) | BT40: 38 | BU40: =Rule_Flags!Q39 | BV40: =Rule_Flags!P39 | BW40: =IF(Rule_Flags!E39=1,"SITE_CONTROL",IF(Rule_Flags!F39=1,"APPROVALS",IF(Rule_Flags!G39=1,"REPORTS",IF(Rule_Flags!H39=1,"DEFICIENCY",IF(Rule_Flags!I39=1,"UNDERWRITING",IF(Rule_Flags!J39=1,"COMPLIANCE","")))))) | BX40: =IF(BW40="SITE_CONTROL","Site control missing or invalid",IF(BW40="APPROVALS","Required approvals or resolutions incomplete",IF(BW40="REPORTS","Required third-party reports incomplete",IF(BW40="DEFICIENCY","Unresolved deficiency or material deficiency",IF(BW40="UNDERWRITING","Underwriting / feasibility not passed",IF(BW40="COMPLIANCE","Deconcentration, one-mile, LURA, or Chapter 12 issue","Ready under current engine rules")))))) | BY40: =IF(BV40="Determination Notice","Streamlined + DN-ready assumptions satisfied",IF(BV40="Board","Board-required or board-ready assumptions satisfied","")) | BZ40: =IF(AND(BP40="Y",BQ40<>"Y"),"Carryforward project retains queue priority",IF(BQ40="Y","New project enters behind carryforward projects","")) | CA40: =_xludf.RANK.EQ(Rule_Flags!O39,Rule_Flags!$O$3:$O$402,0) | CB40: =IF(OR(BU40="Determination Notice Issued",BU40="Board",BU40="Closed"),"Y","N") | CC40: construction_type mapped from raw 'NC' to 'New Construction' | CD40: Mark Gregg | CE40: (210) 771-4127 | CF40: mgregg@streamlineap.com | CG40: Jennine Hovell-Cox | CH40: (713) 260-0501
A41: 2026-02-10 | B41: 2026-02-10 | C41: 25408 | D41: 060425 | E41: Baypointe Apartments | F41: Webster | G41: Harris | H41: 6 | I41: 901 S. Kobayashi Road | J41: 77598 | K41: 45700 | L41: Closed | M41: 45785 | N41: 45870 | O41: 45709 | P41: 45889 | R41: Acq/Rehab | S41: General | T41: 236 | U41: 236 | X41: Harris County HFC | Y41: Local HFC | Z41: 35000000 | AB41: 2229072 | AC41: 2229072 | AF41: N | AG41: Y | AI41: Y | AK41: Y | AL41: Y | AM41: Y | AS41: N | AX41: N | AY41: Y | AZ41: Y | BA41: Y | BB41: Y | BC41: Y | BE41: N | BJ41: Y | BK41: N | BL41: N | BM41: Y | BN41: Y | BO41: 45700 | BP41: Y | BQ41: N | BR41: =IF(COUNTIF(AI41:BM41,"N")+COUNTBLANK(AI41:BM41)=0,"Y","N") | BS41: =IF(AND(BR41="Y",OR(L41="Submitted",L41="Under Review")),"Y",IF(L41="Closed","Y","N")) | BT41: 39 | BU41: =Rule_Flags!Q40 | BV41: =Rule_Flags!P40 | BW41: =IF(Rule_Flags!E40=1,"SITE_CONTROL",IF(Rule_Flags!F40=1,"APPROVALS",IF(Rule_Flags!G40=1,"REPORTS",IF(Rule_Flags!H40=1,"DEFICIENCY",IF(Rule_Flags!I40=1,"UNDERWRITING",IF(Rule_Flags!J40=1,"COMPLIANCE","")))))) | BX41: =IF(BW41="SITE_CONTROL","Site control missing or invalid",IF(BW41="APPROVALS","Required approvals or resolutions incomplete",IF(BW41="REPORTS","Required third-party reports incomplete",IF(BW41="DEFICIENCY","Unresolved deficiency or material deficiency",IF(BW41="UNDERWRITING","Underwriting / feasibility not passed",IF(BW41="COMPLIANCE","Deconcentration, one-mile, LURA, or Chapter 12 issue","Ready under current engine rules")))))) | BY41: =IF(BV41="Determination Notice","Streamlined + DN-ready assumptions satisfied",IF(BV41="Board","Board-required or board-ready assumptions satisfied","")) | BZ41: =IF(AND(BP41="Y",BQ41<>"Y"),"Carryforward project retains queue priority",IF(BQ41="Y","New project enters behind carryforward projects","")) | CA41: =_xludf.RANK.EQ(Rule_Flags!O40,Rule_Flags!$O$3:$O$402,0) | CB41: =IF(OR(BU41="Determination Notice Issued",BU41="Board",BU41="Closed"),"Y","N") | CD41: Brad Fisher | CE41: (913) 787-1676 | CF41: bfisher@aprilhousing.com | CG41: Rene Martinez | CH41: (832) 927-4955
A42: 2026-02-10 | B42: 2026-02-10 | C42: 25414 | E42: Enclave at Crosby | F42: Crosby | G42: Harris | H42: 6 | I42: 15119 FM 2100 Road | J42: 77532 | K42: 45706 | L42: Withdrawn | M42: 45820 | O42: 45709 | P42: 45889 | R42: New Construction | S42: General | T42: 366 | U42: 366 | X42: Harris County HFC | Y42: Local HFC | Z42: 50000000 | AB42: 3701470 | AF42: N | AG42: Y | AI42: Y | AK42: Y | AL42: Y | AM42: Y | AS42: N | AX42: N | AY42: Y | AZ42: Y | BA42: Y | BB42: Y | BC42: Y | BE42: N | BJ42: Y | BK42: N | BL42: N | BM42: Y | BN42: Y | BO42: 45706 | BP42: Y | BQ42: N | BR42: =IF(COUNTIF(AI42:BM42,"N")+COUNTBLANK(AI42:BM42)=0,"Y","N") | BS42: =IF(AND(BR42="Y",OR(L42="Submitted",L42="Under Review")),"Y",IF(L42="Closed","Y","N")) | BT42: 40 | BU42: =Rule_Flags!Q41 | BV42: =Rule_Flags!P41 | BW42: =IF(Rule_Flags!E41=1,"SITE_CONTROL",IF(Rule_Flags!F41=1,"APPROVALS",IF(Rule_Flags!G41=1,"REPORTS",IF(Rule_Flags!H41=1,"DEFICIENCY",IF(Rule_Flags!I41=1,"UNDERWRITING",IF(Rule_Flags!J41=1,"COMPLIANCE","")))))) | BX42: =IF(BW42="SITE_CONTROL","Site control missing or invalid",IF(BW42="APPROVALS","Required approvals or resolutions incomplete",IF(BW42="REPORTS","Required third-party reports incomplete",IF(BW42="DEFICIENCY","Unresolved deficiency or material deficiency",IF(BW42="UNDERWRITING","Underwriting / feasibility not passed",IF(BW42="COMPLIANCE","Deconcentration, one-mile, LURA, or Chapter 12 issue","Ready under current engine rules")))))) | BY42: =IF(BV42="Determination Notice","Streamlined + DN-ready assumptions satisfied",IF(BV42="Board","Board-required or board-ready assumptions satisfied","")) | BZ42: =IF(AND(BP42="Y",BQ42<>"Y"),"Carryforward project retains queue priority",IF(BQ42="Y","New project enters behind carryforward projects","")) | CA42: =_xludf.RANK.EQ(Rule_Flags!O41,Rule_Flags!$O$3:$O$402,0) | CB42: =IF(OR(BU42="Determination Notice Issued",BU42="Board",BU42="Closed"),"Y","N") | CC42: construction_type mapped from raw 'NC' to 'New Construction' | CD42: Mark Gregg | CE42: (210) 771-4127 | CF42: mgregg@streamlineap.com | CG42: Rene Martinez | CH42: (832) 927-4955
A43: 2026-02-10 | B43: 2026-02-10 | C43: 25424 | E43: Branchview Apartments | F43: Pflugerville | G43: Travis | H43: 7 | I43: 14411 Immanuel Road | J43: 78660 | K43: 45715 | L43: Withdrawn | M43: 45820 | O43: 45715 | P43: 45895 | R43: New Construction | S43: General | T43: 330 | U43: 330 | X43: Strategic HFC of Travis County | Y43: Local HFC | Z43: 42000000 | AB43: 2358288 | AF43: N | AG43: Y | AI43: Y | AK43: Y | AL43: Y | AM43: Y | AS43: N | AX43: N | AY43: Y | AZ43: Y | BA43: Y | BB43: Y | BC43: Y | BE43: N | BJ43: Y | BK43: N | BL43: N | BM43: Y | BN43: Y | BO43: 45715 | BP43: Y | BQ43: N | BR43: =IF(COUNTIF(AI43:BM43,"N")+COUNTBLANK(AI43:BM43)=0,"Y","N") | BS43: =IF(AND(BR43="Y",OR(L43="Submitted",L43="Under Review")),"Y",IF(L43="Closed","Y","N")) | BT43: 41 | BU43: =Rule_Flags!Q42 | BV43: =Rule_Flags!P42 | BW43: =IF(Rule_Flags!E42=1,"SITE_CONTROL",IF(Rule_Flags!F42=1,"APPROVALS",IF(Rule_Flags!G42=1,"REPORTS",IF(Rule_Flags!H42=1,"DEFICIENCY",IF(Rule_Flags!I42=1,"UNDERWRITING",IF(Rule_Flags!J42=1,"COMPLIANCE","")))))) | BX43: =IF(BW43="SITE_CONTROL","Site control missing or invalid",IF(BW43="APPROVALS","Required approvals or resolutions incomplete",IF(BW43="REPORTS","Required third-party reports incomplete",IF(BW43="DEFICIENCY","Unresolved deficiency or material deficiency",IF(BW43="UNDERWRITING","Underwriting / feasibility not passed",IF(BW43="COMPLIANCE","Deconcentration, one-mile, LURA, or Chapter 12 issue","Ready under current engine rules")))))) | BY43: =IF(BV43="Determination Notice","Streamlined + DN-ready assumptions satisfied",IF(BV43="Board","Board-required or board-ready assumptions satisfied","")) | BZ43: =IF(AND(BP43="Y",BQ43<>"Y"),"Carryforward project retains queue priority",IF(BQ43="Y","New project enters behind carryforward projects","")) | CA43: =_xludf.RANK.EQ(Rule_Flags!O42,Rule_Flags!$O$3:$O$402,0) | CB43: =IF(OR(BU43="Determination Notice Issued",BU43="Board",BU43="Closed"),"Y","N") | CC43: construction_type mapped from raw 'NC' to 'New Construction' | CD43: Sam Kumar | CE43: (512) 247-7000 | CF43: SKumar@journeymangroup.com | CG43: Dianna Grey | CH43: 512‐562‐9204
A44: 2026-02-10 | B44: 2026-02-10 | C44: 25450 | E44: Little Elm Family Apartments | F44: Little Elm | G44: Denton | H44: 3 | I44: 3655 FM 720 | J44: 75068 | K44: 45719 | L44: Withdrawn | M44: 45820 | O44: 45709 | P44: 45889 | R44: New Construction | S44: General | T44: 288 | U44: 288 | X44: THF PFC | Y44: Other | Z44: 69152737 | AB44: 5384306 | AF44: N | AG44: Y | AH44: Y | AI44: Y | AK44: Y | AL44: Y | AM44: Y | AS44: N | AX44: N | AY44: Y | AZ44: Y | BA44: Y | BB44: Y | BC44: Y | BE44: N | BJ44: Y | BK44: N | BL44: N | BM44: Y | BN44: Y | BO44: 45719 | BP44: Y | BQ44: N | BR44: =IF(COUNTIF(AI44:BM44,"N")+COUNTBLANK(AI44:BM44)=0,"Y","N") | BS44: =IF(AND(BR44="Y",OR(L44="Submitted",L44="Under Review")),"Y",IF(L44="Closed","Y","N")) | BT44: 42 | BU44: =Rule_Flags!Q43 | BV44: =Rule_Flags!P43 | BW44: =IF(Rule_Flags!E43=1,"SITE_CONTROL",IF(Rule_Flags!F43=1,"APPROVALS",IF(Rule_Flags!G43=1,"REPORTS",IF(Rule_Flags!H43=1,"DEFICIENCY",IF(Rule_Flags!I43=1,"UNDERWRITING",IF(Rule_Flags!J43=1,"COMPLIANCE","")))))) | BX44: =IF(BW44="SITE_CONTROL","Site control missing or invalid",IF(BW44="APPROVALS","Required approvals or resolutions incomplete",IF(BW44="REPORTS","Required third-party reports incomplete",IF(BW44="DEFICIENCY","Unresolved deficiency or material deficiency",IF(BW44="UNDERWRITING","Underwriting / feasibility not passed",IF(BW44="COMPLIANCE","Deconcentration, one-mile, LURA, or Chapter 12 issue","Ready under current engine rules")))))) | BY44: =IF(BV44="Determination Notice","Streamlined + DN-ready assumptions satisfied",IF(BV44="Board","Board-required or board-ready assumptions satisfied","")) | BZ44: =IF(AND(BP44="Y",BQ44<>"Y"),"Carryforward project retains queue priority",IF(BQ44="Y","New project enters behind carryforward projects","")) | CA44: =_xludf.RANK.EQ(Rule_Flags!O43,Rule_Flags!$O$3:$O$402,0) | CB44: =IF(OR(BU44="Determination Notice Issued",BU44="Board",BU44="Closed"),"Y","N") | CC44: construction_type mapped from raw 'NC' to 'New Construction' | CD44: Neal Route | CE44: (214) 960-1162 | CF44: nroute@dominiuminc.com | CG44: Allison Millihorn | CH44: (830) 693-8100
A45: 2026-02-10 | B45: 2026-02-10 | C45: 25603 | E45: Legacy on Kiest | F45: Dallas | G45: Dallas | H45: 3 | I45: 2621 Southerland Avenue | J45: 75203 | K45: 3/5/205 | L45: Closed | M45: 45820 | O45: 45665 | P45: 46387 | R45: New Construction | S45: General | T45: 180 | U45: 180 | X45: TDHCA | Y45: TDHCA | Z45: 30000000 | AA45: 30000000 | AB45: 2509813 | AC45: 2509813 | AF45: N | AG45: Y | AI45: Y | AK45: Y | AL45: Y | AM45: Y | AS45: N | AX45: N | AY45: Y | AZ45: Y | BA45: Y | BB45: Y | BC45: Y | BE45: N | BJ45: Y | BK45: N | BL45: N | BM45: Y | BN45: Y | BO45: 3/5/205 | BP45: Y | BQ45: N | BR45: =IF(COUNTIF(AI45:BM45,"N")+COUNTBLANK(AI45:BM45)=0,"Y","N") | BS45: =IF(AND(BR45="Y",OR(L45="Submitted",L45="Under Review")),"Y",IF(L45="Closed","Y","N")) | BT45: 90 | BU45: =Rule_Flags!Q44 | BV45: =Rule_Flags!P44 | BW45: =IF(Rule_Flags!E44=1,"SITE_CONTROL",IF(Rule_Flags!F44=1,"APPROVALS",IF(Rule_Flags!G44=1,"REPORTS",IF(Rule_Flags!H44=1,"DEFICIENCY",IF(Rule_Flags!I44=1,"UNDERWRITING",IF(Rule_Flags!J44=1,"COMPLIANCE","")))))) | BX45: =IF(BW45="SITE_CONTROL","Site control missing or invalid",IF(BW45="APPROVALS","Required approvals or resolutions incomplete",IF(BW45="REPORTS","Required third-party reports incomplete",IF(BW45="DEFICIENCY","Unresolved deficiency or material deficiency",IF(BW45="UNDERWRITING","Underwriting / feasibility not passed",IF(BW45="COMPLIANCE","Deconcentration, one-mile, LURA, or Chapter 12 issue","Ready under current engine rules")))))) | BY45: =IF(BV45="Determination Notice","Streamlined + DN-ready assumptions satisfied",IF(BV45="Board","Board-required or board-ready assumptions satisfied","")) | BZ45: =IF(AND(BP45="Y",BQ45<>"Y"),"Carryforward project retains queue priority",IF(BQ45="Y","New project enters behind carryforward projects","")) | CA45: =_xludf.RANK.EQ(Rule_Flags!O44,Rule_Flags!$O$3:$O$402,0) | CB45: =IF(OR(BU45="Determination Notice Issued",BU45="Board",BU45="Closed"),"Y","N") | CC45: construction_type mapped from raw 'NC' to 'New Construction' | CD45: Jason Trevino | CE45: (512) 578-8488 | CF45: jtrevino@ldgdevelopment.com | CG45: Teresa Morales | CH45: (512) 475-3344
A46: 2026-02-10 | B46: 2026-02-10 | C46: 25448 | D46: 060402 | E46: Hillcrest Manor | F46: Lubbock | G46: Lubbock | H46: 1 | I46: 1102 N Memphis Avenue | J46: 79415 | K46: 45721 | L46: Closed | M46: 45820 | N46: 45838 | O46: 45890 | P46: 46070 | R46: Acq/Rehab | S46: Elderly | T46: 220 | U46: 220 | X46: Lubbock HFC | Y46: Local HFC | Z46: 25000000 | AB46: 1548393 | AC46: 1548393 | AF46: N | AG46: Y | AI46: Y | AK46: Y | AL46: Y | AM46: Y | AS46: N | AX46: N | AY46: Y | AZ46: Y | BA46: Y | BB46: Y | BC46: Y | BE46: N | BJ46: Y | BK46: N | BL46: N | BM46: Y | BN46: Y | BO46: 45721 | BP46: Y | BQ46: N | BR46: =IF(COUNTIF(AI46:BM46,"N")+COUNTBLANK(AI46:BM46)=0,"Y","N") | BS46: =IF(AND(BR46="Y",OR(L46="Submitted",L46="Under Review")),"Y",IF(L46="Closed","Y","N")) | BT46: 43 | BU46: =Rule_Flags!Q45 | BV46: =Rule_Flags!P45 | BW46: =IF(Rule_Flags!E45=1,"SITE_CONTROL",IF(Rule_Flags!F45=1,"APPROVALS",IF(Rule_Flags!G45=1,"REPORTS",IF(Rule_Flags!H45=1,"DEFICIENCY",IF(Rule_Flags!I45=1,"UNDERWRITING",IF(Rule_Flags!J45=1,"COMPLIANCE","")))))) | BX46: =IF(BW46="SITE_CONTROL","Site control missing or invalid",IF(BW46="APPROVALS","Required approvals or resolutions incomplete",IF(BW46="REPORTS","Required third-party reports incomplete",IF(BW46="DEFICIENCY","Unresolved deficiency or material deficiency",IF(BW46="UNDERWRITING","Underwriting / feasibility not passed",IF(BW46="COMPLIANCE","Deconcentration, one-mile, LURA, or Chapter 12 issue","Ready under current engine rules")))))) | BY46: =IF(BV46="Determination Notice","Streamlined + DN-ready assumptions satisfied",IF(BV46="Board","Board-required or board-ready assumptions satisfied","")) | BZ46: =IF(AND(BP46="Y",BQ46<>"Y"),"Carryforward project retains queue priority",IF(BQ46="Y","New project enters behind carryforward projects","")) | CA46: =_xludf.RANK.EQ(Rule_Flags!O45,Rule_Flags!$O$3:$O$402,0) | CB46: =IF(OR(BU46="Determination Notice Issued",BU46="Board",BU46="Closed"),"Y","N") | CD46: Tyler Hunt | CE46: (334) 954-4458 | CF46: tyler.hunt@envolvellc.com | CG46: Shari Flynn | CH46: (806) 745-9559
A47: 2026-02-10 | B47: 2026-02-10 | C47: 25458 | D47: 24452 | E47: Liberty Hill Apts | F47: Liberty Hill | G47: Williamson | H47: 7 | I47: W State Hwy 29 & Butler Farms Blvd | J47: 78642 | K47: 45721 | L47: Withdrawn | M47: 45848 | O47: 45723 | P47: 45903 | R47: New Construction | S47: General | T47: 324 | U47: 324 | X47: Capital Area HFC | Y47: Local HFC | Z47: 69152737 | AB47: 4486344 | AF47: N | AG47: Y | AI47: Y | AK47: Y | AL47: Y | AM47: Y | AS47: N | AX47: N | AY47: Y | AZ47: Y | BA47: Y | BB47: Y | BC47: Y | BE47: N | BJ47: Y | BK47: N | BL47: N | BM47: Y | BN47: Y | BO47: 45721 | BP47: Y | BQ47: N | BR47: =IF(COUNTIF(AI47:BM47,"N")+COUNTBLANK(AI47:BM47)=0,"Y","N") | BS47: =IF(AND(BR47="Y",OR(L47="Submitted",L47="Under Review")),"Y",IF(L47="Closed","Y","N")) | BT47: 44 | BU47: =Rule_Flags!Q46 | BV47: =Rule_Flags!P46 | BW47: =IF(Rule_Flags!E46=1,"SITE_CONTROL",IF(Rule_Flags!F46=1,"APPROVALS",IF(Rule_Flags!G46=1,"REPORTS",IF(Rule_Flags!H46=1,"DEFICIENCY",IF(Rule_Flags!I46=1,"UNDERWRITING",IF(Rule_Flags!J46=1,"COMPLIANCE","")))))) | BX47: =IF(BW47="SITE_CONTROL","Site control missing or invalid",IF(BW47="APPROVALS","Required approvals or resolutions incomplete",IF(BW47="REPORTS","Required third-party reports incomplete",IF(BW47="DEFICIENCY","Unresolved deficiency or material deficiency",IF(BW47="UNDERWRITING","Underwriting / feasibility not passed",IF(BW47="COMPLIANCE","Deconcentration, one-mile, LURA, or Chapter 12 issue","Ready under current engine rules")))))) | BY47: =IF(BV47="Determination Notice","Streamlined + DN-ready assumptions satisfied",IF(BV47="Board","Board-required or board-ready assumptions satisfied","")) | BZ47: =IF(AND(BP47="Y",BQ47<>"Y"),"Carryforward project retains queue priority",IF(BQ47="Y","New project enters behind carryforward projects","")) | CA47: =_xludf.RANK.EQ(Rule_Flags!O46,Rule_Flags!$O$3:$O$402,0) | CB47: =IF(OR(BU47="Determination Notice Issued",BU47="Board",BU47="Closed"),"Y","N") | CC47: construction_type mapped from raw 'NC' to 'New Construction' | CD47: Neal Route | CE47: (214) 960-1162 | CF47: nroute@dominiuminc.com | CG47: James E Shaw | CH47: (512) 347-9953
A48: 2026-02-10 | B48: 2026-02-10 | C48: 25459 | E48: The Foundry | F48: Taylor | G48: Williamson | H48: 7 | I48: East of Old Granger Road at N. Main Street | J48: 76574 | K48: 45723 | L48: Withdrawn | M48: 45820 | O48: 45726 | P48: 45906 | R48: New Construction | S48: General | T48: 321 | U48: 321 | X48: Capital Area HFC | Y48: Local HFC | Z48: 50000000 | AB48: 4367618 | AC48: 4241500 | AF48: N | AG48: N | AI48: Y | AK48: Y | AL48: Y | AM48: Y | AS48: N | AX48: N | AY48: Y | AZ48: Y | BA48: Y | BB48: Y | BC48: Y | BE48: N | BJ48: Y | BK48: N | BL48: N | BM48: Y | BN48: Y | BO48: 45723 | BP48: Y | BQ48: N | BR48: =IF(COUNTIF(AI48:BM48,"N")+COUNTBLANK(AI48:BM48)=0,"Y","N") | BS48: =IF(AND(BR48="Y",OR(L48="Submitted",L48="Under Review")),"Y",IF(L48="Closed","Y","N")) | BT48: 46 | BU48: =Rule_Flags!Q47 | BV48: =Rule_Flags!P47 | BW48: =IF(Rule_Flags!E47=1,"SITE_CONTROL",IF(Rule_Flags!F47=1,"APPROVALS",IF(Rule_Flags!G47=1,"REPORTS",IF(Rule_Flags!H47=1,"DEFICIENCY",IF(Rule_Flags!I47=1,"UNDERWRITING",IF(Rule_Flags!J47=1,"COMPLIANCE","")))))) | BX48: =IF(BW48="SITE_CONTROL","Site control missing or invalid",IF(BW48="APPROVALS","Required approvals or resolutions incomplete",IF(BW48="REPORTS","Required third-party reports incomplete",IF(BW48="DEFICIENCY","Unresolved deficiency or material deficiency",IF(BW48="UNDERWRITING","Underwriting / feasibility not passed",IF(BW48="COMPLIANCE","Deconcentration, one-mile, LURA, or Chapter 12 issue","Ready under current engine rules")))))) | BY48: =IF(BV48="Determination Notice","Streamlined + DN-ready assumptions satisfied",IF(BV48="Board","Board-required or board-ready assumptions satisfied","")) | BZ48: =IF(AND(BP48="Y",BQ48<>"Y"),"Carryforward project retains queue priority",IF(BQ48="Y","New project enters behind carryforward projects","")) | CA48: =_xludf.RANK.EQ(Rule_Flags!O47,Rule_Flags!$O$3:$O$402,0) | CB48: =IF(OR(BU48="Determination Notice Issued",BU48="Board",BU48="Closed"),"Y","N") | CC48: construction_type mapped from raw 'NC' to 'New Construction' | CD48: Mark Gregg | CE48: (210) 771-4127 | CF48: mgregg@streamlineap.com | CG48: James E Shaw | CH48: (512) 347-9953
A49: 2026-02-10 | B49: 2026-02-10 | C49: 25443 | E49: Taylor RAD Family Apts | F49: Taylor | G49: Williamson | H49: 7 | I49: 311 East 7th Street | J49: 76754 | K49: 45723 | L49: Closed | M49: 45939 | N49: 46008 | O49: 45670 | P49: 46752 | R49: New Construction | S49: General | T49: 46 | U49: 46 | X49: Texas Home Collaborative | Y49: Other | Z49: 15000000 | AB49: 1036802 | AC49: 1012036 | AF49: N | AG49: Y | AI49: Y | AK49: Y | AL49: Y | AM49: Y | AS49: N | AX49: N | AY49: Y | AZ49: Y | BA49: Y | BB49: Y | BC49: Y | BE49: N | BJ49: Y | BK49: N | BL49: N | BM49: Y | BN49: Y | BO49: 45723 | BP49: Y | BQ49: N | BR49: =IF(COUNTIF(AI49:BM49,"N")+COUNTBLANK(AI49:BM49)=0,"Y","N") | BS49: =IF(AND(BR49="Y",OR(L49="Submitted",L49="Under Review")),"Y",IF(L49="Closed","Y","N")) | BT49: 45 | BU49: =Rule_Flags!Q48 | BV49: =Rule_Flags!P48 | BW49: =IF(Rule_Flags!E48=1,"SITE_CONTROL",IF(Rule_Flags!F48=1,"APPROVALS",IF(Rule_Flags!G48=1,"REPORTS",IF(Rule_Flags!H48=1,"DEFICIENCY",IF(Rule_Flags!I48=1,"UNDERWRITING",IF(Rule_Flags!J48=1,"COMPLIANCE","")))))) | BX49: =IF(BW49="SITE_CONTROL","Site control missing or invalid",IF(BW49="APPROVALS","Required approvals or resolutions incomplete",IF(BW49="REPORTS","Required third-party reports incomplete",IF(BW49="DEFICIENCY","Unresolved deficiency or material deficiency",IF(BW49="UNDERWRITING","Underwriting / feasibility not passed",IF(BW49="COMPLIANCE","Deconcentration, one-mile, LURA, or Chapter 12 issue","Ready under current engine rules")))))) | BY49: =IF(BV49="Determination Notice","Streamlined + DN-ready assumptions satisfied",IF(BV49="Board","Board-required or board-ready assumptions satisfied","")) | BZ49: =IF(AND(BP49="Y",BQ49<>"Y"),"Carryforward project retains queue priority",IF(BQ49="Y","New project enters behind carryforward projects","")) | CA49: =_xludf.RANK.EQ(Rule_Flags!O48,Rule_Flags!$O$3:$O$402,0) | CB49: =IF(OR(BU49="Determination Notice Issued",BU49="Board",BU49="Closed"),"Y","N") | CC49: construction_type mapped from raw 'NC' to 'New Construction' | CD49: Jennifer Croxton | CE49: (318) 278-1682 | CF49: jcroxton@knightdevco.com | CG49: Antonio Williams | CH49: (903) 838-8548
A50: 2026-02-10 | B50: 2026-02-10 | C50: 25460 | E50: Hays Street Apartments | F50: Houston | G50: Harris | H50: 6 | I50: 1406 Hays Street | J50: 77009 | K50: 45736 | L50: Withdrawn | M50: 45848 | O50: 45737 | P50: 45917 | R50: New Construction | S50: General | T50: 110 | U50: 110 | X50: Harris County HFC | Y50: Local HFC | Z50: 20000000 | AB50: 1115980 | AF50: N | AG50: Y | AI50: Y | AK50: Y | AL50: Y | AM50: Y | AS50: N | AX50: N | AY50: Y | AZ50: Y | BA50: Y | BB50: Y | BC50: Y | BE50: N | BJ50: Y | BK50: N | BL50: N | BM50: Y | BN50: Y | BO50: 45736 | BP50: N | BQ50: Y | BR50: =IF(COUNTIF(AI50:BM50,"N")+COUNTBLANK(AI50:BM50)=0,"Y","N") | BS50: =IF(AND(BR50="Y",OR(L50="Submitted",L50="Under Review")),"Y",IF(L50="Closed","Y","N")) | BT50: 47 | BU50: =Rule_Flags!Q49 | BV50: =Rule_Flags!P49 | BW50: =IF(Rule_Flags!E49=1,"SITE_CONTROL",IF(Rule_Flags!F49=1,"APPROVALS",IF(Rule_Flags!G49=1,"REPORTS",IF(Rule_Flags!H49=1,"DEFICIENCY",IF(Rule_Flags!I49=1,"UNDERWRITING",IF(Rule_Flags!J49=1,"COMPLIANCE","")))))) | BX50: =IF(BW50="SITE_CONTROL","Site control missing or invalid",IF(BW50="APPROVALS","Required approvals or resolutions incomplete",IF(BW50="REPORTS","Required third-party reports incomplete",IF(BW50="DEFICIENCY","Unresolved deficiency or material deficiency",IF(BW50="UNDERWRITING","Underwriting / feasibility not passed",IF(BW50="COMPLIANCE","Deconcentration, one-mile, LURA, or Chapter 12 issue","Ready under current engine rules")))))) | BY50: =IF(BV50="Determination Notice","Streamlined + DN-ready assumptions satisfied",IF(BV50="Board","Board-required or board-ready assumptions satisfied","")) | BZ50: =IF(AND(BP50="Y",BQ50<>"Y"),"Carryforward project retains queue priority",IF(BQ50="Y","New project enters behind carryforward projects","")) | CA50: =_xludf.RANK.EQ(Rule_Flags!O49,Rule_Flags!$O$3:$O$402,0) | CB50: =IF(OR(BU50="Determination Notice Issued",BU50="Board",BU50="Closed"),"Y","N") | CC50: construction_type mapped from raw 'NC' to 'New Construction' | CD50: Sheri Wilhelm | CE50: 818-706-0694 | CF50: swilhelm@amcalhousing.com | CG50: Rene Martinez | CH50: (832) 927-4955
A51: 2026-02-10 | B51: 2026-02-10 | C51: 25454 | E51: Palms Breeze Village | F51: Brownsville | G51: Cameron | H51: 11 | I51: 464 N. Illinois Avenue | J51: 78521 | K51: 45744 | L51: Withdrawn | M51: 45848 | O51: 45715 | P51: 45895 | R51: New Construction | S51: General | T51: 324 | U51: 324 | X51: Cameron County HFC | Y51: Local HFC | Z51: 35000000 | AB51: 3014886 | AF51: Y | AG51: Y | AI51: Y | AK51: Y | AL51: Y | AM51: Y | AS51: N | AX51: N | AY51: Y | AZ51: Y | BA51: Y | BB51: Y | BC51: Y | BE51: N | BJ51: Y | BK51: N | BL51: N | BM51: Y | BN51: Y | BO51: 45744 | BP51: N | BQ51: Y | BR51: =IF(COUNTIF(AI51:BM51,"N")+COUNTBLANK(AI51:BM51)=0,"Y","N") | BS51: =IF(AND(BR51="Y",OR(L51="Submitted",L51="Under Review")),"Y",IF(L51="Closed","Y","N")) | BT51: 48 | BU51: =Rule_Flags!Q50 | BV51: =Rule_Flags!P50 | BW51: =IF(Rule_Flags!E50=1,"SITE_CONTROL",IF(Rule_Flags!F50=1,"APPROVALS",IF(Rule_Flags!G50=1,"REPORTS",IF(Rule_Flags!H50=1,"DEFICIENCY",IF(Rule_Flags!I50=1,"UNDERWRITING",IF(Rule_Flags!J50=1,"COMPLIANCE","")))))) | BX51: =IF(BW51="SITE_CONTROL","Site control missing or invalid",IF(BW51="APPROVALS","Required approvals or resolutions incomplete",IF(BW51="REPORTS","Required third-party reports incomplete",IF(BW51="DEFICIENCY","Unresolved deficiency or material deficiency",IF(BW51="UNDERWRITING","Underwriting / feasibility not passed",IF(BW51="COMPLIANCE","Deconcentration, one-mile, LURA, or Chapter 12 issue","Ready under current engine rules")))))) | BY51: =IF(BV51="Determination Notice","Streamlined + DN-ready assumptions satisfied",IF(BV51="Board","Board-required or board-ready assumptions satisfied","")) | BZ51: =IF(AND(BP51="Y",BQ51<>"Y"),"Carryforward project retains queue priority",IF(BQ51="Y","New project enters behind carryforward projects","")) | CA51: =_xludf.RANK.EQ(Rule_Flags!O50,Rule_Flags!$O$3:$O$402,0) | CB51: =IF(OR(BU51="Determination Notice Issued",BU51="Board",BU51="Closed"),"Y","N") | CC51: construction_type mapped from raw 'NC' to 'New Construction' | CD51: Richard Ashton | CE51: (214) 5633273 | CF51: rashton@amd42.com | CG51: Jeff Smith | CH51: (713) 461-2749
A52: 2026-02-10 | B52: 2026-02-10 | C52: 24702/25453 | E52: Payton Gin | F52: Austin | G52: Travis | H52: 7 | I52: 1800 Payton Gin Road | J52: 78758 | K52: 45601 | L52: Approved | M52: 45694 | N52: 45749 | O52: 45971 | P52: 46151 | R52: New Construction | S52: General | T52: 176 | U52: 176 | X52: Travis County HFC | Y52: Local HFC | Z52: 33000000 | AB52: 2909484 | AC52: 2909060 | AF52: N | AG52: Y | AI52: Y | AK52: Y | AL52: Y | AM52: Y | AS52: N | AX52: N | AY52: Y | AZ52: Y | BA52: Y | BB52: Y | BC52: Y | BE52: N | BJ52: Y | BK52: N | BL52: N | BM52: Y | BN52: Y | BO52: 45601 | BP52: N | BQ52: Y | BR52: =IF(COUNTIF(AI52:BM52,"N")+COUNTBLANK(AI52:BM52)=0,"Y","N") | BS52: =IF(AND(BR52="Y",OR(L52="Submitted",L52="Under Review")),"Y",IF(L52="Closed","Y","N")) | BT52: 3 | BU52: =Rule_Flags!Q51 | BV52: =Rule_Flags!P51 | BW52: =IF(Rule_Flags!E51=1,"SITE_CONTROL",IF(Rule_Flags!F51=1,"APPROVALS",IF(Rule_Flags!G51=1,"REPORTS",IF(Rule_Flags!H51=1,"DEFICIENCY",IF(Rule_Flags!I51=1,"UNDERWRITING",IF(Rule_Flags!J51=1,"COMPLIANCE","")))))) | BX52: =IF(BW52="SITE_CONTROL","Site control missing or invalid",IF(BW52="APPROVALS","Required approvals or resolutions incomplete",IF(BW52="REPORTS","Required third-party reports incomplete",IF(BW52="DEFICIENCY","Unresolved deficiency or material deficiency",IF(BW52="UNDERWRITING","Underwriting / feasibility not passed",IF(BW52="COMPLIANCE","Deconcentration, one-mile, LURA, or Chapter 12 issue","Ready under current engine rules")))))) | BY52: =IF(BV52="Determination Notice","Streamlined + DN-ready assumptions satisfied",IF(BV52="Board","Board-required or board-ready assumptions satisfied","")) | BZ52: =IF(AND(BP52="Y",BQ52<>"Y"),"Carryforward project retains queue priority",IF(BQ52="Y","New project enters behind carryforward projects","")) | CA52: =_xludf.RANK.EQ(Rule_Flags!O51,Rule_Flags!$O$3:$O$402,0) | CB52: =IF(OR(BU52="Determination Notice Issued",BU52="Board",BU52="Closed"),"Y","N") | CC52: construction_type mapped from raw 'NC' to 'New Construction' | CD52: Logan Schmidt | CE52: (608) 604-2163 | CF52: logan.schmidt@roerscompanies.com | CG52: Ana Everett | CH52: (512) 854-1745
A53: 2026-02-10 | B53: 2026-02-10 | C53: 25604 | E53: Trinity Junction | F53: Dallas | G53: Dallas | H53: 3 | I53: 813 JJ Lemmon Road | J53: 75241 | K53: TBD | L53: Pre-Application | M53: TBD | O53: 45883 | P53: 46063 | R53: New Construction | S53: General | T53: 300 | U53: 300 | X53: TDHCA | Y53: TDHCA | Z53: 50000000 | AB53: 4371486 | AF53: N | AG53: Y | AI53: Y | AK53: Y | AL53: Y | AM53: Y | AS53: N | AX53: N | AY53: Y | AZ53: Y | BA53: Y | BB53: Y | BC53: Y | BE53: N | BJ53: Y | BK53: N | BL53: N | BM53: Y | BN53: Y | BO53: TBD | BP53: N | BQ53: Y | BR53: =IF(COUNTIF(AI53:BM53,"N")+COUNTBLANK(AI53:BM53)=0,"Y","N") | BS53: =IF(AND(BR53="Y",OR(L53="Submitted",L53="Under Review")),"Y",IF(L53="Closed","Y","N")) | BT53: 91 | BU53: =Rule_Flags!Q52 | BV53: =Rule_Flags!P52 | BW53: =IF(Rule_Flags!E52=1,"SITE_CONTROL",IF(Rule_Flags!F52=1,"APPROVALS",IF(Rule_Flags!G52=1,"REPORTS",IF(Rule_Flags!H52=1,"DEFICIENCY",IF(Rule_Flags!I52=1,"UNDERWRITING",IF(Rule_Flags!J52=1,"COMPLIANCE","")))))) | BX53: =IF(BW53="SITE_CONTROL","Site control missing or invalid",IF(BW53="APPROVALS","Required approvals or resolutions incomplete",IF(BW53="REPORTS","Required third-party reports incomplete",IF(BW53="DEFICIENCY","Unresolved deficiency or material deficiency",IF(BW53="UNDERWRITING","Underwriting / feasibility not passed",IF(BW53="COMPLIANCE","Deconcentration, one-mile, LURA, or Chapter 12 issue","Ready under current engine rules")))))) | BY53: =IF(BV53="Determination Notice","Streamlined + DN-ready assumptions satisfied",IF(BV53="Board","Board-required or board-ready assumptions satisfied","")) | BZ53: =IF(AND(BP53="Y",BQ53<>"Y"),"Carryforward project retains queue priority",IF(BQ53="Y","New project enters behind carryforward projects","")) | CA53: =_xludf.RANK.EQ(Rule_Flags!O52,Rule_Flags!$O$3:$O$402,0) | CB53: =IF(OR(BU53="Determination Notice Issued",BU53="Board",BU53="Closed"),"Y","N") | CC53: construction_type mapped from raw 'NC' to 'New Construction' | CD53: Jason Trevino | CE53: (512)578-8488 | CF53: jtrevino@ldgdevelopment.com | CG53: Teresa Morales | CH53: (512) 475-3344
A54: 2026-02-10 | B54: 2026-02-10 | C54: 25600 | D54: 24614 | E54: Waters at Arrowood | F54: Houston | G54: Harris | H54: 6 | I54: 8304 S. Course Road | J54: 77072 | K54: 45762 | L54: Withdrawn | M54: 45967 | O54: 45883 | P54: 46063 | R54: Acq/Rehab | S54: General | T54: 302 | U54: 302 | X54: TDHCA | Y54: TDHCA | Z54: 30500000 | AB54: 2105730 | AF54: N | AG54: Y | AI54: Y | AK54: Y | AL54: Y | AM54: Y | AS54: N | AX54: N | AY54: Y | AZ54: Y | BA54: Y | BB54: Y | BC54: Y | BE54: N | BJ54: Y | BK54: N | BL54: N | BM54: Y | BN54: Y | BO54: 45762 | BP54: N | BQ54: Y | BR54: =IF(COUNTIF(AI54:BM54,"N")+COUNTBLANK(AI54:BM54)=0,"Y","N") | BS54: =IF(AND(BR54="Y",OR(L54="Submitted",L54="Under Review")),"Y",IF(L54="Closed","Y","N")) | BT54: 49 | BU54: =Rule_Flags!Q53 | BV54: =Rule_Flags!P53 | BW54: =IF(Rule_Flags!E53=1,"SITE_CONTROL",IF(Rule_Flags!F53=1,"APPROVALS",IF(Rule_Flags!G53=1,"REPORTS",IF(Rule_Flags!H53=1,"DEFICIENCY",IF(Rule_Flags!I53=1,"UNDERWRITING",IF(Rule_Flags!J53=1,"COMPLIANCE","")))))) | BX54: =IF(BW54="SITE_CONTROL","Site control missing or invalid",IF(BW54="APPROVALS","Required approvals or resolutions incomplete",IF(BW54="REPORTS","Required third-party reports incomplete",IF(BW54="DEFICIENCY","Unresolved deficiency or material deficiency",IF(BW54="UNDERWRITING","Underwriting / feasibility not passed",IF(BW54="COMPLIANCE","Deconcentration, one-mile, LURA, or Chapter 12 issue","Ready under current engine rules")))))) | BY54: =IF(BV54="Determination Notice","Streamlined + DN-ready assumptions satisfied",IF(BV54="Board","Board-required or board-ready assumptions satisfied","")) | BZ54: =IF(AND(BP54="Y",BQ54<>"Y"),"Carryforward project retains queue priority",IF(BQ54="Y","New project enters behind carryforward projects","")) | CA54: =_xludf.RANK.EQ(Rule_Flags!O53,Rule_Flags!$O$3:$O$402,0) | CB54: =IF(OR(BU54="Determination Notice Issued",BU54="Board",BU54="Closed"),"Y","N") | CD54: Rafael Navarro | CE54: (469) 206-8930 | CF54: rnavarro@atlantichousing.org | CG54: Teresa Morales | CH54: (512) 475-3344
A55: 2026-02-10 | B55: 2026-02-10 | C55: 25461 | E55: Coolwood Oaks | F55: Houston | G55: Harris | H55: 6 | I55: 777 Coolwood Drive | J55: 77013 | K55: 45782 | L55: Approved | M55: 45904 | N55: 45910 | O55: 45890 | P55: 46070 | R55: Acq/Rehab | S55: General | T55: 168 | U55: 168 | X55: Houston HFC | Y55: Local HFC | Z55: 27000000 | AB55: 1690387 | AC55: 1690387 | AF55: N | AG55: Y | AI55: Y | AK55: Y | AL55: Y | AM55: Y | AS55: N | AX55: N | AY55: Y | AZ55: Y | BA55: Y | BB55: Y | BC55: Y | BE55: N | BJ55: Y | BK55: N | BL55: N | BM55: Y | BN55: Y | BO55: 45782 | BP55: N | BQ55: Y | BR55: =IF(COUNTIF(AI55:BM55,"N")+COUNTBLANK(AI55:BM55)=0,"Y","N") | BS55: =IF(AND(BR55="Y",OR(L55="Submitted",L55="Under Review")),"Y",IF(L55="Closed","Y","N")) | BT55: 50 | BU55: =Rule_Flags!Q54 | BV55: =Rule_Flags!P54 | BW55: =IF(Rule_Flags!E54=1,"SITE_CONTROL",IF(Rule_Flags!F54=1,"APPROVALS",IF(Rule_Flags!G54=1,"REPORTS",IF(Rule_Flags!H54=1,"DEFICIENCY",IF(Rule_Flags!I54=1,"UNDERWRITING",IF(Rule_Flags!J54=1,"COMPLIANCE","")))))) | BX55: =IF(BW55="SITE_CONTROL","Site control missing or invalid",IF(BW55="APPROVALS","Required approvals or resolutions incomplete",IF(BW55="REPORTS","Required third-party reports incomplete",IF(BW55="DEFICIENCY","Unresolved deficiency or material deficiency",IF(BW55="UNDERWRITING","Underwriting / feasibility not passed",IF(BW55="COMPLIANCE","Deconcentration, one-mile, LURA, or Chapter 12 issue","Ready under current engine rules")))))) | BY55: =IF(BV55="Determination Notice","Streamlined + DN-ready assumptions satisfied",IF(BV55="Board","Board-required or board-ready assumptions satisfied","")) | BZ55: =IF(AND(BP55="Y",BQ55<>"Y"),"Carryforward project retains queue priority",IF(BQ55="Y","New project enters behind carryforward projects","")) | CA55: =_xludf.RANK.EQ(Rule_Flags!O54,Rule_Flags!$O$3:$O$402,0) | CB55: =IF(OR(BU55="Determination Notice Issued",BU55="Board",BU55="Closed"),"Y","N") | CD55: Allan Izzo | CE55: (646) 825-7106 | CF55: allan.izzo@fairstead.com | CG55: Richard Mudd, Sr. | CH55: (713) 461-2749
A56: 2026-02-10 | B56: 2026-02-10 | C56: 25455 | E56: Orion Apartments | F56: San Antonio | G56: Bexar | H56: 9 | I56: 13107 SW Loop 410 | J56: 78224 | K56: 45784 | L56: Closed | M56: 45904 | N56: 45905 | O56: 45672 | P56: 46752 | R56: New Construction | S56: General | T56: 336 | U56: 336 | X56: San Antonio HT PFC | Y56: Other | Z56: 50000000 | AB56: 4650430 | AC56: 4650430 | AF56: N | AG56: Y | AH56: Y | AI56: Y | AK56: Y | AL56: Y | AM56: Y | AS56: N | AX56: N | AY56: Y | AZ56: Y | BA56: Y | BB56: Y | BC56: Y | BE56: N | BJ56: Y | BK56: N | BL56: N | BM56: Y | BN56: Y | BO56: 45784 | BP56: N | BQ56: Y | BR56: =IF(COUNTIF(AI56:BM56,"N")+COUNTBLANK(AI56:BM56)=0,"Y","N") | BS56: =IF(AND(BR56="Y",OR(L56="Submitted",L56="Under Review")),"Y",IF(L56="Closed","Y","N")) | BT56: 51 | BU56: =Rule_Flags!Q55 | BV56: =Rule_Flags!P55 | BW56: =IF(Rule_Flags!E55=1,"SITE_CONTROL",IF(Rule_Flags!F55=1,"APPROVALS",IF(Rule_Flags!G55=1,"REPORTS",IF(Rule_Flags!H55=1,"DEFICIENCY",IF(Rule_Flags!I55=1,"UNDERWRITING",IF(Rule_Flags!J55=1,"COMPLIANCE","")))))) | BX56: =IF(BW56="SITE_CONTROL","Site control missing or invalid",IF(BW56="APPROVALS","Required approvals or resolutions incomplete",IF(BW56="REPORTS","Required third-party reports incomplete",IF(BW56="DEFICIENCY","Unresolved deficiency or material deficiency",IF(BW56="UNDERWRITING","Underwriting / feasibility not passed",IF(BW56="COMPLIANCE","Deconcentration, one-mile, LURA, or Chapter 12 issue","Ready under current engine rules")))))) | BY56: =IF(BV56="Determination Notice","Streamlined + DN-ready assumptions satisfied",IF(BV56="Board","Board-required or board-ready assumptions satisfied","")) | BZ56: =IF(AND(BP56="Y",BQ56<>"Y"),"Carryforward project retains queue priority",IF(BQ56="Y","New project enters behind carryforward projects","")) | CA56: =_xludf.RANK.EQ(Rule_Flags!O55,Rule_Flags!$O$3:$O$402,0) | CB56: =IF(OR(BU56="Determination Notice Issued",BU56="Board",BU56="Closed"),"Y","N") | CC56: construction_type mapped from raw 'NC' to 'New Construction' | CD56: Jean Latsha | CE56: (512) 470-7312 | CF56: jlatsha@pedcor.net | CG56: Pedro Alanis | CH56: (210) 735-2772
A57: 2026-02-10 | B57: 2026-02-10 | C57: 25421 | E57: Sycamores at Pleasant Valley | F57: Austin | G57: Travis | H57: 7 | I57: 5900 South Pleasant Valley | J57: 78744 | K57: 45786 | L57: Approved | M57: 45904 | N57: 45915 | O57: 45911 | P57: 46091 | R57: New Construction | S57: General | T57: 75 | U57: 75 | X57: Austin HFC | Y57: Local HFC | Z57: 25000000 | AB57: 1489920 | AC57: 1489920 | AF57: N | AG57: Y | AI57: Y | AK57: Y | AL57: Y | AM57: Y | AS57: N | AX57: N | AY57: Y | AZ57: Y | BA57: Y | BB57: Y | BC57: Y | BE57: N | BJ57: Y | BK57: N | BL57: N | BM57: Y | BN57: Y | BO57: 45786 | BP57: N | BQ57: Y | BR57: =IF(COUNTIF(AI57:BM57,"N")+COUNTBLANK(AI57:BM57)=0,"Y","N") | BS57: =IF(AND(BR57="Y",OR(L57="Submitted",L57="Under Review")),"Y",IF(L57="Closed","Y","N")) | BT57: 52 | BU57: =Rule_Flags!Q56 | BV57: =Rule_Flags!P56 | BW57: =IF(Rule_Flags!E56=1,"SITE_CONTROL",IF(Rule_Flags!F56=1,"APPROVALS",IF(Rule_Flags!G56=1,"REPORTS",IF(Rule_Flags!H56=1,"DEFICIENCY",IF(Rule_Flags!I56=1,"UNDERWRITING",IF(Rule_Flags!J56=1,"COMPLIANCE","")))))) | BX57: =IF(BW57="SITE_CONTROL","Site control missing or invalid",IF(BW57="APPROVALS","Required approvals or resolutions incomplete",IF(BW57="REPORTS","Required third-party reports incomplete",IF(BW57="DEFICIENCY","Unresolved deficiency or material deficiency",IF(BW57="UNDERWRITING","Underwriting / feasibility not passed",IF(BW57="COMPLIANCE","Deconcentration, one-mile, LURA, or Chapter 12 issue","Ready under current engine rules")))))) | BY57: =IF(BV57="Determination Notice","Streamlined + DN-ready assumptions satisfied",IF(BV57="Board","Board-required or board-ready assumptions satisfied","")) | BZ57: =IF(AND(BP57="Y",BQ57<>"Y"),"Carryforward project retains queue priority",IF(BQ57="Y","New project enters behind carryforward projects","")) | CA57: =_xludf.RANK.EQ(Rule_Flags!O56,Rule_Flags!$O$3:$O$402,0) | CB57: =IF(OR(BU57="Determination Notice Issued",BU57="Board",BU57="Closed"),"Y","N") | CC57: construction_type mapped from raw 'NC' to 'New Construction' | CD57: Sarah Andre | CE57: (512) 698-3369 | CF57: sarah@structuretexas.com | CG57: Genaro Pena | CH57: (512) 974-2137
A58: 2026-02-10 | B58: 2026-02-10 | C58: 25601 | D58: 24613 | E58: Waters at Waterchase | F58: Dallas | G58: Dallas | H58: 3 | I58: 12365 Plano Road | J58: 75243 | K58: 45790 | L58: Active | M58: 46002 | O58: 45883 | P58: 46063 | R58: Acq/Rehab | S58: General | T58: 130 | U58: 130 | X58: TDHCA | Y58: TDHCA | Z58: 20000000 | AB58: 1353213 | AF58: N | AG58: Y | AI58: Y | AK58: Y | AL58: Y | AM58: Y | AS58: N | AX58: N | AY58: Y | AZ58: Y | BA58: Y | BB58: Y | BC58: Y | BE58: N | BJ58: Y | BK58: N | BL58: N | BM58: Y | BN58: Y | BO58: 45790 | BP58: N | BQ58: Y | BR58: =IF(COUNTIF(AI58:BM58,"N")+COUNTBLANK(AI58:BM58)=0,"Y","N") | BS58: =IF(AND(BR58="Y",OR(L58="Submitted",L58="Under Review")),"Y",IF(L58="Closed","Y","N")) | BT58: 53 | BU58: =Rule_Flags!Q57 | BV58: =Rule_Flags!P57 | BW58: =IF(Rule_Flags!E57=1,"SITE_CONTROL",IF(Rule_Flags!F57=1,"APPROVALS",IF(Rule_Flags!G57=1,"REPORTS",IF(Rule_Flags!H57=1,"DEFICIENCY",IF(Rule_Flags!I57=1,"UNDERWRITING",IF(Rule_Flags!J57=1,"COMPLIANCE","")))))) | BX58: =IF(BW58="SITE_CONTROL","Site control missing or invalid",IF(BW58="APPROVALS","Required approvals or resolutions incomplete",IF(BW58="REPORTS","Required third-party reports incomplete",IF(BW58="DEFICIENCY","Unresolved deficiency or material deficiency",IF(BW58="UNDERWRITING","Underwriting / feasibility not passed",IF(BW58="COMPLIANCE","Deconcentration, one-mile, LURA, or Chapter 12 issue","Ready under current engine rules")))))) | BY58: =IF(BV58="Determination Notice","Streamlined + DN-ready assumptions satisfied",IF(BV58="Board","Board-required or board-ready assumptions satisfied","")) | BZ58: =IF(AND(BP58="Y",BQ58<>"Y"),"Carryforward project retains queue priority",IF(BQ58="Y","New project enters behind carryforward projects","")) | CA58: =_xludf.RANK.EQ(Rule_Flags!O57,Rule_Flags!$O$3:$O$402,0) | CB58: =IF(OR(BU58="Determination Notice Issued",BU58="Board",BU58="Closed"),"Y","N") | CD58: Rafael Navarro | CE58: (469) 206-8930 | CF58: rnavarro@atlantichousing.org | CG58: Teresa Morales | CH58: (512) 475-3344
A59: 2026-02-10 | B59: 2026-02-10 | C59: 25606 | D59: 24619 | E59: Braniff Lofts | F59: Dallas | G59: Dallas | H59: 3 | I59: 2801 Wycliff Avenue | J59: 75219 | K59: 45800 | L59: Active | M59: 45904 | O59: 45663 | P59: 46752 | R59: New Construction | S59: Supportive Housing | T59: 48 | U59: 48 | X59: TDHCA | Y59: TDHCA | Z59: 20000000 | AB59: 1280966 | AF59: Y | AG59: Y | AI59: Y | AK59: Y | AL59: Y | AM59: Y | AS59: N | AX59: N | AY59: Y | AZ59: Y | BA59: Y | BB59: Y | BC59: Y | BE59: N | BJ59: Y | BK59: N | BL59: N | BM59: Y | BN59: Y | BO59: 45800 | BP59: N | BQ59: Y | BR59: =IF(COUNTIF(AI59:BM59,"N")+COUNTBLANK(AI59:BM59)=0,"Y","N") | BS59: =IF(AND(BR59="Y",OR(L59="Submitted",L59="Under Review")),"Y",IF(L59="Closed","Y","N")) | BT59: 54 | BU59: =Rule_Flags!Q58 | BV59: =Rule_Flags!P58 | BW59: =IF(Rule_Flags!E58=1,"SITE_CONTROL",IF(Rule_Flags!F58=1,"APPROVALS",IF(Rule_Flags!G58=1,"REPORTS",IF(Rule_Flags!H58=1,"DEFICIENCY",IF(Rule_Flags!I58=1,"UNDERWRITING",IF(Rule_Flags!J58=1,"COMPLIANCE","")))))) | BX59: =IF(BW59="SITE_CONTROL","Site control missing or invalid",IF(BW59="APPROVALS","Required approvals or resolutions incomplete",IF(BW59="REPORTS","Required third-party reports incomplete",IF(BW59="DEFICIENCY","Unresolved deficiency or material deficiency",IF(BW59="UNDERWRITING","Underwriting / feasibility not passed",IF(BW59="COMPLIANCE","Deconcentration, one-mile, LURA, or Chapter 12 issue","Ready under current engine rules")))))) | BY59: =IF(BV59="Determination Notice","Streamlined + DN-ready assumptions satisfied",IF(BV59="Board","Board-required or board-ready assumptions satisfied","")) | BZ59: =IF(AND(BP59="Y",BQ59<>"Y"),"Carryforward project retains queue priority",IF(BQ59="Y","New project enters behind carryforward projects","")) | CA59: =_xludf.RANK.EQ(Rule_Flags!O58,Rule_Flags!$O$3:$O$402,0) | CB59: =IF(OR(BU59="Determination Notice Issued",BU59="Board",BU59="Closed"),"Y","N") | CC59: construction_type mapped from raw 'NC' to 'New Construction' | CD59: Jessica Krochtengel | CE59: (215) 806-2216 | CF59: jess@sycamoredevelopment.com | CG59: Teresa Morales | CH59: (512) 475-3344
A60: 2026-02-10 | B60: 2026-02-10 | C60: 25463 | D60: 96003 | E60: Waterford at Spencer Oaks | F60: Denton | G60: Denton | H60: 3 | I60: 2100 Spencer Road | J60: 76205 | K60: 45813 | L60: Closed | M60: 45904 | N60: 45904 | O60: 45748 | P60: 45928 | R60: Acq/Rehab | S60: General | T60: 208 | U60: 207 | X60: Legacy Denton PFC | Y60: Other | Z60: 44200000 | AB60: 3461207 | AC60: 3461207 | AF60: N | AG60: Y | AH60: Y | AI60: Y | AK60: Y | AL60: Y | AM60: Y | AS60: N | AX60: N | AY60: Y | AZ60: Y | BA60: Y | BB60: Y | BC60: Y | BE60: N | BJ60: Y | BK60: N | BL60: N | BM60: Y | BN60: Y | BO60: 45813 | BP60: N | BQ60: Y | BR60: =IF(COUNTIF(AI60:BM60,"N")+COUNTBLANK(AI60:BM60)=0,"Y","N") | BS60: =IF(AND(BR60="Y",OR(L60="Submitted",L60="Under Review")),"Y",IF(L60="Closed","Y","N")) | BT60: 57 | BU60: =Rule_Flags!Q59 | BV60: =Rule_Flags!P59 | BW60: =IF(Rule_Flags!E59=1,"SITE_CONTROL",IF(Rule_Flags!F59=1,"APPROVALS",IF(Rule_Flags!G59=1,"REPORTS",IF(Rule_Flags!H59=1,"DEFICIENCY",IF(Rule_Flags!I59=1,"UNDERWRITING",IF(Rule_Flags!J59=1,"COMPLIANCE","")))))) | BX60: =IF(BW60="SITE_CONTROL","Site control missing or invalid",IF(BW60="APPROVALS","Required approvals or resolutions incomplete",IF(BW60="REPORTS","Required third-party reports incomplete",IF(BW60="DEFICIENCY","Unresolved deficiency or material deficiency",IF(BW60="UNDERWRITING","Underwriting / feasibility not passed",IF(BW60="COMPLIANCE","Deconcentration, one-mile, LURA, or Chapter 12 issue","Ready under current engine rules")))))) | BY60: =IF(BV60="Determination Notice","Streamlined + DN-ready assumptions satisfied",IF(BV60="Board","Board-required or board-ready assumptions satisfied","")) | BZ60: =IF(AND(BP60="Y",BQ60<>"Y"),"Carryforward project retains queue priority",IF(BQ60="Y","New project enters behind carryforward projects","")) | CA60: =_xludf.RANK.EQ(Rule_Flags!O59,Rule_Flags!$O$3:$O$402,0) | CB60: =IF(OR(BU60="Determination Notice Issued",BU60="Board",BU60="Closed"),"Y","N") | CC60: property_tax_exemption normalized from 'Y (50%)' to 'Y' | CD60: Tim Smith | CE60: (832) 443-0333 | CF60: tsmith@hokeservices.com | CG60: Sherri McDade | CH60: (940) 383-1504
A61: 2026-02-10 | B61: 2026-02-10 | C61: 25468 | E61: Lofts at Creekview | F61: San Antonio | G61: Bexar | H61: 9 | I61: 3623 and 3841 East Commerce | J61: 78216 | K61: 45813 | L61: Closed | M61: 11/6/205 | N61: 45939 | O61: 45770 | P61: 45950 | R61: New Construction | S61: General | T61: 301 | U61: 301 | X61: San Antonio HT PFC | Y61: Other | Z61: 40000000 | AB61: 3537379 | AC61: 3532516 | AF61: N | AG61: Y | AH61: Y | AI61: Y | AK61: Y | AL61: Y | AM61: Y | AS61: N | AX61: N | AY61: Y | AZ61: Y | BA61: Y | BB61: Y | BC61: Y | BE61: N | BJ61: Y | BK61: N | BL61: N | BM61: Y | BN61: Y | BO61: 45813 | BP61: N | BQ61: Y | BR61: =IF(COUNTIF(AI61:BM61,"N")+COUNTBLANK(AI61:BM61)=0,"Y","N") | BS61: =IF(AND(BR61="Y",OR(L61="Submitted",L61="Under Review")),"Y",IF(L61="Closed","Y","N")) | BT61: 58 | BU61: =Rule_Flags!Q60 | BV61: =Rule_Flags!P60 | BW61: =IF(Rule_Flags!E60=1,"SITE_CONTROL",IF(Rule_Flags!F60=1,"APPROVALS",IF(Rule_Flags!G60=1,"REPORTS",IF(Rule_Flags!H60=1,"DEFICIENCY",IF(Rule_Flags!I60=1,"UNDERWRITING",IF(Rule_Flags!J60=1,"COMPLIANCE","")))))) | BX61: =IF(BW61="SITE_CONTROL","Site control missing or invalid",IF(BW61="APPROVALS","Required approvals or resolutions incomplete",IF(BW61="REPORTS","Required third-party reports incomplete",IF(BW61="DEFICIENCY","Unresolved deficiency or material deficiency",IF(BW61="UNDERWRITING","Underwriting / feasibility not passed",IF(BW61="COMPLIANCE","Deconcentration, one-mile, LURA, or Chapter 12 issue","Ready under current engine rules")))))) | BY61: =IF(BV61="Determination Notice","Streamlined + DN-ready assumptions satisfied",IF(BV61="Board","Board-required or board-ready assumptions satisfied","")) | BZ61: =IF(AND(BP61="Y",BQ61<>"Y"),"Carryforward project retains queue priority",IF(BQ61="Y","New project enters behind carryforward projects","")) | CA61: =_xludf.RANK.EQ(Rule_Flags!O60,Rule_Flags!$O$3:$O$402,0) | CB61: =IF(OR(BU61="Determination Notice Issued",BU61="Board",BU61="Closed"),"Y","N") | CC61: construction_type mapped from raw 'NC' to 'New Construction' | CD61: Sarah Andre | CE61: (512) 698-3369 | CF61: sarah@structuretexas.com | CG61: Pedro Alanis | CH61: (210) 735-2772
A62: 2026-02-10 | B62: 2026-02-10 | C62: 25426 | E62: Roselawn Village | F62: Denton | G62: Denton | H62: 3 | I62: 2800 Roselawn Drive | J62: 76205 | K62: 45813 | L62: Approved | M62: 45904 | N62: 45890 | O62: 45789 | P62: 45969 | R62: New Construction | S62: General | T62: 297 | U62: 297 | X62: Legacy Denton PFC | Y62: Other | Z62: 49000000 | AB62: 3561139 | AC62: 3561139 | AF62: N | AG62: Y | AH62: Y | AI62: Y | AK62: Y | AL62: Y | AM62: Y | AS62: N | AX62: N | AY62: Y | AZ62: Y | BA62: Y | BB62: Y | BC62: Y | BE62: N | BJ62: Y | BK62: N | BL62: N | BM62: Y | BN62: Y | BO62: 45813 | BP62: N | BQ62: Y | BR62: =IF(COUNTIF(AI62:BM62,"N")+COUNTBLANK(AI62:BM62)=0,"Y","N") | BS62: =IF(AND(BR62="Y",OR(L62="Submitted",L62="Under Review")),"Y",IF(L62="Closed","Y","N")) | BT62: 55 | BU62: =Rule_Flags!Q61 | BV62: =Rule_Flags!P61 | BW62: =IF(Rule_Flags!E61=1,"SITE_CONTROL",IF(Rule_Flags!F61=1,"APPROVALS",IF(Rule_Flags!G61=1,"REPORTS",IF(Rule_Flags!H61=1,"DEFICIENCY",IF(Rule_Flags!I61=1,"UNDERWRITING",IF(Rule_Flags!J61=1,"COMPLIANCE","")))))) | BX62: =IF(BW62="SITE_CONTROL","Site control missing or invalid",IF(BW62="APPROVALS","Required approvals or resolutions incomplete",IF(BW62="REPORTS","Required third-party reports incomplete",IF(BW62="DEFICIENCY","Unresolved deficiency or material deficiency",IF(BW62="UNDERWRITING","Underwriting / feasibility not passed",IF(BW62="COMPLIANCE","Deconcentration, one-mile, LURA, or Chapter 12 issue","Ready under current engine rules")))))) | BY62: =IF(BV62="Determination Notice","Streamlined + DN-ready assumptions satisfied",IF(BV62="Board","Board-required or board-ready assumptions satisfied","")) | BZ62: =IF(AND(BP62="Y",BQ62<>"Y"),"Carryforward project retains queue priority",IF(BQ62="Y","New project enters behind carryforward projects","")) | CA62: =_xludf.RANK.EQ(Rule_Flags!O61,Rule_Flags!$O$3:$O$402,0) | CB62: =IF(OR(BU62="Determination Notice Issued",BU62="Board",BU62="Closed"),"Y","N") | CC62: construction_type mapped from raw 'NC' to 'New Construction' | CD62: Sarah Andre | CE62: (512) 698-3369 | CF62: sarah@structuretexas.com | CG62: Sherri McDade | CH62: (940) 383-1504
A63: 2026-02-10 | B63: 2026-02-10 | C63: 25462 | D63: 97028 | E63: Tuscany at Goldmark | F63: Dallas | G63: Dallas | H63: 3 | I63: 13731 Goldmark Drive | J63: 75240 | K63: 45813 | L63: Withdrawn | M63: 45904 | O63: 45748 | P63: 45928 | R63: Acq/Rehab | S63: Elderly | T63: 184 | U63: 183 | X63: Dallas HFC | Y63: Local HFC | Z63: 32000000 | AB63: 2271676 | AF63: N | AG63: Y | AI63: Y | AK63: Y | AL63: Y | AM63: Y | AS63: N | AX63: N | AY63: Y | AZ63: Y | BA63: Y | BB63: Y | BC63: Y | BE63: N | BJ63: Y | BK63: N | BL63: N | BM63: Y | BN63: Y | BO63: 45813 | BP63: N | BQ63: Y | BR63: =IF(COUNTIF(AI63:BM63,"N")+COUNTBLANK(AI63:BM63)=0,"Y","N") | BS63: =IF(AND(BR63="Y",OR(L63="Submitted",L63="Under Review")),"Y",IF(L63="Closed","Y","N")) | BT63: 56 | BU63: =Rule_Flags!Q62 | BV63: =Rule_Flags!P62 | BW63: =IF(Rule_Flags!E62=1,"SITE_CONTROL",IF(Rule_Flags!F62=1,"APPROVALS",IF(Rule_Flags!G62=1,"REPORTS",IF(Rule_Flags!H62=1,"DEFICIENCY",IF(Rule_Flags!I62=1,"UNDERWRITING",IF(Rule_Flags!J62=1,"COMPLIANCE","")))))) | BX63: =IF(BW63="SITE_CONTROL","Site control missing or invalid",IF(BW63="APPROVALS","Required approvals or resolutions incomplete",IF(BW63="REPORTS","Required third-party reports incomplete",IF(BW63="DEFICIENCY","Unresolved deficiency or material deficiency",IF(BW63="UNDERWRITING","Underwriting / feasibility not passed",IF(BW63="COMPLIANCE","Deconcentration, one-mile, LURA, or Chapter 12 issue","Ready under current engine rules")))))) | BY63: =IF(BV63="Determination Notice","Streamlined + DN-ready assumptions satisfied",IF(BV63="Board","Board-required or board-ready assumptions satisfied","")) | BZ63: =IF(AND(BP63="Y",BQ63<>"Y"),"Carryforward project retains queue priority",IF(BQ63="Y","New project enters behind carryforward projects","")) | CA63: =_xludf.RANK.EQ(Rule_Flags!O62,Rule_Flags!$O$3:$O$402,0) | CB63: =IF(OR(BU63="Determination Notice Issued",BU63="Board",BU63="Closed"),"Y","N") | CC63: property_tax_exemption normalized from 'Y (50%)' to 'Y' | CD63: Brad Fisher | CE63: (913) 787-1676 | CF63: bfisher@aprilhousing.com | CG63: Aaron Eaquinto | CH63: (214) 670-4942
A64: 2026-02-10 | B64: 2026-02-10 | C64: 25456 | E64: Stones Crossing Apt Homes | F64: San Antonio | G64: Bexar | H64: 9 | I64: 23219 U.S. HWY 281 N | J64: 78258 | K64: 45820 | L64: Approved | M64: 45939 | N64: 45905 | O64: 45672 | P64: 46752 | R64: New Construction | S64: General | T64: 336 | U64: 336 | X64: San Antonio HT PFC | Y64: Other | Z64: 60000000 | AB64: 4546209 | AC64: 4546209 | AF64: N | AG64: Y | AH64: Y | AI64: Y | AK64: Y | AL64: Y | AM64: Y | AS64: N | AX64: N | AY64: Y | AZ64: Y | BA64: Y | BB64: Y | BC64: Y | BE64: N | BJ64: Y | BK64: N | BL64: N | BM64: Y | BN64: Y | BO64: 45820 | BP64: N | BQ64: Y | BR64: =IF(COUNTIF(AI64:BM64,"N")+COUNTBLANK(AI64:BM64)=0,"Y","N") | BS64: =IF(AND(BR64="Y",OR(L64="Submitted",L64="Under Review")),"Y",IF(L64="Closed","Y","N")) | BT64: 59 | BU64: =Rule_Flags!Q63 | BV64: =Rule_Flags!P63 | BW64: =IF(Rule_Flags!E63=1,"SITE_CONTROL",IF(Rule_Flags!F63=1,"APPROVALS",IF(Rule_Flags!G63=1,"REPORTS",IF(Rule_Flags!H63=1,"DEFICIENCY",IF(Rule_Flags!I63=1,"UNDERWRITING",IF(Rule_Flags!J63=1,"COMPLIANCE","")))))) | BX64: =IF(BW64="SITE_CONTROL","Site control missing or invalid",IF(BW64="APPROVALS","Required approvals or resolutions incomplete",IF(BW64="REPORTS","Required third-party reports incomplete",IF(BW64="DEFICIENCY","Unresolved deficiency or material deficiency",IF(BW64="UNDERWRITING","Underwriting / feasibility not passed",IF(BW64="COMPLIANCE","Deconcentration, one-mile, LURA, or Chapter 12 issue","Ready under current engine rules")))))) | BY64: =IF(BV64="Determination Notice","Streamlined + DN-ready assumptions satisfied",IF(BV64="Board","Board-required or board-ready assumptions satisfied","")) | BZ64: =IF(AND(BP64="Y",BQ64<>"Y"),"Carryforward project retains queue priority",IF(BQ64="Y","New project enters behind carryforward projects","")) | CA64: =_xludf.RANK.EQ(Rule_Flags!O63,Rule_Flags!$O$3:$O$402,0) | CB64: =IF(OR(BU64="Determination Notice Issued",BU64="Board",BU64="Closed"),"Y","N") | CC64: construction_type mapped from raw 'NC' to 'New Construction' | CD64: Jean Latsha | CE64: (512) 470-7312 | CF64: jlatsha@pedcor.net | CG64: Pedro Alanis | CH64: (210) 735-2772
A65: 2026-02-10 | B65: 2026-02-10 | C65: 25465 | E65: Haverstock Hills East | F65: Houston | G65: Harris | H65: 6 | I65: 5619 Aldine Bender Road | J65: 77032 | K65: 45824 | L65: Closed | M65: 45939 | N65: 45929 | O65: 45818 | P65: 45998 | R65: Acq/Rehab | S65: General | T65: 268 | U65: 268 | X65: Harris County HFC | Y65: Local HFC | Z65: 69152737 | AB65: 3418358 | AC65: 3418358 | AF65: N | AG65: Y | AI65: Y | AK65: Y | AL65: Y | AM65: Y | AS65: N | AX65: N | AY65: Y | AZ65: Y | BA65: Y | BB65: Y | BC65: Y | BE65: N | BJ65: Y | BK65: N | BL65: N | BM65: Y | BN65: Y | BO65: 45824 | BP65: N | BQ65: Y | BR65: =IF(COUNTIF(AI65:BM65,"N")+COUNTBLANK(AI65:BM65)=0,"Y","N") | BS65: =IF(AND(BR65="Y",OR(L65="Submitted",L65="Under Review")),"Y",IF(L65="Closed","Y","N")) | BT65: 60 | BU65: =Rule_Flags!Q64 | BV65: =Rule_Flags!P64 | BW65: =IF(Rule_Flags!E64=1,"SITE_CONTROL",IF(Rule_Flags!F64=1,"APPROVALS",IF(Rule_Flags!G64=1,"REPORTS",IF(Rule_Flags!H64=1,"DEFICIENCY",IF(Rule_Flags!I64=1,"UNDERWRITING",IF(Rule_Flags!J64=1,"COMPLIANCE","")))))) | BX65: =IF(BW65="SITE_CONTROL","Site control missing or invalid",IF(BW65="APPROVALS","Required approvals or resolutions incomplete",IF(BW65="REPORTS","Required third-party reports incomplete",IF(BW65="DEFICIENCY","Unresolved deficiency or material deficiency",IF(BW65="UNDERWRITING","Underwriting / feasibility not passed",IF(BW65="COMPLIANCE","Deconcentration, one-mile, LURA, or Chapter 12 issue","Ready under current engine rules")))))) | BY65: =IF(BV65="Determination Notice","Streamlined + DN-ready assumptions satisfied",IF(BV65="Board","Board-required or board-ready assumptions satisfied","")) | BZ65: =IF(AND(BP65="Y",BQ65<>"Y"),"Carryforward project retains queue priority",IF(BQ65="Y","New project enters behind carryforward projects","")) | CA65: =_xludf.RANK.EQ(Rule_Flags!O64,Rule_Flags!$O$3:$O$402,0) | CB65: =IF(OR(BU65="Determination Notice Issued",BU65="Board",BU65="Closed"),"Y","N") | CD65: Allan Izzo | CE65: (646) 8257106 | CF65: allan.izzo@fairstead.com | CG65: Rene Martinez | CH65: (832) 927-4824
A66: 2026-02-10 | B66: 2026-02-10 | C66: 25466 | E66: Haverstock Hills West | F66: Houston | G66: Harris | H66: 6 | I66: 5609 Aldine Bender Road | J66: 77032 | K66: 45824 | L66: Closed | M66: 45939 | N66: 45929 | O66: 45819 | P66: 45999 | R66: Acq/Rehab | S66: General | T66: 432 | U66: 432 | X66: Harris County HFC | Y66: Local HFC | Z66: 69152737 | AB66: 5582580 | AC66: 5582580 | AF66: N | AG66: Y | AI66: Y | AK66: Y | AL66: Y | AM66: Y | AS66: N | AX66: N | AY66: Y | AZ66: Y | BA66: Y | BB66: Y | BC66: Y | BE66: N | BJ66: Y | BK66: N | BL66: N | BM66: Y | BN66: Y | BO66: 45824 | BP66: N | BQ66: Y | BR66: =IF(COUNTIF(AI66:BM66,"N")+COUNTBLANK(AI66:BM66)=0,"Y","N") | BS66: =IF(AND(BR66="Y",OR(L66="Submitted",L66="Under Review")),"Y",IF(L66="Closed","Y","N")) | BT66: 61 | BU66: =Rule_Flags!Q65 | BV66: =Rule_Flags!P65 | BW66: =IF(Rule_Flags!E65=1,"SITE_CONTROL",IF(Rule_Flags!F65=1,"APPROVALS",IF(Rule_Flags!G65=1,"REPORTS",IF(Rule_Flags!H65=1,"DEFICIENCY",IF(Rule_Flags!I65=1,"UNDERWRITING",IF(Rule_Flags!J65=1,"COMPLIANCE","")))))) | BX66: =IF(BW66="SITE_CONTROL","Site control missing or invalid",IF(BW66="APPROVALS","Required approvals or resolutions incomplete",IF(BW66="REPORTS","Required third-party reports incomplete",IF(BW66="DEFICIENCY","Unresolved deficiency or material deficiency",IF(BW66="UNDERWRITING","Underwriting / feasibility not passed",IF(BW66="COMPLIANCE","Deconcentration, one-mile, LURA, or Chapter 12 issue","Ready under current engine rules")))))) | BY66: =IF(BV66="Determination Notice","Streamlined + DN-ready assumptions satisfied",IF(BV66="Board","Board-required or board-ready assumptions satisfied","")) | BZ66: =IF(AND(BP66="Y",BQ66<>"Y"),"Carryforward project retains queue priority",IF(BQ66="Y","New project enters behind carryforward projects","")) | CA66: =_xludf.RANK.EQ(Rule_Flags!O65,Rule_Flags!$O$3:$O$402,0) | CB66: =IF(OR(BU66="Determination Notice Issued",BU66="Board",BU66="Closed"),"Y","N") | CD66: Allan Izzo | CE66: (646) 8257106 | CF66: allan.izzo@fairstead.com | CG66: Rene Martinez | CH66: (832) 927-4824
A67: 2026-02-10 | B67: 2026-02-10 | C67: 25467 | E67: Cameron HiLine | F67: Austin | G67: Travis | H67: 7 | I67: 1124 Clayton Lane | J67: 78723 | K67: 45833 | L67: Closed | M67: 45939 | N67: 45919 | O67: 45785 | P67: 45965 | R67: New Construction | S67: General | T67: 227 | U67: 227 | X67: Austin Affordable PFC | Y67: Other | Z67: 40000000 | AB67: 3315696 | AC67: 3315696 | AF67: N | AG67: Y | AH67: Y | AI67: Y | AK67: Y | AL67: Y | AM67: Y | AS67: N | AX67: N | AY67: Y | AZ67: Y | BA67: Y | BB67: Y | BC67: Y | BE67: N | BJ67: Y | BK67: N | BL67: N | BM67: Y | BN67: Y | BO67: 45833 | BP67: N | BQ67: Y | BR67: =IF(COUNTIF(AI67:BM67,"N")+COUNTBLANK(AI67:BM67)=0,"Y","N") | BS67: =IF(AND(BR67="Y",OR(L67="Submitted",L67="Under Review")),"Y",IF(L67="Closed","Y","N")) | BT67: 62 | BU67: =Rule_Flags!Q66 | BV67: =Rule_Flags!P66 | BW67: =IF(Rule_Flags!E66=1,"SITE_CONTROL",IF(Rule_Flags!F66=1,"APPROVALS",IF(Rule_Flags!G66=1,"REPORTS",IF(Rule_Flags!H66=1,"DEFICIENCY",IF(Rule_Flags!I66=1,"UNDERWRITING",IF(Rule_Flags!J66=1,"COMPLIANCE","")))))) | BX67: =IF(BW67="SITE_CONTROL","Site control missing or invalid",IF(BW67="APPROVALS","Required approvals or resolutions incomplete",IF(BW67="REPORTS","Required third-party reports incomplete",IF(BW67="DEFICIENCY","Unresolved deficiency or material deficiency",IF(BW67="UNDERWRITING","Underwriting / feasibility not passed",IF(BW67="COMPLIANCE","Deconcentration, one-mile, LURA, or Chapter 12 issue","Ready under current engine rules")))))) | BY67: =IF(BV67="Determination Notice","Streamlined + DN-ready assumptions satisfied",IF(BV67="Board","Board-required or board-ready assumptions satisfied","")) | BZ67: =IF(AND(BP67="Y",BQ67<>"Y"),"Carryforward project retains queue priority",IF(BQ67="Y","New project enters behind carryforward projects","")) | CA67: =_xludf.RANK.EQ(Rule_Flags!O66,Rule_Flags!$O$3:$O$402,0) | CB67: =IF(OR(BU67="Determination Notice Issued",BU67="Board",BU67="Closed"),"Y","N") | CC67: construction_type mapped from raw 'NC' to 'New Construction' | CD67: Adrian Iglesias | CE67: (214) 613-6569 | CF67: aiglesias@ghdevelopment.com | CG67: Ron Kowal | CH67: 512‐477‐4488
A68: 2026-02-10 | B68: 2026-02-10 | C68: 25470 | D68: 060424 | E68: Lafayette Village | F68: Houston | G68: Harris | H68: 6 | I68: 4822 E Sam Houston Pkway N | J68: 77015 | K68: 45838 | L68: Approved | M68: 45939 | N68: 45975 | O68: 45880 | P68: 46060 | R68: Acq/Rehab | S68: General | T68: 250 | U68: 250 | X68: HHA Fountainview PFC | Y68: Other | Z68: 30000000 | AB68: 1413291 | AC68: 1413291 | AF68: N | AG68: Y | AH68: Y | AI68: Y | AK68: Y | AL68: Y | AM68: Y | AS68: N | AX68: N | AY68: Y | AZ68: Y | BA68: Y | BB68: Y | BC68: Y | BE68: N | BJ68: Y | BK68: N | BL68: N | BM68: Y | BN68: Y | BO68: 45838 | BP68: N | BQ68: Y | BR68: =IF(COUNTIF(AI68:BM68,"N")+COUNTBLANK(AI68:BM68)=0,"Y","N") | BS68: =IF(AND(BR68="Y",OR(L68="Submitted",L68="Under Review")),"Y",IF(L68="Closed","Y","N")) | BT68: 63 | BU68: =Rule_Flags!Q67 | BV68: =Rule_Flags!P67 | BW68: =IF(Rule_Flags!E67=1,"SITE_CONTROL",IF(Rule_Flags!F67=1,"APPROVALS",IF(Rule_Flags!G67=1,"REPORTS",IF(Rule_Flags!H67=1,"DEFICIENCY",IF(Rule_Flags!I67=1,"UNDERWRITING",IF(Rule_Flags!J67=1,"COMPLIANCE","")))))) | BX68: =IF(BW68="SITE_CONTROL","Site control missing or invalid",IF(BW68="APPROVALS","Required approvals or resolutions incomplete",IF(BW68="REPORTS","Required third-party reports incomplete",IF(BW68="DEFICIENCY","Unresolved deficiency or material deficiency",IF(BW68="UNDERWRITING","Underwriting / feasibility not passed",IF(BW68="COMPLIANCE","Deconcentration, one-mile, LURA, or Chapter 12 issue","Ready under current engine rules")))))) | BY68: =IF(BV68="Determination Notice","Streamlined + DN-ready assumptions satisfied",IF(BV68="Board","Board-required or board-ready assumptions satisfied","")) | BZ68: =IF(AND(BP68="Y",BQ68<>"Y"),"Carryforward project retains queue priority",IF(BQ68="Y","New project enters behind carryforward projects","")) | CA68: =_xludf.RANK.EQ(Rule_Flags!O67,Rule_Flags!$O$3:$O$402,0) | CB68: =IF(OR(BU68="Determination Notice Issued",BU68="Board",BU68="Closed"),"Y","N") | CD68: Jeremy Bartholomew | CE68: (713) 334-5514 | CF68: jeremy@resolutioncompanies.com | CG68: Jamie Bryant | CH68: (713) 260-0522
A69: 2026-02-10 | B69: 2026-02-10 | C69: 25423 | E69: Emberstone Apartments | F69: San Antonio | G69: Bexar | H69: 9 | I69: 14970 Watson Road | J69: 78073 | K69: 45839 | L69: Approved | M69: 45939 | N69: 45909 | O69: 45800 | P69: 45980 | R69: Acq/Rehab | S69: General | T69: 247 | U69: 247 | X69: Las Varas PFC | Y69: Other | Z69: 35000000 | AB69: 2982325 | AC69: 2982325 | AF69: N | AG69: Y | AH69: Y | AI69: Y | AK69: Y | AL69: Y | AM69: Y | AS69: N | AX69: N | AY69: Y | AZ69: Y | BA69: Y | BB69: Y | BC69: Y | BE69: N | BJ69: Y | BK69: N | BL69: N | BM69: Y | BN69: Y | BO69: 45839 | BP69: N | BQ69: Y | BR69: =IF(COUNTIF(AI69:BM69,"N")+COUNTBLANK(AI69:BM69)=0,"Y","N") | BS69: =IF(AND(BR69="Y",OR(L69="Submitted",L69="Under Review")),"Y",IF(L69="Closed","Y","N")) | BT69: 64 | BU69: =Rule_Flags!Q68 | BV69: =Rule_Flags!P68 | BW69: =IF(Rule_Flags!E68=1,"SITE_CONTROL",IF(Rule_Flags!F68=1,"APPROVALS",IF(Rule_Flags!G68=1,"REPORTS",IF(Rule_Flags!H68=1,"DEFICIENCY",IF(Rule_Flags!I68=1,"UNDERWRITING",IF(Rule_Flags!J68=1,"COMPLIANCE","")))))) | BX69: =IF(BW69="SITE_CONTROL","Site control missing or invalid",IF(BW69="APPROVALS","Required approvals or resolutions incomplete",IF(BW69="REPORTS","Required third-party reports incomplete",IF(BW69="DEFICIENCY","Unresolved deficiency or material deficiency",IF(BW69="UNDERWRITING","Underwriting / feasibility not passed",IF(BW69="COMPLIANCE","Deconcentration, one-mile, LURA, or Chapter 12 issue","Ready under current engine rules")))))) | BY69: =IF(BV69="Determination Notice","Streamlined + DN-ready assumptions satisfied",IF(BV69="Board","Board-required or board-ready assumptions satisfied","")) | BZ69: =IF(AND(BP69="Y",BQ69<>"Y"),"Carryforward project retains queue priority",IF(BQ69="Y","New project enters behind carryforward projects","")) | CA69: =_xludf.RANK.EQ(Rule_Flags!O68,Rule_Flags!$O$3:$O$402,0) | CB69: =IF(OR(BU69="Determination Notice Issued",BU69="Board",BU69="Closed"),"Y","N") | CD69: Carly Gast | CE69: (641) 830-9088 | CF69: cgast@kittleproperties.com | CG69: Michael Reyes | CH69: (210) 477-6130
A70: 2026-02-10 | B70: 2026-02-10 | C70: 25608 | D70: 24605 | E70: The Preserve at Dominion Park | F70: Houston | G70: Harris | H70: 6 | I70: 13100 Kuykendahl Road | J70: 77090 | K70: 45877 | L70: Active | M70: 46002 | O70: 45883 | P70: 46063 | R70: New Construction | S70: Elderly | T70: 134 | U70: 134 | X70: TDHCA | Y70: TDHCA | Z70: 20000000 | AB70: 1463676 | AF70: N | AG70: N | AI70: Y | AK70: Y | AL70: Y | AM70: Y | AS70: N | AX70: N | AY70: Y | AZ70: Y | BA70: Y | BB70: Y | BC70: Y | BE70: N | BJ70: Y | BK70: N | BL70: N | BM70: Y | BN70: Y | BO70: 45877 | BP70: N | BQ70: Y | BR70: =IF(COUNTIF(AI70:BM70,"N")+COUNTBLANK(AI70:BM70)=0,"Y","N") | BS70: =IF(AND(BR70="Y",OR(L70="Submitted",L70="Under Review")),"Y",IF(L70="Closed","Y","N")) | BT70: 67 | BU70: =Rule_Flags!Q69 | BV70: =Rule_Flags!P69 | BW70: =IF(Rule_Flags!E69=1,"SITE_CONTROL",IF(Rule_Flags!F69=1,"APPROVALS",IF(Rule_Flags!G69=1,"REPORTS",IF(Rule_Flags!H69=1,"DEFICIENCY",IF(Rule_Flags!I69=1,"UNDERWRITING",IF(Rule_Flags!J69=1,"COMPLIANCE","")))))) | BX70: =IF(BW70="SITE_CONTROL","Site control missing or invalid",IF(BW70="APPROVALS","Required approvals or resolutions incomplete",IF(BW70="REPORTS","Required third-party reports incomplete",IF(BW70="DEFICIENCY","Unresolved deficiency or material deficiency",IF(BW70="UNDERWRITING","Underwriting / feasibility not passed",IF(BW70="COMPLIANCE","Deconcentration, one-mile, LURA, or Chapter 12 issue","Ready under current engine rules")))))) | BY70: =IF(BV70="Determination Notice","Streamlined + DN-ready assumptions satisfied",IF(BV70="Board","Board-required or board-ready assumptions satisfied","")) | BZ70: =IF(AND(BP70="Y",BQ70<>"Y"),"Carryforward project retains queue priority",IF(BQ70="Y","New project enters behind carryforward projects","")) | CA70: =_xludf.RANK.EQ(Rule_Flags!O69,Rule_Flags!$O$3:$O$402,0) | CB70: =IF(OR(BU70="Determination Notice Issued",BU70="Board",BU70="Closed"),"Y","N") | CC70: construction_type mapped from raw 'NC' to 'New Construction' | CD70: Willie Drew | CE70: (713) 232-0354 | CF70: mountaintopdev@live.com | CG70: Teresa Morales | CH70: (512) 475-3344
A71: 2026-02-10 | B71: 2026-02-10 | C71: 25469 | E71: Sacred Heart Villas | F71: San Antonio | G71: Bexar | H71: 9 | I71: 120 S. Trinity Street | J71: 78207 | K71: 45852 | L71: Approved | M71: 45939 | N71: 45939 | O71: 46051 | P71: 46231 | R71: Acq/Rehab | S71: General | T71: 89 | U71: 89 | X71: Las Varas PFC | Y71: Other | Z71: 12000000 | AB71: 1035566 | AC71: 1035566 | AF71: N | AG71: Y | AH71: Y | AI71: Y | AK71: Y | AL71: Y | AM71: Y | AS71: N | AX71: N | AY71: Y | AZ71: Y | BA71: Y | BB71: Y | BC71: Y | BE71: N | BJ71: Y | BK71: N | BL71: N | BM71: Y | BN71: Y | BO71: 45852 | BP71: N | BQ71: Y | BR71: =IF(COUNTIF(AI71:BM71,"N")+COUNTBLANK(AI71:BM71)=0,"Y","N") | BS71: =IF(AND(BR71="Y",OR(L71="Submitted",L71="Under Review")),"Y",IF(L71="Closed","Y","N")) | BT71: 65 | BU71: =Rule_Flags!Q70 | BV71: =Rule_Flags!P70 | BW71: =IF(Rule_Flags!E70=1,"SITE_CONTROL",IF(Rule_Flags!F70=1,"APPROVALS",IF(Rule_Flags!G70=1,"REPORTS",IF(Rule_Flags!H70=1,"DEFICIENCY",IF(Rule_Flags!I70=1,"UNDERWRITING",IF(Rule_Flags!J70=1,"COMPLIANCE","")))))) | BX71: =IF(BW71="SITE_CONTROL","Site control missing or invalid",IF(BW71="APPROVALS","Required approvals or resolutions incomplete",IF(BW71="REPORTS","Required third-party reports incomplete",IF(BW71="DEFICIENCY","Unresolved deficiency or material deficiency",IF(BW71="UNDERWRITING","Underwriting / feasibility not passed",IF(BW71="COMPLIANCE","Deconcentration, one-mile, LURA, or Chapter 12 issue","Ready under current engine rules")))))) | BY71: =IF(BV71="Determination Notice","Streamlined + DN-ready assumptions satisfied",IF(BV71="Board","Board-required or board-ready assumptions satisfied","")) | BZ71: =IF(AND(BP71="Y",BQ71<>"Y"),"Carryforward project retains queue priority",IF(BQ71="Y","New project enters behind carryforward projects","")) | CA71: =_xludf.RANK.EQ(Rule_Flags!O70,Rule_Flags!$O$3:$O$402,0) | CB71: =IF(OR(BU71="Determination Notice Issued",BU71="Board",BU71="Closed"),"Y","N") | CC71: property_tax_exemption normalized from 'Y (50%)' to 'Y' | CD71: Sarah McDowell | CE71: (206) 697-1386 | CF71: smcdowell@chavezfoundation.org | CG71: Miranda Castro | CH71: (210) 556-5725
A72: 2026-02-10 | B72: 2026-02-10 | C72: 25609 | D72: 24617 | E72: The Gateway at Trinity Forest | F72: Dallas | G72: Dallas | H72: 3 | I72: 2050 Dowdy Ferry Road | J72: 75217 | K72: 45874 | L72: Closed | M72: 45967 | O72: 45883 | P72: 46063 | R72: New Construction | S72: General | T72: 330 | U72: 330 | X72: TDHCA | Y72: TDHCA | Z72: 50000000 | AB72: 4514430 | AC72: 4514387 | AF72: N | AG72: Y | AI72: Y | AK72: Y | AL72: Y | AM72: Y | AS72: N | AX72: N | AY72: Y | AZ72: Y | BA72: Y | BB72: Y | BC72: Y | BE72: N | BJ72: Y | BK72: N | BL72: N | BM72: Y | BN72: Y | BO72: 45874 | BP72: N | BQ72: Y | BR72: =IF(COUNTIF(AI72:BM72,"N")+COUNTBLANK(AI72:BM72)=0,"Y","N") | BS72: =IF(AND(BR72="Y",OR(L72="Submitted",L72="Under Review")),"Y",IF(L72="Closed","Y","N")) | BT72: 66 | BU72: =Rule_Flags!Q71 | BV72: =Rule_Flags!P71 | BW72: =IF(Rule_Flags!E71=1,"SITE_CONTROL",IF(Rule_Flags!F71=1,"APPROVALS",IF(Rule_Flags!G71=1,"REPORTS",IF(Rule_Flags!H71=1,"DEFICIENCY",IF(Rule_Flags!I71=1,"UNDERWRITING",IF(Rule_Flags!J71=1,"COMPLIANCE","")))))) | BX72: =IF(BW72="SITE_CONTROL","Site control missing or invalid",IF(BW72="APPROVALS","Required approvals or resolutions incomplete",IF(BW72="REPORTS","Required third-party reports incomplete",IF(BW72="DEFICIENCY","Unresolved deficiency or material deficiency",IF(BW72="UNDERWRITING","Underwriting / feasibility not passed",IF(BW72="COMPLIANCE","Deconcentration, one-mile, LURA, or Chapter 12 issue","Ready under current engine rules")))))) | BY72: =IF(BV72="Determination Notice","Streamlined + DN-ready assumptions satisfied",IF(BV72="Board","Board-required or board-ready assumptions satisfied","")) | BZ72: =IF(AND(BP72="Y",BQ72<>"Y"),"Carryforward project retains queue priority",IF(BQ72="Y","New project enters behind carryforward projects","")) | CA72: =_xludf.RANK.EQ(Rule_Flags!O71,Rule_Flags!$O$3:$O$402,0) | CB72: =IF(OR(BU72="Determination Notice Issued",BU72="Board",BU72="Closed"),"Y","N") | CC72: construction_type mapped from raw 'NC' to 'New Construction' | CD72: Jason Trevino | CE72: (512) 578-8488 | CF72: jtrevino@ldgdevelopment.com | CG72: Teresa Morales | CH72: (512) 475-3344
A73: 2026-02-10 | B73: 2026-02-10 | C73: 25471 | D73: 060617 | E73: Idlewilde Apartments | F73: Houston | G73: Harris | H73: 6 | I73: 9915 FM 1960 | J73: 77070 | K73: 45881 | L73: Approved | M73: 46002 | N73: 45975 | O73: 45880 | P73: 46060 | R73: Acq/Rehab | S73: General | T73: 250 | U73: 250 | X73: HHA Fountainview PFC | Y73: Other | Z73: 30000000 | AB73: 1399297 | AC73: 1399297 | AF73: N | AG73: Y | AH73: Y | AI73: Y | AK73: Y | AL73: Y | AM73: Y | AS73: N | AX73: N | AY73: Y | AZ73: Y | BA73: Y | BB73: Y | BC73: Y | BE73: N | BJ73: Y | BK73: N | BL73: N | BM73: Y | BN73: Y | BO73: 45881 | BP73: N | BQ73: Y | BR73: =IF(COUNTIF(AI73:BM73,"N")+COUNTBLANK(AI73:BM73)=0,"Y","N") | BS73: =IF(AND(BR73="Y",OR(L73="Submitted",L73="Under Review")),"Y",IF(L73="Closed","Y","N")) | BT73: 68 | BU73: =Rule_Flags!Q72 | BV73: =Rule_Flags!P72 | BW73: =IF(Rule_Flags!E72=1,"SITE_CONTROL",IF(Rule_Flags!F72=1,"APPROVALS",IF(Rule_Flags!G72=1,"REPORTS",IF(Rule_Flags!H72=1,"DEFICIENCY",IF(Rule_Flags!I72=1,"UNDERWRITING",IF(Rule_Flags!J72=1,"COMPLIANCE","")))))) | BX73: =IF(BW73="SITE_CONTROL","Site control missing or invalid",IF(BW73="APPROVALS","Required approvals or resolutions incomplete",IF(BW73="REPORTS","Required third-party reports incomplete",IF(BW73="DEFICIENCY","Unresolved deficiency or material deficiency",IF(BW73="UNDERWRITING","Underwriting / feasibility not passed",IF(BW73="COMPLIANCE","Deconcentration, one-mile, LURA, or Chapter 12 issue","Ready under current engine rules")))))) | BY73: =IF(BV73="Determination Notice","Streamlined + DN-ready assumptions satisfied",IF(BV73="Board","Board-required or board-ready assumptions satisfied","")) | BZ73: =IF(AND(BP73="Y",BQ73<>"Y"),"Carryforward project retains queue priority",IF(BQ73="Y","New project enters behind carryforward projects","")) | CA73: =_xludf.RANK.EQ(Rule_Flags!O72,Rule_Flags!$O$3:$O$402,0) | CB73: =IF(OR(BU73="Determination Notice Issued",BU73="Board",BU73="Closed"),"Y","N") | CD73: Jeremy Bartholomew | CE73: (713) 334-5514 | CF73: jeremy@resolutioncompanies.com | CG73: Jamie Bryant | CH73: (713) 260-0522
A74: 2026-02-10 | B74: 2026-02-10 | C74: 25481 | E74: Odem Victoria Apartments | F74: Victoria | G74: Victoria | H74: 10 | I74: 2303 Odem Street | J74: 77901 | K74: 45882 | L74: Withdrawn | M74: 46002 | O74: 45882 | P74: 46062 | R74: New Construction | S74: General | T74: 300 | U74: 300 | X74: Victoria HFC | Y74: Local HFC | Z74: 35000000 | AB74: 2625990 | AC74: 2816555 | AF74: N | AG74: Y | AI74: Y | AK74: Y | AL74: Y | AM74: Y | AS74: N | AX74: N | AY74: Y | AZ74: Y | BA74: Y | BB74: Y | BC74: Y | BE74: N | BJ74: Y | BK74: N | BL74: N | BM74: Y | BN74: Y | BO74: 45882 | BP74: N | BQ74: Y | BR74: =IF(COUNTIF(AI74:BM74,"N")+COUNTBLANK(AI74:BM74)=0,"Y","N") | BS74: =IF(AND(BR74="Y",OR(L74="Submitted",L74="Under Review")),"Y",IF(L74="Closed","Y","N")) | BT74: 69 | BU74: =Rule_Flags!Q73 | BV74: =Rule_Flags!P73 | BW74: =IF(Rule_Flags!E73=1,"SITE_CONTROL",IF(Rule_Flags!F73=1,"APPROVALS",IF(Rule_Flags!G73=1,"REPORTS",IF(Rule_Flags!H73=1,"DEFICIENCY",IF(Rule_Flags!I73=1,"UNDERWRITING",IF(Rule_Flags!J73=1,"COMPLIANCE","")))))) | BX74: =IF(BW74="SITE_CONTROL","Site control missing or invalid",IF(BW74="APPROVALS","Required approvals or resolutions incomplete",IF(BW74="REPORTS","Required third-party reports incomplete",IF(BW74="DEFICIENCY","Unresolved deficiency or material deficiency",IF(BW74="UNDERWRITING","Underwriting / feasibility not passed",IF(BW74="COMPLIANCE","Deconcentration, one-mile, LURA, or Chapter 12 issue","Ready under current engine rules")))))) | BY74: =IF(BV74="Determination Notice","Streamlined + DN-ready assumptions satisfied",IF(BV74="Board","Board-required or board-ready assumptions satisfied","")) | BZ74: =IF(AND(BP74="Y",BQ74<>"Y"),"Carryforward project retains queue priority",IF(BQ74="Y","New project enters behind carryforward projects","")) | CA74: =_xludf.RANK.EQ(Rule_Flags!O73,Rule_Flags!$O$3:$O$402,0) | CB74: =IF(OR(BU74="Determination Notice Issued",BU74="Board",BU74="Closed"),"Y","N") | CC74: construction_type mapped from raw 'NC' to 'New Construction' | CD74: Alex Ison | CE74: (440) 715-5154 | CF74: alex.ison@rbmliving.com | CG74: Allison Lacey | CH74: (361) 485-3520
A75: 2026-02-10 | B75: 2026-02-10 | C75: 25480 | E75: Westmoreland Townhomes | F75: Dallas | G75: Dallas | H75: 3 | I75: 6600 South Westmoreland Drive | J75: 75237 | K75: 45887 | L75: Closed | M75: 46002 | N75: 45981 | O75: 45832 | P75: 46012 | R75: New Construction | S75: Elderly | T75: 216 | U75: 216 | X75: City of Dallas HFC | Y75: Local HFC | Z75: 40000000 | AB75: 3065774 | AC75: 3065445 | AF75: N | AG75: Y | AI75: Y | AK75: Y | AL75: Y | AM75: Y | AS75: N | AX75: N | AY75: Y | AZ75: Y | BA75: Y | BB75: Y | BC75: Y | BE75: N | BJ75: Y | BK75: N | BL75: N | BM75: Y | BN75: Y | BO75: 45887 | BP75: N | BQ75: Y | BR75: =IF(COUNTIF(AI75:BM75,"N")+COUNTBLANK(AI75:BM75)=0,"Y","N") | BS75: =IF(AND(BR75="Y",OR(L75="Submitted",L75="Under Review")),"Y",IF(L75="Closed","Y","N")) | BT75: 70 | BU75: =Rule_Flags!Q74 | BV75: =Rule_Flags!P74 | BW75: =IF(Rule_Flags!E74=1,"SITE_CONTROL",IF(Rule_Flags!F74=1,"APPROVALS",IF(Rule_Flags!G74=1,"REPORTS",IF(Rule_Flags!H74=1,"DEFICIENCY",IF(Rule_Flags!I74=1,"UNDERWRITING",IF(Rule_Flags!J74=1,"COMPLIANCE","")))))) | BX75: =IF(BW75="SITE_CONTROL","Site control missing or invalid",IF(BW75="APPROVALS","Required approvals or resolutions incomplete",IF(BW75="REPORTS","Required third-party reports incomplete",IF(BW75="DEFICIENCY","Unresolved deficiency or material deficiency",IF(BW75="UNDERWRITING","Underwriting / feasibility not passed",IF(BW75="COMPLIANCE","Deconcentration, one-mile, LURA, or Chapter 12 issue","Ready under current engine rules")))))) | BY75: =IF(BV75="Determination Notice","Streamlined + DN-ready assumptions satisfied",IF(BV75="Board","Board-required or board-ready assumptions satisfied","")) | BZ75: =IF(AND(BP75="Y",BQ75<>"Y"),"Carryforward project retains queue priority",IF(BQ75="Y","New project enters behind carryforward projects","")) | CA75: =_xludf.RANK.EQ(Rule_Flags!O74,Rule_Flags!$O$3:$O$402,0) | CB75: =IF(OR(BU75="Determination Notice Issued",BU75="Board",BU75="Closed"),"Y","N") | CC75: construction_type mapped from raw 'NC' to 'New Construction' | CD75: Blake Hopkins | CE75: (469) 929-9445 | CF75: bhopkins@lincolnavenue.com | CG75: Aaron Eaquinto | CH75: 214-670-5988
A76: 2026-02-10 | B76: 2026-02-10 | C76: 25475 | E76: Humble Family Apartments | F76: Humble | G76: Harris | H76: 6 | I76: W Lake Houston Parkway | J76: 77346 | K76: 45888 | L76: Withdrawn | M76: 46002 | O76: 45881 | P76: 46061 | R76: New Construction | S76: General | T76: 306 | U76: 306 | X76: Harris County HFC | Y76: Local HFC | Z76: 69152737 | AB76: 5638702 | AF76: N | AG76: Y | AI76: Y | AK76: Y | AL76: Y | AM76: Y | AS76: N | AX76: N | AY76: Y | AZ76: Y | BA76: Y | BB76: Y | BC76: Y | BE76: N | BJ76: Y | BK76: N | BL76: N | BM76: Y | BN76: Y | BO76: 45888 | BP76: N | BQ76: Y | BR76: =IF(COUNTIF(AI76:BM76,"N")+COUNTBLANK(AI76:BM76)=0,"Y","N") | BS76: =IF(AND(BR76="Y",OR(L76="Submitted",L76="Under Review")),"Y",IF(L76="Closed","Y","N")) | BT76: 71 | BU76: =Rule_Flags!Q75 | BV76: =Rule_Flags!P75 | BW76: =IF(Rule_Flags!E75=1,"SITE_CONTROL",IF(Rule_Flags!F75=1,"APPROVALS",IF(Rule_Flags!G75=1,"REPORTS",IF(Rule_Flags!H75=1,"DEFICIENCY",IF(Rule_Flags!I75=1,"UNDERWRITING",IF(Rule_Flags!J75=1,"COMPLIANCE","")))))) | BX76: =IF(BW76="SITE_CONTROL","Site control missing or invalid",IF(BW76="APPROVALS","Required approvals or resolutions incomplete",IF(BW76="REPORTS","Required third-party reports incomplete",IF(BW76="DEFICIENCY","Unresolved deficiency or material deficiency",IF(BW76="UNDERWRITING","Underwriting / feasibility not passed",IF(BW76="COMPLIANCE","Deconcentration, one-mile, LURA, or Chapter 12 issue","Ready under current engine rules")))))) | BY76: =IF(BV76="Determination Notice","Streamlined + DN-ready assumptions satisfied",IF(BV76="Board","Board-required or board-ready assumptions satisfied","")) | BZ76: =IF(AND(BP76="Y",BQ76<>"Y"),"Carryforward project retains queue priority",IF(BQ76="Y","New project enters behind carryforward projects","")) | CA76: =_xludf.RANK.EQ(Rule_Flags!O75,Rule_Flags!$O$3:$O$402,0) | CB76: =IF(OR(BU76="Determination Notice Issued",BU76="Board",BU76="Closed"),"Y","N") | CC76: construction_type mapped from raw 'NC' to 'New Construction' | CD76: Jeff Spicer | CE76: 214-960-1158 | CF76: jeff.spicer@Dominiuminc.com | CG76: Rene Martinez | CH76: 832-927-4824
A77: 2026-02-10 | B77: 2026-02-10 | C77: 25479 | E77: Tabor Village | F77: Dallas | G77: Dallas | H77: 3 | I77: 6200 Baraboo Drive | J77: 75241 | K77: 45890 | L77: Closed | M77: 46002 | N77: 45994 | O77: 45866 | P77: 46046 | R77: New Construction | S77: Elderly | T77: 229 | U77: 206 | X77: City of Dallas HFC | Y77: Local HFC | Z77: 38000000 | AB77: 2598977 | AC77: 2598977 | AF77: N | AG77: Y | AI77: Y | AK77: Y | AL77: Y | AM77: Y | AS77: N | AX77: N | AY77: Y | AZ77: Y | BA77: Y | BB77: Y | BC77: Y | BE77: N | BJ77: Y | BK77: N | BL77: N | BM77: Y | BN77: Y | BO77: 45890 | BP77: N | BQ77: Y | BR77: =IF(COUNTIF(AI77:BM77,"N")+COUNTBLANK(AI77:BM77)=0,"Y","N") | BS77: =IF(AND(BR77="Y",OR(L77="Submitted",L77="Under Review")),"Y",IF(L77="Closed","Y","N")) | BT77: 72 | BU77: =Rule_Flags!Q76 | BV77: =Rule_Flags!P76 | BW77: =IF(Rule_Flags!E76=1,"SITE_CONTROL",IF(Rule_Flags!F76=1,"APPROVALS",IF(Rule_Flags!G76=1,"REPORTS",IF(Rule_Flags!H76=1,"DEFICIENCY",IF(Rule_Flags!I76=1,"UNDERWRITING",IF(Rule_Flags!J76=1,"COMPLIANCE","")))))) | BX77: =IF(BW77="SITE_CONTROL","Site control missing or invalid",IF(BW77="APPROVALS","Required approvals or resolutions incomplete",IF(BW77="REPORTS","Required third-party reports incomplete",IF(BW77="DEFICIENCY","Unresolved deficiency or material deficiency",IF(BW77="UNDERWRITING","Underwriting / feasibility not passed",IF(BW77="COMPLIANCE","Deconcentration, one-mile, LURA, or Chapter 12 issue","Ready under current engine rules")))))) | BY77: =IF(BV77="Determination Notice","Streamlined + DN-ready assumptions satisfied",IF(BV77="Board","Board-required or board-ready assumptions satisfied","")) | BZ77: =IF(AND(BP77="Y",BQ77<>"Y"),"Carryforward project retains queue priority",IF(BQ77="Y","New project enters behind carryforward projects","")) | CA77: =_xludf.RANK.EQ(Rule_Flags!O76,Rule_Flags!$O$3:$O$402,0) | CB77: =IF(OR(BU77="Determination Notice Issued",BU77="Board",BU77="Closed"),"Y","N") | CC77: construction_type mapped from raw 'NC' to 'New Construction' | CD77: Blake Hopkins | CE77: (469) 929-9445 | CF77: bhopkins@lincolnavenue.com | CG77: Aaron Eaquinto | CH77: (214) 670-5988
A78: 2026-02-10 | B78: 2026-02-10 | C78: 25483 | E78: Cobblestone Manor | F78: Fort Worth | G78: Tarrant | H78: 3 | I78: 8201 Sartain Drive | J78: 76120 | K78: 45896 | L78: Approved | M78: 46002 | N78: 46010 | O78: 45891 | P78: 46071 | R78: Acq/Rehab | S78: Elderly | T78: 220 | U78: 220 | X78: Tarrant County HFC | Y78: Local HFC | Z78: 45000000 | AB78: 2044665 | AC78: 2007397 | AF78: N | AG78: Y | AI78: Y | AK78: Y | AL78: Y | AM78: Y | AS78: N | AX78: N | AY78: Y | AZ78: Y | BA78: Y | BB78: Y | BC78: Y | BE78: N | BJ78: Y | BK78: N | BL78: N | BM78: Y | BN78: Y | BO78: 45896 | BP78: N | BQ78: Y | BR78: =IF(COUNTIF(AI78:BM78,"N")+COUNTBLANK(AI78:BM78)=0,"Y","N") | BS78: =IF(AND(BR78="Y",OR(L78="Submitted",L78="Under Review")),"Y",IF(L78="Closed","Y","N")) | BT78: 73 | BU78: =Rule_Flags!Q77 | BV78: =Rule_Flags!P77 | BW78: =IF(Rule_Flags!E77=1,"SITE_CONTROL",IF(Rule_Flags!F77=1,"APPROVALS",IF(Rule_Flags!G77=1,"REPORTS",IF(Rule_Flags!H77=1,"DEFICIENCY",IF(Rule_Flags!I77=1,"UNDERWRITING",IF(Rule_Flags!J77=1,"COMPLIANCE","")))))) | BX78: =IF(BW78="SITE_CONTROL","Site control missing or invalid",IF(BW78="APPROVALS","Required approvals or resolutions incomplete",IF(BW78="REPORTS","Required third-party reports incomplete",IF(BW78="DEFICIENCY","Unresolved deficiency or material deficiency",IF(BW78="UNDERWRITING","Underwriting / feasibility not passed",IF(BW78="COMPLIANCE","Deconcentration, one-mile, LURA, or Chapter 12 issue","Ready under current engine rules")))))) | BY78: =IF(BV78="Determination Notice","Streamlined + DN-ready assumptions satisfied",IF(BV78="Board","Board-required or board-ready assumptions satisfied","")) | BZ78: =IF(AND(BP78="Y",BQ78<>"Y"),"Carryforward project retains queue priority",IF(BQ78="Y","New project enters behind carryforward projects","")) | CA78: =_xludf.RANK.EQ(Rule_Flags!O77,Rule_Flags!$O$3:$O$402,0) | CB78: =IF(OR(BU78="Determination Notice Issued",BU78="Board",BU78="Closed"),"Y","N") | CD78: Neal Route | CE78: (214)960-1162 | CF78: nroute@dominiuminc.com | CG78: Tim Nelson | CH78: (512) 481-2022
A79: 2026-02-10 | B79: 2026-02-10 | C79: 25484 | E79: Ella Apartments | F79: Lubbock | G79: Lubbock | H79: 1 | I79: 1102 58th Street | J79: 79412 | K79: 45905 | L79: Approved | M79: 46002 | N79: 46048 | O79: 45882 | P79: 46062 | R79: Acq/Rehab | S79: General | T79: 152 | U79: 152 | X79: Lubbock HFC | Y79: Local HFC | Z79: 22000000 | AB79: 1171123 | AC79: 1171123 | AF79: N | AG79: Y | AI79: Y | AK79: Y | AL79: Y | AM79: Y | AS79: N | AX79: N | AY79: Y | AZ79: Y | BA79: Y | BB79: Y | BC79: Y | BE79: N | BJ79: Y | BK79: N | BL79: N | BM79: Y | BN79: Y | BO79: 45905 | BP79: N | BQ79: Y | BR79: =IF(COUNTIF(AI79:BM79,"N")+COUNTBLANK(AI79:BM79)=0,"Y","N") | BS79: =IF(AND(BR79="Y",OR(L79="Submitted",L79="Under Review")),"Y",IF(L79="Closed","Y","N")) | BT79: 76 | BU79: =Rule_Flags!Q78 | BV79: =Rule_Flags!P78 | BW79: =IF(Rule_Flags!E78=1,"SITE_CONTROL",IF(Rule_Flags!F78=1,"APPROVALS",IF(Rule_Flags!G78=1,"REPORTS",IF(Rule_Flags!H78=1,"DEFICIENCY",IF(Rule_Flags!I78=1,"UNDERWRITING",IF(Rule_Flags!J78=1,"COMPLIANCE","")))))) | BX79: =IF(BW79="SITE_CONTROL","Site control missing or invalid",IF(BW79="APPROVALS","Required approvals or resolutions incomplete",IF(BW79="REPORTS","Required third-party reports incomplete",IF(BW79="DEFICIENCY","Unresolved deficiency or material deficiency",IF(BW79="UNDERWRITING","Underwriting / feasibility not passed",IF(BW79="COMPLIANCE","Deconcentration, one-mile, LURA, or Chapter 12 issue","Ready under current engine rules")))))) | BY79: =IF(BV79="Determination Notice","Streamlined + DN-ready assumptions satisfied",IF(BV79="Board","Board-required or board-ready assumptions satisfied","")) | BZ79: =IF(AND(BP79="Y",BQ79<>"Y"),"Carryforward project retains queue priority",IF(BQ79="Y","New project enters behind carryforward projects","")) | CA79: =_xludf.RANK.EQ(Rule_Flags!O78,Rule_Flags!$O$3:$O$402,0) | CB79: =IF(OR(BU79="Determination Notice Issued",BU79="Board",BU79="Closed"),"Y","N") | CD79: Tisha Vaidya | CE79: 214-336-7495 | CF79: tisha@elizabethpropertygroup.com | CG79: Shari Flynn | CH79: (806) 866-9801
A80: 2026-02-10 | B80: 2026-02-10 | C80: 25473 | D80: 04452 | E80: Seville Place | F80: La Porte | G80: Harris | H80: 6 | I80: 3701 Louella Blvd | J80: 77571 | K80: 45905 | L80: Approved | M80: 46002 | N80: 46009 | O80: 46057 | P80: 46237 | R80: Acq/Rehab | S80: General | T80: 180 | U80: 180 | X80: The Southeast Texas HFC | Y80: Local HFC | Z80: 22500000 | AB80: 1130081 | AC80: 1130081 | AF80: N | AG80: Y | AI80: Y | AK80: Y | AL80: Y | AM80: Y | AS80: N | AX80: N | AY80: Y | AZ80: Y | BA80: Y | BB80: Y | BC80: Y | BE80: N | BJ80: Y | BK80: N | BL80: N | BM80: Y | BN80: Y | BO80: 45905 | BP80: N | BQ80: Y | BR80: =IF(COUNTIF(AI80:BM80,"N")+COUNTBLANK(AI80:BM80)=0,"Y","N") | BS80: =IF(AND(BR80="Y",OR(L80="Submitted",L80="Under Review")),"Y",IF(L80="Closed","Y","N")) | BT80: 74 | BU80: =Rule_Flags!Q79 | BV80: =Rule_Flags!P79 | BW80: =IF(Rule_Flags!E79=1,"SITE_CONTROL",IF(Rule_Flags!F79=1,"APPROVALS",IF(Rule_Flags!G79=1,"REPORTS",IF(Rule_Flags!H79=1,"DEFICIENCY",IF(Rule_Flags!I79=1,"UNDERWRITING",IF(Rule_Flags!J79=1,"COMPLIANCE","")))))) | BX80: =IF(BW80="SITE_CONTROL","Site control missing or invalid",IF(BW80="APPROVALS","Required approvals or resolutions incomplete",IF(BW80="REPORTS","Required third-party reports incomplete",IF(BW80="DEFICIENCY","Unresolved deficiency or material deficiency",IF(BW80="UNDERWRITING","Underwriting / feasibility not passed",IF(BW80="COMPLIANCE","Deconcentration, one-mile, LURA, or Chapter 12 issue","Ready under current engine rules")))))) | BY80: =IF(BV80="Determination Notice","Streamlined + DN-ready assumptions satisfied",IF(BV80="Board","Board-required or board-ready assumptions satisfied","")) | BZ80: =IF(AND(BP80="Y",BQ80<>"Y"),"Carryforward project retains queue priority",IF(BQ80="Y","New project enters behind carryforward projects","")) | CA80: =_xludf.RANK.EQ(Rule_Flags!O79,Rule_Flags!$O$3:$O$402,0) | CB80: =IF(OR(BU80="Determination Notice Issued",BU80="Board",BU80="Closed"),"Y","N") | CD80: Jeremy Bartholomew | CE80: (713) 334-5514 | CF80: jeremy@resolutioncompanies.com | CG80: Jennine Hovell-Cox | CH80: (713) 260-0501
A81: 2026-02-10 | B81: 2026-02-10 | C81: 25474 | E81: Central at Commerce | F81: San Antonio | G81: Bexar | H81: 9 | I81: 1231 East Commerce Street | J81: 78205 | K81: 45905 | L81: Closed | M81: 46002 | N81: 46000 | O81: 45863 | P81: 46043 | R81: New Construction | S81: General | T81: 279 | U81: 279 | X81: Las Varas PFC | Y81: Other | Z81: 50000000 | AB81: 4205378 | AC81: 4186219 | AF81: N | AG81: Y | AH81: Y | AI81: Y | AK81: Y | AL81: Y | AM81: Y | AS81: N | AX81: N | AY81: Y | AZ81: Y | BA81: Y | BB81: Y | BC81: Y | BE81: N | BJ81: Y | BK81: N | BL81: N | BM81: Y | BN81: Y | BO81: 45905 | BP81: N | BQ81: Y | BR81: =IF(COUNTIF(AI81:BM81,"N")+COUNTBLANK(AI81:BM81)=0,"Y","N") | BS81: =IF(AND(BR81="Y",OR(L81="Submitted",L81="Under Review")),"Y",IF(L81="Closed","Y","N")) | BT81: 75 | BU81: =Rule_Flags!Q80 | BV81: =Rule_Flags!P80 | BW81: =IF(Rule_Flags!E80=1,"SITE_CONTROL",IF(Rule_Flags!F80=1,"APPROVALS",IF(Rule_Flags!G80=1,"REPORTS",IF(Rule_Flags!H80=1,"DEFICIENCY",IF(Rule_Flags!I80=1,"UNDERWRITING",IF(Rule_Flags!J80=1,"COMPLIANCE","")))))) | BX81: =IF(BW81="SITE_CONTROL","Site control missing or invalid",IF(BW81="APPROVALS","Required approvals or resolutions incomplete",IF(BW81="REPORTS","Required third-party reports incomplete",IF(BW81="DEFICIENCY","Unresolved deficiency or material deficiency",IF(BW81="UNDERWRITING","Underwriting / feasibility not passed",IF(BW81="COMPLIANCE","Deconcentration, one-mile, LURA, or Chapter 12 issue","Ready under current engine rules")))))) | BY81: =IF(BV81="Determination Notice","Streamlined + DN-ready assumptions satisfied",IF(BV81="Board","Board-required or board-ready assumptions satisfied","")) | BZ81: =IF(AND(BP81="Y",BQ81<>"Y"),"Carryforward project retains queue priority",IF(BQ81="Y","New project enters behind carryforward projects","")) | CA81: =_xludf.RANK.EQ(Rule_Flags!O80,Rule_Flags!$O$3:$O$402,0) | CB81: =IF(OR(BU81="Determination Notice Issued",BU81="Board",BU81="Closed"),"Y","N") | CC81: construction_type mapped from raw 'NC' to 'New Construction' | CD81: Derek Hays | CE81: (317) 506-6537 | CF81: dhays@theannexgrp.com | CG81: Timothy Alcott | CH81: (210) 477-6633
A82: 2026-02-10 | B82: 2026-02-10 | C82: 25490 | E82: Aster Villas Apartments | F82: Pharr | G82: Hidalgo | H82: 11 | I82: 102 Polk Ave | J82: 78577 | K82: 45908 | L82: Withdrawn | M82: 46002 | O82: 45866 | P82: 46046 | R82: New Construction | S82: Elderly | T82: 196 | U82: 196 | X82: Pharr HFC | Y82: Local HFC | Z82: 37000000 | AB82: 1794968 | AF82: N | AG82: Y | AI82: Y | AK82: Y | AL82: Y | AM82: Y | AS82: N | AX82: N | AY82: Y | AZ82: Y | BA82: Y | BB82: Y | BC82: Y | BE82: N | BJ82: Y | BK82: N | BL82: N | BM82: Y | BN82: Y | BO82: 45908 | BP82: N | BQ82: Y | BR82: =IF(COUNTIF(AI82:BM82,"N")+COUNTBLANK(AI82:BM82)=0,"Y","N") | BS82: =IF(AND(BR82="Y",OR(L82="Submitted",L82="Under Review")),"Y",IF(L82="Closed","Y","N")) | BT82: 77 | BU82: =Rule_Flags!Q81 | BV82: =Rule_Flags!P81 | BW82: =IF(Rule_Flags!E81=1,"SITE_CONTROL",IF(Rule_Flags!F81=1,"APPROVALS",IF(Rule_Flags!G81=1,"REPORTS",IF(Rule_Flags!H81=1,"DEFICIENCY",IF(Rule_Flags!I81=1,"UNDERWRITING",IF(Rule_Flags!J81=1,"COMPLIANCE","")))))) | BX82: =IF(BW82="SITE_CONTROL","Site control missing or invalid",IF(BW82="APPROVALS","Required approvals or resolutions incomplete",IF(BW82="REPORTS","Required third-party reports incomplete",IF(BW82="DEFICIENCY","Unresolved deficiency or material deficiency",IF(BW82="UNDERWRITING","Underwriting / feasibility not passed",IF(BW82="COMPLIANCE","Deconcentration, one-mile, LURA, or Chapter 12 issue","Ready under current engine rules")))))) | BY82: =IF(BV82="Determination Notice","Streamlined + DN-ready assumptions satisfied",IF(BV82="Board","Board-required or board-ready assumptions satisfied","")) | BZ82: =IF(AND(BP82="Y",BQ82<>"Y"),"Carryforward project retains queue priority",IF(BQ82="Y","New project enters behind carryforward projects","")) | CA82: =_xludf.RANK.EQ(Rule_Flags!O81,Rule_Flags!$O$3:$O$402,0) | CB82: =IF(OR(BU82="Determination Notice Issued",BU82="Board",BU82="Closed"),"Y","N") | CC82: construction_type mapped from raw 'NC' to 'New Construction' | CD82: Lazaro Guerra | CE82: (956) 787-1822 | CF82: lazaro.guerra@pharrha.org | CG82: Lazaro Guerra | CH82: (956) 787-1822
A83: 2026-02-10 | B83: 2026-02-10 | C83: 25402 | E83: Tapestry at Katy | F83: Katy | G83: Harris | H83: 6 | I83: 5138 & 5202 Katy Hockley Road | J83: 77493 | K83: 45924 | L83: Approved | M83: 46037 | N83: 46001 | O83: 45884 | P83: 46064 | R83: New Construction | S83: General | T83: 360 | U83: 360 | X83: Harris County HFC | Y83: Local HFC | Z83: 50000000 | AB83: 3954296 | AC83: 3932722 | AF83: N | AG83: Y | AI83: Y | AK83: Y | AL83: Y | AM83: Y | AS83: N | AX83: N | AY83: Y | AZ83: Y | BA83: Y | BB83: Y | BC83: Y | BE83: N | BJ83: Y | BK83: N | BL83: N | BM83: Y | BN83: Y | BO83: 45924 | BP83: Y | BQ83: N | BR83: =IF(COUNTIF(AI83:BM83,"N")+COUNTBLANK(AI83:BM83)=0,"Y","N") | BS83: =IF(AND(BR83="Y",OR(L83="Submitted",L83="Under Review")),"Y",IF(L83="Closed","Y","N")) | BT83: 78 | BU83: =Rule_Flags!Q82 | BV83: =Rule_Flags!P82 | BW83: =IF(Rule_Flags!E82=1,"SITE_CONTROL",IF(Rule_Flags!F82=1,"APPROVALS",IF(Rule_Flags!G82=1,"REPORTS",IF(Rule_Flags!H82=1,"DEFICIENCY",IF(Rule_Flags!I82=1,"UNDERWRITING",IF(Rule_Flags!J82=1,"COMPLIANCE","")))))) | BX83: =IF(BW83="SITE_CONTROL","Site control missing or invalid",IF(BW83="APPROVALS","Required approvals or resolutions incomplete",IF(BW83="REPORTS","Required third-party reports incomplete",IF(BW83="DEFICIENCY","Unresolved deficiency or material deficiency",IF(BW83="UNDERWRITING","Underwriting / feasibility not passed",IF(BW83="COMPLIANCE","Deconcentration, one-mile, LURA, or Chapter 12 issue","Ready under current engine rules")))))) | BY83: =IF(BV83="Determination Notice","Streamlined + DN-ready assumptions satisfied",IF(BV83="Board","Board-required or board-ready assumptions satisfied","")) | BZ83: =IF(AND(BP83="Y",BQ83<>"Y"),"Carryforward project retains queue priority",IF(BQ83="Y","New project enters behind carryforward projects","")) | CA83: =_xludf.RANK.EQ(Rule_Flags!O82,Rule_Flags!$O$3:$O$402,0) | CB83: =IF(OR(BU83="Determination Notice Issued",BU83="Board",BU83="Closed"),"Y","N") | CC83: construction_type mapped from raw 'NC' to 'New Construction' | CD83: Mark Gregg | CE83: (210) 771-4127 | CF83: mgregg@streamlineap.com | CG83: Rene Martinez | CH83: (832) 927-4955
A84: 2026-02-10 | B84: 2026-02-10 | C84: 24499/25419 | E84: Belmont Apartments | F84: Austin | G84: Travis | H84: 7 | I84: 4401 East Slaughter Lane | J84: 78747 | K84: 45926 | L84: Approved | M84: 46037 | N84: 46050 | O84: 45904 | P84: 46084 | R84: New Construction | S84: General | T84: 348 | U84: 348 | X84: Travis County Facilities Corporation | Y84: Other | Z84: 60000000 | AB84: 3206071 | AC84: 3206071 | AF84: N | AG84: Y | AI84: Y | AK84: Y | AL84: Y | AM84: Y | AS84: N | AX84: N | AY84: Y | AZ84: Y | BA84: Y | BB84: Y | BC84: Y | BE84: N | BJ84: Y | BK84: N | BL84: N | BM84: Y | BN84: Y | BO84: 45926 | BP84: N | BQ84: Y | BR84: =IF(COUNTIF(AI84:BM84,"N")+COUNTBLANK(AI84:BM84)=0,"Y","N") | BS84: =IF(AND(BR84="Y",OR(L84="Submitted",L84="Under Review")),"Y",IF(L84="Closed","Y","N")) | BT84: 79 | BU84: =Rule_Flags!Q83 | BV84: =Rule_Flags!P83 | BW84: =IF(Rule_Flags!E83=1,"SITE_CONTROL",IF(Rule_Flags!F83=1,"APPROVALS",IF(Rule_Flags!G83=1,"REPORTS",IF(Rule_Flags!H83=1,"DEFICIENCY",IF(Rule_Flags!I83=1,"UNDERWRITING",IF(Rule_Flags!J83=1,"COMPLIANCE","")))))) | BX84: =IF(BW84="SITE_CONTROL","Site control missing or invalid",IF(BW84="APPROVALS","Required approvals or resolutions incomplete",IF(BW84="REPORTS","Required third-party reports incomplete",IF(BW84="DEFICIENCY","Unresolved deficiency or material deficiency",IF(BW84="UNDERWRITING","Underwriting / feasibility not passed",IF(BW84="COMPLIANCE","Deconcentration, one-mile, LURA, or Chapter 12 issue","Ready under current engine rules")))))) | BY84: =IF(BV84="Determination Notice","Streamlined + DN-ready assumptions satisfied",IF(BV84="Board","Board-required or board-ready assumptions satisfied","")) | BZ84: =IF(AND(BP84="Y",BQ84<>"Y"),"Carryforward project retains queue priority",IF(BQ84="Y","New project enters behind carryforward projects","")) | CA84: =_xludf.RANK.EQ(Rule_Flags!O83,Rule_Flags!$O$3:$O$402,0) | CB84: =IF(OR(BU84="Determination Notice Issued",BU84="Board",BU84="Closed"),"Y","N") | CC84: construction_type mapped from raw 'NC' to 'New Construction' | CD84: Anne Tyler | CE84: (440) 773-7850 | CF84: atyler@nrpgroup.com | CG84: Patrick Howard | CH84: (512) 854-1885
A85: 2026-02-10 | B85: 2026-02-10 | C85: 25610 | E85: South 1st Affordable Apartments | F85: Austin | G85: Travis | H85: 7 | I85: 714 Turtle Creek Boulevard | J85: 78745 | K85: 45931 | L85: Pre-Application | M85: TBD | O85: TBD | P85: TBD | R85: Acq/Rehab | S85: General | T85: 125 | U85: 125 | X85: TDHCA | Y85: TDHCA | Z85: 20000000 | AB85: 1285218 | AF85: N | AG85: Y | AI85: Y | AK85: Y | AL85: Y | AM85: Y | AS85: N | AX85: N | AY85: Y | AZ85: Y | BA85: Y | BB85: Y | BC85: Y | BE85: N | BJ85: Y | BK85: N | BL85: N | BM85: Y | BN85: Y | BO85: 45931 | BP85: N | BQ85: Y | BR85: =IF(COUNTIF(AI85:BM85,"N")+COUNTBLANK(AI85:BM85)=0,"Y","N") | BS85: =IF(AND(BR85="Y",OR(L85="Submitted",L85="Under Review")),"Y",IF(L85="Closed","Y","N")) | BT85: 80 | BU85: =Rule_Flags!Q84 | BV85: =Rule_Flags!P84 | BW85: =IF(Rule_Flags!E84=1,"SITE_CONTROL",IF(Rule_Flags!F84=1,"APPROVALS",IF(Rule_Flags!G84=1,"REPORTS",IF(Rule_Flags!H84=1,"DEFICIENCY",IF(Rule_Flags!I84=1,"UNDERWRITING",IF(Rule_Flags!J84=1,"COMPLIANCE","")))))) | BX85: =IF(BW85="SITE_CONTROL","Site control missing or invalid",IF(BW85="APPROVALS","Required approvals or resolutions incomplete",IF(BW85="REPORTS","Required third-party reports incomplete",IF(BW85="DEFICIENCY","Unresolved deficiency or material deficiency",IF(BW85="UNDERWRITING","Underwriting / feasibility not passed",IF(BW85="COMPLIANCE","Deconcentration, one-mile, LURA, or Chapter 12 issue","Ready under current engine rules")))))) | BY85: =IF(BV85="Determination Notice","Streamlined + DN-ready assumptions satisfied",IF(BV85="Board","Board-required or board-ready assumptions satisfied","")) | BZ85: =IF(AND(BP85="Y",BQ85<>"Y"),"Carryforward project retains queue priority",IF(BQ85="Y","New project enters behind carryforward projects","")) | CA85: =_xludf.RANK.EQ(Rule_Flags!O84,Rule_Flags!$O$3:$O$402,0) | CB85: =IF(OR(BU85="Determination Notice Issued",BU85="Board",BU85="Closed"),"Y","N") | CC85: property_tax_exemption normalized from 'Y(50%)' to 'Y' | CD85: Anthony Clark | CE85: (512) 502-2032 | CF85: anthony@narrowroad.com | CG85: Teresa Morales | CH85: (512) 475-3344
A86: 2026-02-10 | B86: 2026-02-10 | C86: 25491 | E86: Avanti Hills | F86: Mesquite | G86: Dallas | H86: 3 | I86: NWQ E Glen Blvd & Clay Mathis Road | J86: 75181 | K86: 45932 | L86: Approved | M86: 46037 | N86: 46034 | O86: 46049 | P86: 46229 | R86: New Construction | S86: Elderly | T86: 260 | U86: 260 | X86: The Mesquite HFC | Y86: Local HFC | Z86: 60000000 | AB86: 3525639 | AC86: 3497922 | AF86: N | AG86: Y | AI86: Y | AK86: Y | AL86: Y | AM86: Y | AS86: N | AX86: N | AY86: Y | AZ86: Y | BA86: Y | BB86: Y | BC86: Y | BE86: N | BJ86: Y | BK86: N | BL86: N | BM86: Y | BN86: Y | BO86: 45932 | BP86: N | BQ86: Y | BR86: =IF(COUNTIF(AI86:BM86,"N")+COUNTBLANK(AI86:BM86)=0,"Y","N") | BS86: =IF(AND(BR86="Y",OR(L86="Submitted",L86="Under Review")),"Y",IF(L86="Closed","Y","N")) | BT86: 81 | BU86: =Rule_Flags!Q85 | BV86: =Rule_Flags!P85 | BW86: =IF(Rule_Flags!E85=1,"SITE_CONTROL",IF(Rule_Flags!F85=1,"APPROVALS",IF(Rule_Flags!G85=1,"REPORTS",IF(Rule_Flags!H85=1,"DEFICIENCY",IF(Rule_Flags!I85=1,"UNDERWRITING",IF(Rule_Flags!J85=1,"COMPLIANCE","")))))) | BX86: =IF(BW86="SITE_CONTROL","Site control missing or invalid",IF(BW86="APPROVALS","Required approvals or resolutions incomplete",IF(BW86="REPORTS","Required third-party reports incomplete",IF(BW86="DEFICIENCY","Unresolved deficiency or material deficiency",IF(BW86="UNDERWRITING","Underwriting / feasibility not passed",IF(BW86="COMPLIANCE","Deconcentration, one-mile, LURA, or Chapter 12 issue","Ready under current engine rules")))))) | BY86: =IF(BV86="Determination Notice","Streamlined + DN-ready assumptions satisfied",IF(BV86="Board","Board-required or board-ready assumptions satisfied","")) | BZ86: =IF(AND(BP86="Y",BQ86<>"Y"),"Carryforward project retains queue priority",IF(BQ86="Y","New project enters behind carryforward projects","")) | CA86: =_xludf.RANK.EQ(Rule_Flags!O85,Rule_Flags!$O$3:$O$402,0) | CB86: =IF(OR(BU86="Determination Notice Issued",BU86="Board",BU86="Closed"),"Y","N") | CC86: construction_type mapped from raw 'NC' to 'New Construction' | CD86: CJ Lintner | CE86: (317) 502-9239 | CF86: clintner@kcgcompanies.com | CG86: Ted Chinn | CH86: (972) 216-6287
A87: 2026-02-10 | B87: 2026-02-10 | C87: 25477 | E87: Torrington Forest | F87: Dallas | G87: Dallas | H87: 3 | I87: 7100 Great Trinity Forest Way | J87: 75217 | K87: 45936 | L87: Approved | M87: 46037 | N87: 46034 | O87: 46057 | P87: 46092 | R87: New Construction | S87: General | T87: 248 | U87: 248 | X87: City of Dallas HFC | Y87: Local HFC | Z87: 40000000 | AB87: 3408255 | AC87: 3280417 | AF87: N | AG87: Y | AI87: Y | AK87: Y | AL87: Y | AM87: Y | AS87: N | AX87: N | AY87: Y | AZ87: Y | BA87: Y | BB87: Y | BC87: Y | BE87: N | BJ87: Y | BK87: N | BL87: N | BM87: Y | BN87: Y | BO87: 45936 | BP87: N | BQ87: Y | BR87: =IF(COUNTIF(AI87:BM87,"N")+COUNTBLANK(AI87:BM87)=0,"Y","N") | BS87: =IF(AND(BR87="Y",OR(L87="Submitted",L87="Under Review")),"Y",IF(L87="Closed","Y","N")) | BT87: 82 | BU87: =Rule_Flags!Q86 | BV87: =Rule_Flags!P86 | BW87: =IF(Rule_Flags!E86=1,"SITE_CONTROL",IF(Rule_Flags!F86=1,"APPROVALS",IF(Rule_Flags!G86=1,"REPORTS",IF(Rule_Flags!H86=1,"DEFICIENCY",IF(Rule_Flags!I86=1,"UNDERWRITING",IF(Rule_Flags!J86=1,"COMPLIANCE","")))))) | BX87: =IF(BW87="SITE_CONTROL","Site control missing or invalid",IF(BW87="APPROVALS","Required approvals or resolutions incomplete",IF(BW87="REPORTS","Required third-party reports incomplete",IF(BW87="DEFICIENCY","Unresolved deficiency or material deficiency",IF(BW87="UNDERWRITING","Underwriting / feasibility not passed",IF(BW87="COMPLIANCE","Deconcentration, one-mile, LURA, or Chapter 12 issue","Ready under current engine rules")))))) | BY87: =IF(BV87="Determination Notice","Streamlined + DN-ready assumptions satisfied",IF(BV87="Board","Board-required or board-ready assumptions satisfied","")) | BZ87: =IF(AND(BP87="Y",BQ87<>"Y"),"Carryforward project retains queue priority",IF(BQ87="Y","New project enters behind carryforward projects","")) | CA87: =_xludf.RANK.EQ(Rule_Flags!O86,Rule_Flags!$O$3:$O$402,0) | CB87: =IF(OR(BU87="Determination Notice Issued",BU87="Board",BU87="Closed"),"Y","N") | CC87: construction_type mapped from raw 'NC' to 'New Construction' | CD87: Karsten Lowe | CE87: (210) 493-8633 | CF87: Karsten.Lowe@jpi.com | CG87: Aaron Eaquinto | CH87: (469) 799-2670
A88: 2026-02-10 | B88: 2026-02-10 | C88: 25494 | E88: Lakeside Lofts | F88: San Antonio | G88: Bexar | H88: 9 | I88: 5606 US Highway 87 E | J88: 78222 | K88: 45936 | L88: Approved | M88: 46037 | N88: 46010 | O88: 46057 | P88: 46092 | R88: New Construction | S88: General | T88: 336 | U88: 336 | X88: Las Varas PFC | Y88: Other | Z88: 45000000 | AB88: 3512745 | AC88: 3512745 | AF88: N | AG88: Y | AH88: Y | AI88: Y | AK88: Y | AL88: Y | AM88: Y | AS88: N | AX88: N | AY88: Y | AZ88: Y | BA88: Y | BB88: Y | BC88: Y | BE88: N | BJ88: Y | BK88: N | BL88: N | BM88: Y | BN88: Y | BO88: 45936 | BP88: N | BQ88: Y | BR88: =IF(COUNTIF(AI88:BM88,"N")+COUNTBLANK(AI88:BM88)=0,"Y","N") | BS88: =IF(AND(BR88="Y",OR(L88="Submitted",L88="Under Review")),"Y",IF(L88="Closed","Y","N")) | BT88: 83 | BU88: =Rule_Flags!Q87 | BV88: =Rule_Flags!P87 | BW88: =IF(Rule_Flags!E87=1,"SITE_CONTROL",IF(Rule_Flags!F87=1,"APPROVALS",IF(Rule_Flags!G87=1,"REPORTS",IF(Rule_Flags!H87=1,"DEFICIENCY",IF(Rule_Flags!I87=1,"UNDERWRITING",IF(Rule_Flags!J87=1,"COMPLIANCE","")))))) | BX88: =IF(BW88="SITE_CONTROL","Site control missing or invalid",IF(BW88="APPROVALS","Required approvals or resolutions incomplete",IF(BW88="REPORTS","Required third-party reports incomplete",IF(BW88="DEFICIENCY","Unresolved deficiency or material deficiency",IF(BW88="UNDERWRITING","Underwriting / feasibility not passed",IF(BW88="COMPLIANCE","Deconcentration, one-mile, LURA, or Chapter 12 issue","Ready under current engine rules")))))) | BY88: =IF(BV88="Determination Notice","Streamlined + DN-ready assumptions satisfied",IF(BV88="Board","Board-required or board-ready assumptions satisfied","")) | BZ88: =IF(AND(BP88="Y",BQ88<>"Y"),"Carryforward project retains queue priority",IF(BQ88="Y","New project enters behind carryforward projects","")) | CA88: =_xludf.RANK.EQ(Rule_Flags!O87,Rule_Flags!$O$3:$O$402,0) | CB88: =IF(OR(BU88="Determination Notice Issued",BU88="Board",BU88="Closed"),"Y","N") | CC88: construction_type mapped from raw 'NC' to 'New Construction' | CD88: Jason Arechiga | CE88: (210) 216-4600 | CF88: jarechiga@nrpgroup.com | CG88: Timothy Alcott | CH88: (210) 477-6633
A89: 2026-02-10 | B89: 2026-02-10 | C89: 25487 | D89: 00011 | E89: Heritage Oaks | F89: Kerrville | G89: Kerr | H89: 9 | I89: 2350 Junction Hwy | J89: 78028 | K89: 45938 | L89: Approved | M89: 46037 | N89: 46056 | O89: 45890 | P89: 46070 | R89: Acq/Rehab | S89: General | T89: 76 | U89: 76 | X89: Alamo Area PFC | Y89: Other | Z89: 22000000 | AB89: 709033 | AC89: 709033 | AF89: N | AG89: Y | AH89: Y | AI89: Y | AK89: Y | AL89: Y | AM89: Y | AS89: N | AX89: N | AY89: Y | AZ89: Y | BA89: Y | BB89: Y | BC89: Y | BE89: N | BJ89: Y | BK89: N | BL89: N | BM89: Y | BN89: Y | BO89: 45938 | BP89: N | BQ89: Y | BR89: =IF(COUNTIF(AI89:BM89,"N")+COUNTBLANK(AI89:BM89)=0,"Y","N") | BS89: =IF(AND(BR89="Y",OR(L89="Submitted",L89="Under Review")),"Y",IF(L89="Closed","Y","N")) | BT89: 84 | BU89: =Rule_Flags!Q88 | BV89: =Rule_Flags!P88 | BW89: =IF(Rule_Flags!E88=1,"SITE_CONTROL",IF(Rule_Flags!F88=1,"APPROVALS",IF(Rule_Flags!G88=1,"REPORTS",IF(Rule_Flags!H88=1,"DEFICIENCY",IF(Rule_Flags!I88=1,"UNDERWRITING",IF(Rule_Flags!J88=1,"COMPLIANCE","")))))) | BX89: =IF(BW89="SITE_CONTROL","Site control missing or invalid",IF(BW89="APPROVALS","Required approvals or resolutions incomplete",IF(BW89="REPORTS","Required third-party reports incomplete",IF(BW89="DEFICIENCY","Unresolved deficiency or material deficiency",IF(BW89="UNDERWRITING","Underwriting / feasibility not passed",IF(BW89="COMPLIANCE","Deconcentration, one-mile, LURA, or Chapter 12 issue","Ready under current engine rules")))))) | BY89: =IF(BV89="Determination Notice","Streamlined + DN-ready assumptions satisfied",IF(BV89="Board","Board-required or board-ready assumptions satisfied","")) | BZ89: =IF(AND(BP89="Y",BQ89<>"Y"),"Carryforward project retains queue priority",IF(BQ89="Y","New project enters behind carryforward projects","")) | CA89: =_xludf.RANK.EQ(Rule_Flags!O88,Rule_Flags!$O$3:$O$402,0) | CB89: =IF(OR(BU89="Determination Notice Issued",BU89="Board",BU89="Closed"),"Y","N") | CC89: property_tax_exemption normalized from 'Y (50%)' to 'Y' | CD89: Lisa Toler | CE89: (334) 954-4458 | CF89: lisa.toler@envolvellc.com | CG89: Clifford Herberg | CH89: (210) 362-5200
A90: 2026-02-10 | B90: 2026-02-10 | C90: 25488 | D90: 07242/08935 | E90: Paseo de Paz | F90: Kerrville | G90: Kerr | H90: 9 | I90: 401 Clearwater Paseo | J90: 78028 | K90: 45938 | L90: Approved | M90: 46037 | N90: 46056 | O90: 45890 | P90: 46070 | R90: Acq/Rehab | S90: General | T90: 76 | U90: 76 | X90: Alamo Area PFC | Y90: Other | Z90: 22000000 | AB90: 568048 | AC90: 568048 | AF90: N | AG90: Y | AH90: Y | AI90: Y | AK90: Y | AL90: Y | AM90: Y | AS90: N | AX90: N | AY90: Y | AZ90: Y | BA90: Y | BB90: Y | BC90: Y | BE90: N | BJ90: Y | BK90: N | BL90: N | BM90: Y | BN90: Y | BO90: 45938 | BP90: N | BQ90: Y | BR90: =IF(COUNTIF(AI90:BM90,"N")+COUNTBLANK(AI90:BM90)=0,"Y","N") | BS90: =IF(AND(BR90="Y",OR(L90="Submitted",L90="Under Review")),"Y",IF(L90="Closed","Y","N")) | BT90: 85 | BU90: =Rule_Flags!Q89 | BV90: =Rule_Flags!P89 | BW90: =IF(Rule_Flags!E89=1,"SITE_CONTROL",IF(Rule_Flags!F89=1,"APPROVALS",IF(Rule_Flags!G89=1,"REPORTS",IF(Rule_Flags!H89=1,"DEFICIENCY",IF(Rule_Flags!I89=1,"UNDERWRITING",IF(Rule_Flags!J89=1,"COMPLIANCE","")))))) | BX90: =IF(BW90="SITE_CONTROL","Site control missing or invalid",IF(BW90="APPROVALS","Required approvals or resolutions incomplete",IF(BW90="REPORTS","Required third-party reports incomplete",IF(BW90="DEFICIENCY","Unresolved deficiency or material deficiency",IF(BW90="UNDERWRITING","Underwriting / feasibility not passed",IF(BW90="COMPLIANCE","Deconcentration, one-mile, LURA, or Chapter 12 issue","Ready under current engine rules")))))) | BY90: =IF(BV90="Determination Notice","Streamlined + DN-ready assumptions satisfied",IF(BV90="Board","Board-required or board-ready assumptions satisfied","")) | BZ90: =IF(AND(BP90="Y",BQ90<>"Y"),"Carryforward project retains queue priority",IF(BQ90="Y","New project enters behind carryforward projects","")) | CA90: =_xludf.RANK.EQ(Rule_Flags!O89,Rule_Flags!$O$3:$O$402,0) | CB90: =IF(OR(BU90="Determination Notice Issued",BU90="Board",BU90="Closed"),"Y","N") | CC90: property_tax_exemption normalized from 'Y (50%)' to 'Y' | CD90: Lisa Toler | CE90: (334) 954-4458 | CF90: lisa.toler@envolvellc.com | CG90: Clifford Herberg | CH90: (210) 362-5200
A91: 2026-02-10 | B91: 2026-02-10 | C91: 25489 | D91: 98156 | E91: The Meadows | F91: Kerrville | G91: Kerr | H91: 9 | I91: 2300 Junction Hwy | J91: 78028 | K91: 45938 | L91: Approved | M91: 46037 | N91: 46056 | O91: 45890 | P91: 46070 | R91: Acq/Rehab | S91: General | T91: 72 | U91: 72 | X91: Alamo Area PFC | Y91: Other | Z91: 22000000 | AB91: 597966 | AC91: 597966 | AF91: N | AG91: Y | AH91: Y | AI91: Y | AK91: Y | AL91: Y | AM91: Y | AS91: N | AX91: N | AY91: Y | AZ91: Y | BA91: Y | BB91: Y | BC91: Y | BE91: N | BJ91: Y | BK91: N | BL91: N | BM91: Y | BN91: Y | BO91: 45938 | BP91: N | BQ91: Y | BR91: =IF(COUNTIF(AI91:BM91,"N")+COUNTBLANK(AI91:BM91)=0,"Y","N") | BS91: =IF(AND(BR91="Y",OR(L91="Submitted",L91="Under Review")),"Y",IF(L91="Closed","Y","N")) | BT91: 86 | BU91: =Rule_Flags!Q90 | BV91: =Rule_Flags!P90 | BW91: =IF(Rule_Flags!E90=1,"SITE_CONTROL",IF(Rule_Flags!F90=1,"APPROVALS",IF(Rule_Flags!G90=1,"REPORTS",IF(Rule_Flags!H90=1,"DEFICIENCY",IF(Rule_Flags!I90=1,"UNDERWRITING",IF(Rule_Flags!J90=1,"COMPLIANCE","")))))) | BX91: =IF(BW91="SITE_CONTROL","Site control missing or invalid",IF(BW91="APPROVALS","Required approvals or resolutions incomplete",IF(BW91="REPORTS","Required third-party reports incomplete",IF(BW91="DEFICIENCY","Unresolved deficiency or material deficiency",IF(BW91="UNDERWRITING","Underwriting / feasibility not passed",IF(BW91="COMPLIANCE","Deconcentration, one-mile, LURA, or Chapter 12 issue","Ready under current engine rules")))))) | BY91: =IF(BV91="Determination Notice","Streamlined + DN-ready assumptions satisfied",IF(BV91="Board","Board-required or board-ready assumptions satisfied","")) | BZ91: =IF(AND(BP91="Y",BQ91<>"Y"),"Carryforward project retains queue priority",IF(BQ91="Y","New project enters behind carryforward projects","")) | CA91: =_xludf.RANK.EQ(Rule_Flags!O90,Rule_Flags!$O$3:$O$402,0) | CB91: =IF(OR(BU91="Determination Notice Issued",BU91="Board",BU91="Closed"),"Y","N") | CC91: property_tax_exemption normalized from 'Y (50%)' to 'Y' | CD91: Lisa Toler | CE91: (334) 954-4458 | CF91: lisa.toler@envolvellc.com | CG91: Clifford Herberg | CH91: (210) 362-5200
A92: 2026-02-10 | B92: 2026-02-10 | C92: 25614 | E92: Lariat | F92: Mustang Ridge | G92: Travis | H92: 7 | I92: NEQ S Hwy 183 & Gunnison Grove Ave | J92: 78610 | K92: 45966 | L92: Withdrawn | M92: TBD | O92: TBD | P92: TBD | R92: New Construction | S92: General | T92: 264 | U92: 264 | X92: TDHCA | Y92: TDHCA | Z92: 50000000 | AB92: 4078838 | AF92: N | AG92: Y | AI92: Y | AK92: Y | AL92: Y | AM92: Y | AS92: N | AX92: N | AY92: Y | AZ92: Y | BA92: Y | BB92: Y | BC92: Y | BE92: N | BJ92: Y | BK92: N | BL92: N | BM92: Y | BN92: Y | BO92: 45966 | BP92: N | BQ92: Y | BR92: =IF(COUNTIF(AI92:BM92,"N")+COUNTBLANK(AI92:BM92)=0,"Y","N") | BS92: =IF(AND(BR92="Y",OR(L92="Submitted",L92="Under Review")),"Y",IF(L92="Closed","Y","N")) | BT92: 87 | BU92: =Rule_Flags!Q91 | BV92: =Rule_Flags!P91 | BW92: =IF(Rule_Flags!E91=1,"SITE_CONTROL",IF(Rule_Flags!F91=1,"APPROVALS",IF(Rule_Flags!G91=1,"REPORTS",IF(Rule_Flags!H91=1,"DEFICIENCY",IF(Rule_Flags!I91=1,"UNDERWRITING",IF(Rule_Flags!J91=1,"COMPLIANCE","")))))) | BX92: =IF(BW92="SITE_CONTROL","Site control missing or invalid",IF(BW92="APPROVALS","Required approvals or resolutions incomplete",IF(BW92="REPORTS","Required third-party reports incomplete",IF(BW92="DEFICIENCY","Unresolved deficiency or material deficiency",IF(BW92="UNDERWRITING","Underwriting / feasibility not passed",IF(BW92="COMPLIANCE","Deconcentration, one-mile, LURA, or Chapter 12 issue","Ready under current engine rules")))))) | BY92: =IF(BV92="Determination Notice","Streamlined + DN-ready assumptions satisfied",IF(BV92="Board","Board-required or board-ready assumptions satisfied","")) | BZ92: =IF(AND(BP92="Y",BQ92<>"Y"),"Carryforward project retains queue priority",IF(BQ92="Y","New project enters behind carryforward projects","")) | CA92: =_xludf.RANK.EQ(Rule_Flags!O91,Rule_Flags!$O$3:$O$402,0) | CB92: =IF(OR(BU92="Determination Notice Issued",BU92="Board",BU92="Closed"),"Y","N") | CC92: construction_type mapped from raw 'NC' to 'New Construction' | CD92: Jason Trevino | CE92: (512) 578-8488 | CF92: jtrevino@ldgdevelopment.com | CG92: Teresa Morales | CH92: (512) 475-3344
A93: 2026-02-10 | B93: 2026-02-10 | C93: 25482 | E93: Tapestry at Easton Park | F93: Austin | G93: Travis | H93: 7 | I93: 7504 Cota Vista Drive | J93: 78744 | K93: 45974 | L93: Withdrawn | M93: 46037 | O93: 45881 | P93: 46061 | R93: New Construction | S93: General | T93: 323 | U93: 323 | X93: Travis County HFC | Y93: Local HFC | Z93: 52000000 | AB93: 2955340 | AF93: N | AG93: Y | AI93: Y | AK93: Y | AL93: Y | AM93: Y | AS93: N | AX93: N | AY93: Y | AZ93: Y | BA93: Y | BB93: Y | BC93: Y | BE93: N | BJ93: Y | BK93: N | BL93: N | BM93: Y | BN93: Y | BO93: 45974 | BP93: N | BQ93: Y | BR93: =IF(COUNTIF(AI93:BM93,"N")+COUNTBLANK(AI93:BM93)=0,"Y","N") | BS93: =IF(AND(BR93="Y",OR(L93="Submitted",L93="Under Review")),"Y",IF(L93="Closed","Y","N")) | BT93: 88 | BU93: =Rule_Flags!Q92 | BV93: =Rule_Flags!P92 | BW93: =IF(Rule_Flags!E92=1,"SITE_CONTROL",IF(Rule_Flags!F92=1,"APPROVALS",IF(Rule_Flags!G92=1,"REPORTS",IF(Rule_Flags!H92=1,"DEFICIENCY",IF(Rule_Flags!I92=1,"UNDERWRITING",IF(Rule_Flags!J92=1,"COMPLIANCE","")))))) | BX93: =IF(BW93="SITE_CONTROL","Site control missing or invalid",IF(BW93="APPROVALS","Required approvals or resolutions incomplete",IF(BW93="REPORTS","Required third-party reports incomplete",IF(BW93="DEFICIENCY","Unresolved deficiency or material deficiency",IF(BW93="UNDERWRITING","Underwriting / feasibility not passed",IF(BW93="COMPLIANCE","Deconcentration, one-mile, LURA, or Chapter 12 issue","Ready under current engine rules")))))) | BY93: =IF(BV93="Determination Notice","Streamlined + DN-ready assumptions satisfied",IF(BV93="Board","Board-required or board-ready assumptions satisfied","")) | BZ93: =IF(AND(BP93="Y",BQ93<>"Y"),"Carryforward project retains queue priority",IF(BQ93="Y","New project enters behind carryforward projects","")) | CA93: =_xludf.RANK.EQ(Rule_Flags!O92,Rule_Flags!$O$3:$O$402,0) | CB93: =IF(OR(BU93="Determination Notice Issued",BU93="Board",BU93="Closed"),"Y","N") | CC93: construction_type mapped from raw 'NC' to 'New Construction' | CD93: Mark Gregg | CE93: (210) 771-4127 | CF93: mgregg@streamlineap.com | CG93: Andy Brown | CH93: (512) 854‐9555
A94: 2026-02-10 | B94: 2026-02-10 | C94: 25615 | E94: Mela Ranch | F94: Cleburne | G94: Johnson | H94: 3 | I94: 427 N. Hyde Park Boulevard | J94: 76033 | K94: 45987 | L94: Pre-Application | M94: TBD | O94: TBD | P94: TBD | R94: New Construction | S94: General | T94: 280 | U94: 280 | X94: TDHCA | Y94: TDHCA | Z94: 31000000 | AB94: 2865362 | AF94: N | AG94: Y | AI94: Y | AK94: Y | AL94: Y | AM94: Y | AS94: N | AX94: N | AY94: Y | AZ94: Y | BA94: Y | BB94: Y | BC94: Y | BE94: N | BJ94: Y | BK94: N | BL94: N | BM94: Y | BN94: Y | BO94: 45987 | BP94: N | BQ94: Y | BR94: =IF(COUNTIF(AI94:BM94,"N")+COUNTBLANK(AI94:BM94)=0,"Y","N") | BS94: =IF(AND(BR94="Y",OR(L94="Submitted",L94="Under Review")),"Y",IF(L94="Closed","Y","N")) | BT94: 89 | BU94: =Rule_Flags!Q93 | BV94: =Rule_Flags!P93 | BW94: =IF(Rule_Flags!E93=1,"SITE_CONTROL",IF(Rule_Flags!F93=1,"APPROVALS",IF(Rule_Flags!G93=1,"REPORTS",IF(Rule_Flags!H93=1,"DEFICIENCY",IF(Rule_Flags!I93=1,"UNDERWRITING",IF(Rule_Flags!J93=1,"COMPLIANCE","")))))) | BX94: =IF(BW94="SITE_CONTROL","Site control missing or invalid",IF(BW94="APPROVALS","Required approvals or resolutions incomplete",IF(BW94="REPORTS","Required third-party reports incomplete",IF(BW94="DEFICIENCY","Unresolved deficiency or material deficiency",IF(BW94="UNDERWRITING","Underwriting / feasibility not passed",IF(BW94="COMPLIANCE","Deconcentration, one-mile, LURA, or Chapter 12 issue","Ready under current engine rules")))))) | BY94: =IF(BV94="Determination Notice","Streamlined + DN-ready assumptions satisfied",IF(BV94="Board","Board-required or board-ready assumptions satisfied","")) | BZ94: =IF(AND(BP94="Y",BQ94<>"Y"),"Carryforward project retains queue priority",IF(BQ94="Y","New project enters behind carryforward projects","")) | CA94: =_xludf.RANK.EQ(Rule_Flags!O93,Rule_Flags!$O$3:$O$402,0) | CB94: =IF(OR(BU94="Determination Notice Issued",BU94="Board",BU94="Closed"),"Y","N") | CC94: construction_type mapped from raw 'NC' to 'New Construction' | CD94: Jerod Mund | CE94: (817) 300-9838 | CF94: jmund00@gmail.com | CG94: Teresa Morales | CH94: (512) 473-3344
E95: Jimbo's Apartment | F95: Houston | R95: New Construction | T95: 100 | AB95: 10 | AI95: Y | AK95: Y | AL95: Y | AM95: Y | AS95: N | AX95: N | AY95: Y | AZ95: Y | BA95: Y | BB95: Y | BC95: Y | BE95: N | BJ95: Y | BK95: N | BL95: N | BM95: Y | BN95: Y | BP95: N | BQ95: Y | BR95: =IF(COUNTIF(AI95:BM95,"N")+COUNTBLANK(AI95:BM95)=0,"Y","N") | BS95: =IF(AND(BR95="Y",OR(L95="Submitted",L95="Under Review")),"Y",IF(L95="Closed","Y","N")) | BU95: =IF(L95="Closed","Closed",IF(OR(L95="Withdrawn",L95="Terminated"),L95,IF(OR(AI95="N",AI95="",AK95="N",AK95="",AL95="N",AL95="",AM95="N",AM95="",AX95="Y",AND(AS95="Y",AV95<>"Y"),AZ95="N",AZ95="",BA95="N",BA95="",BB95="N",BB95="",BC95="N",BE95="Y",BL95="Y"),"No Advancement",IF(AND(BJ95="Y",BM95="Y",BK95<>"Y"),"Determination Notice Issued",IF(OR(BN95="Y",BK95="Y"),"Board","Under Review"))))) | BV95: =IF(BU95="Determination Notice Issued","Determination Notice",IF(BU95="Board","Board",IF(BU95="No Advancement","Blocked","Under Review"))) | BW95: =IF(OR(AI95="N",AI95=""),"SITE_CONTROL",IF(OR(AK95="N",AK95="",AL95="N",AL95=""),"APPROVALS",IF(OR(AM95="N",AM95=""),"REPORTS",IF(OR(AX95="Y",AND(AS95="Y",AV95<>"Y")),"DEFICIENCY",IF(OR(AZ95="N",AZ95="",BA95="N",BA95=""),"UNDERWRITING",IF(OR(BB95="N",BB95="",BC95="N",BE95="Y",BL95="Y"),"COMPLIANCE","")))))) | BX95: =IF(BW95="","Ready under current engine rules",BW95) | CA95: =1 | CB95: =IF(OR(BU95="Determination Notice Issued",BU95="Board",BU95="Closed"),"Y","N")
BR96: =IF(COUNTIF(AI96:BM96,"N")+COUNTBLANK(AI96:BM96)=0,"Y","N") | BS96: =IF(AND(BR96="Y",OR(L96="Submitted",L96="Under Review")),"Y",IF(L96="Closed","Y","N")) | BU96: =Rule_Flags!Q95 | BV96: =Rule_Flags!P95 | BW96: =IF(Rule_Flags!E95=1,"SITE_CONTROL",IF(Rule_Flags!F95=1,"APPROVALS",IF(Rule_Flags!G95=1,"REPORTS",IF(Rule_Flags!H95=1,"DEFICIENCY",IF(Rule_Flags!I95=1,"UNDERWRITING",IF(Rule_Flags!J95=1,"COMPLIANCE","")))))) | BX96: =IF(BW96="SITE_CONTROL","Site control missing or invalid",IF(BW96="APPROVALS","Required approvals or resolutions incomplete",IF(BW96="REPORTS","Required third-party reports incomplete",IF(BW96="DEFICIENCY","Unresolved deficiency or material deficiency",IF(BW96="UNDERWRITING","Underwriting / feasibility not passed",IF(BW96="COMPLIANCE","Deconcentration, one-mile, LURA, or Chapter 12 issue","Ready under current engine rules")))))) | BY96: =IF(BV96="Determination Notice","Streamlined + DN-ready assumptions satisfied",IF(BV96="Board","Board-required or board-ready assumptions satisfied","")) | BZ96: =IF(AND(BP96="Y",BQ96<>"Y"),"Carryforward project retains queue priority",IF(BQ96="Y","New project enters behind carryforward projects","")) | CA96: =_xludf.RANK.EQ(Rule_Flags!O95,Rule_Flags!$O$3:$O$402,0) | CB96: =IF(OR(BU96="Determination Notice Issued",BU96="Board",BU96="Closed"),"Y","N")
